Workbook
Name all_subsystems: '[1]Служебный ОП'!$A$3:$A$22
Name all_subsystems: '[1]Служебный ОП'!$A$3:$A$22
Name all_subsystems: '[2]Служебный ОП'!$A$3:$A$22
Name ASUTP_APMDZ: '[3]Служебный АСУТП'!$N$2:$N$3
Name ASUTP_APMDZ: 'Служебный АСУТП'!$N$2:$N$3
Name ASUTP_APT: '[4]Служебный АСУТП'!$Z$2:$Z$4
Name ASUTP_APT: '[3]Служебный АСУТП'!$AA$2:$AA$4
Name ASUTP_APT: '[4]Служебный АСУТП'!$Z$2:$Z$4
Name ASUTP_APT: 'Служебный АСУТП'!$AA$2:$AA$4
Name ASUTP_AVZ: '[5]Служебный АСУТП'!$E$2
Name ASUTP_AVZ: '[6]Служебный АСУТП'!$E$2:$E$9
Name ASUTP_AVZ: '[4]Служебный АСУТП'!$E$2:$E$9
Name ASUTP_AVZ: '[7]Служебный АСУТП'!$E$2:$E$5
Name ASUTP_AVZ: '[3]Служебный АСУТП'!$E$2:$E$9
Name ASUTP_AVZ: '[5]Служебный АСУТП'!$E$2
Name ASUTP_AVZ: '[6]Служебный АСУТП'!$E$2:$E$9
Name ASUTP_AVZ: '[8]Служебный АСУТП'!$E$2:$E$5
Name ASUTP_AVZ: 'Служебный АСУТП'!$E$2:$E$9
Name ASUTP_AZ: '[5]Служебный АСУТП'!$J$2:$J$3
Name ASUTP_AZ: '[6]Служебный АСУТП'!$J$2:$J$6
Name ASUTP_AZ: '[4]Служебный АСУТП'!$J$2:$J$6
Name ASUTP_AZ: '[7]Служебный АСУТП'!$J$2:$J$5
Name ASUTP_AZ: '[3]Служебный АСУТП'!$J$2:$J$6
Name ASUTP_AZ: '[5]Служебный АСУТП'!$J$2:$J$3
Name ASUTP_AZ: '[6]Служебный АСУТП'!$J$2:$J$6
Name ASUTP_AZ: '[8]Служебный АСУТП'!$J$2:$J$5
Name ASUTP_AZ: 'Служебный АСУТП'!$J$2:$J$6
Name ASUTP_CONFIG: '[4]Служебный АСУТП'!$W$2
Name ASUTP_CONFIG: '[3]Служебный АСУТП'!$X$2
Name ASUTP_CONFIG: '[4]Служебный АСУТП'!$W$2
Name ASUTP_CONFIG: 'Служебный АСУТП'!$X$2
Name ASUTP_DAM: '[5]Служебный АСУТП'!$O$2
Name ASUTP_DAM: '[6]Служебный АСУТП'!$O$2:$O$5
Name ASUTP_DAM: '[4]Служебный АСУТП'!$O$2:$O$5
Name ASUTP_DAM: '[7]Служебный АСУТП'!$O$2:$O$7
Name ASUTP_DAM: '[3]Служебный АСУТП'!$P$2:$P$5
Name ASUTP_DAM: '[5]Служебный АСУТП'!$O$2
Name ASUTP_DAM: '[6]Служебный АСУТП'!$O$2:$O$5
Name ASUTP_DAM: '[8]Служебный АСУТП'!$O$2:$O$7
Name ASUTP_DAM: 'Служебный АСУТП'!$P$2:$P$5
Name ASUTP_DCAP: '[4]Служебный АСУТП'!$V$2:$V$4
Name ASUTP_DCAP: '[3]Служебный АСУТП'!$W$2:$W$4
Name ASUTP_DCAP: '[4]Служебный АСУТП'!$V$2:$V$4
Name ASUTP_DCAP: 'Служебный АСУТП'!$W$2:$W$4
Name ASUTP_EDR: '[4]Служебный АСУТП'!$AC$2:$AC$3
Name ASUTP_EDR: '[3]Служебный АСУТП'!$AD$2:$AD$3
Name ASUTP_EDR: '[4]Служебный АСУТП'!$AC$2:$AC$3
Name ASUTP_EDR: 'Служебный АСУТП'!$AD$2:$AD$3
Name ASUTP_GOSSOPKA: '[4]Служебный АСУТП'!$T$2:$T$3
Name ASUTP_GOSSOPKA: '[3]Служебный АСУТП'!$U$2:$U$3
Name ASUTP_GOSSOPKA: '[4]Служебный АСУТП'!$T$2:$T$3
Name ASUTP_GOSSOPKA: 'Служебный АСУТП'!$U$2:$U$3
Name ASUTP_IDS: '[5]Служебный АСУТП'!$L$2:$L$4
Name ASUTP_IDS: '[6]Служебный АСУТП'!$L$2:$L$4
Name ASUTP_IDS: '[4]Служебный АСУТП'!$L$2:$L$4
Name ASUTP_IDS: '[7]Служебный АСУТП'!$L$2:$L$4
Name ASUTP_IDS: '[3]Служебный АСУТП'!$L$2:$L$4
Name ASUTP_IDS: '[5]Служебный АСУТП'!$L$2:$L$4
Name ASUTP_IDS: '[6]Служебный АСУТП'!$L$2:$L$4
Name ASUTP_IDS: '[8]Служебный АСУТП'!$L$2:$L$4

Sheet Информация
A1: Заявка на бюджетирование проекта
A2: № п.п. | B2: Вопрос | C2: Значение
A3: 1 | B3: ФИО разработчика спецификации
A4: 2 | B4: ФИО ответственного за проект
A5: 3 | B5: Дата, когда необходим ответ
A6: 4 | B6: Цепочка поставки. Выбрать из списка: Для внутренних нужд - для использования внутри Солар, без права передачи третьим лицам и без права использования для выгодоприобретения. Перепродажа - передача права конечному заказчику. Услуги третьим лицам - покупка на баланс Солар с правом оказания сервисов и использования продукта с целью выгодоприобретения. Сервисы - покупка на баланс Солар для обеспечения работы каких либо сервисов без передачи продукта (в любом виде) конечному заказчику или любому другому третьему лицу.
A7: 5 | B7: Название конечного заказчика (Если для внутренних нужд, указывать Солар)
A8: 6 | B8: Название проекта
A9: 7 | B9: Номер пресейла, если есть
A10: 8 | B10: Название участников - партнер/партнеры (указать), если есть
A11: 9 | B11: Ссылка на конкурс, если есть
A12: 10 | B12: Планируемая дата подачи в конкурс, если известна
A13: 11 | B13: Прогнозируемая дата поставки по конкурсу, если известна
A14: 12 | B14: Адрес доставки
A15: 13 | B15: Формы для регистрации проектов по вендорам выложены в папке по ссылке: | C15: Ссылка будет позднее
A16: 14 | B16: Если формы нет в папке, просьба заполнить следующие поля.
A17: 15 | B17: ИНН конечного заказчика
A18: 16 | B18: КПП конечного заказчика
A19: 17 | B19: ФИО контактного лица заказчика
A20: 18 | B20: Должность контактного лица заказчика
A21: 19 | B21: Телефон контактного лица заказчика
A22: 20 | B22: Корпоративный адрес электронной почты контактного лица заказчика
A23: 21 | B23: Сайт организации

Sheet Файл оценки
F1: Трз по ролям
A2: Заказчик | D2: Сумарные ТРз | E2: Ответственное подразделение | F2: И | G2: СИ | H2: ВИ | I2: ГИП | L2: Заполнять командировки с комментарием учтены ли дни на дорогу в столбце H, если учтены писать кол-во дней в дороге, если так же добавляются Трз на предварительную подготовку к выезду так же писать комментарий. Например: Командировка на Завод N1, учтено в расчете 2 дня на дорогу туда-обратно, 1 день на подготовку к выезду, 4 дня работа на площадке = итого 6 дней (с дорогой 2 дня)
A3: Наименование сервиса или услуги | D3: =SUM(D4:D8) -> 103.10938 | E3: =IF(D3,IF(D4=MAX(D4:D8),B4,IF(D5=MAX(D4:D8),B5,IF(D6=MAX(D4:D8),B6,IF(D7=MAX(D4:D8),B7,IF(D8=MAX(D4:D8),B8))))),"") -> ОКиА
A4: Ответственный исполнитель | B4: ОКиА | D4: =SUMIF($D$14:$D$251,"=Инженер ОК",$E$14:$E$251) + SUMIF($D$14:$D$251,"Старший инженер ОК",$E$14:$E$251)+ SUMIF($D$14:$D$251,"Ведущий инженер ОК",$E$14:$E$251)+ SUMIF($D$14:$D$251,"ГИП ОК",$E$14:$E$251) -> 82.7375 | F4: =SUMIF($D$14:$D$251,"Инженер ОК",$E$14:$E$251) -> 38.0725 | G4: =SUMIF($D$14:$D$251,"Старший инженер ОК",$E$14:$E$251) -> 30.779813 | H4: =SUMIF($D$14:$D$251,"Ведущий инженер ОК",$E$14:$E$251) -> 13.885188 | I4: =SUMIF($D$14:$D$251,"ГИП ОК",$E$14:$E$251) -> 0
B5: ОП | D5: =SUMIF($D$14:$D$251,"Инженер ОП",$E$14:$E$251) + SUMIF($D$14:$D$251,"Старший инженер ОП",$E$14:$E$251) + SUMIF($D$14:$D$251,"Ведущий инженер ОП",$E$14:$E$251)+ SUMIF($D$14:$D$251,"ГИП ОП",$E$14:$E$251) -> 6.790625 | F5: =SUMIF($D$14:$D$251,"Инженер ОП",$E$14:$E$251) -> 0 | G5: =SUMIF($D$14:$D$251,"Старший инженер ОП",$E$14:$E$251) -> 0 | H5: =SUMIF($D$14:$D$251,"Ведущий инженер ОП",$E$14:$E$251) -> 0 | I5: =SUMIF($D$14:$D$251,"ГИП ОП",$E$14:$E$251) -> 6.790625
B6: ОВ | D6: =SUMIF($D$14:$D$251,"=Инженер ОВ",$E$14:$E$251) + SUMIF($D$14:$D$251,"Старший инженер ОВ",$E$14:$E$251) + SUMIF($D$14:$D$251,"Ведущий инженер ОВ",$E$14:$E$251) + SUMIF($D$14:$D$251,"ГИП ОВ",$E$14:$E$251) -> 0 | F6: =SUMIF($D$14:$D$251,"Инженер ОВ",$E$14:$E$251) -> 0 | G6: =SUMIF($D$14:$D$251,"Старший инженер ОВ",$E$14:$E$251) -> 0 | H6: =SUMIF($D$14:$D$251,"Ведущий инженер ОВ",$E$14:$E$251) -> 0 | I6: =SUMIF($D$14:$D$251,"ГИП ОВ",$E$14:$E$251) -> 0
B7: Нормоконтроль | D7: =SUMIF($D$14:$D$251,"=Нормоконтроль ОП",$E$14:$E$251) -> 0
B8: РП | D8: =SUMIF($D$14:$D$251,"Администратор проектов",$E$14:$E$251)+SUMIF($D$14:$D$251,"Ведущий РП",$E$14:$E$251)+SUMIF($D$14:$D$251,"РП",$E$14:$E$251) -> 13.58125
C9: * - желтой заливкой обозначен ТО
D10: =IF(SUM(D4:D6)>500,(IF(SUM(D4:D6)>500,"Согласовать c Директором ЦКП","")),(IF(AND(SUM(D4:D6)>100,SUM(D4:D6)<500),CONCATENATE("Согласовать с руководителем ",IF(D3,IF(D4=MAX(D4:D8),B4,IF(D5=MAX(D4:D8),B5,IF(D6=MAX(D4:D8),B6,IF(D7=MAX(D4:D8),B7,IF(D8=MAX(D4:D8),B8))))),""))))) -> FALSE
D11: =IF(A253<>"","У расчета есть ограничения","")
F12: Командировки
A13: Наименование работ по ТЗ | B13: Подэтапы для САДКО | C13: Результаты этапа (документация/детализация) | D13: Специалист | E13: Количество ч\д | F13: Количество человек | G13: Количество суток в одной поездке на одного человека (с учетом дороги) | H13: Количество поездок | I13: Куда | J13: Трудощатраты в командировке | K13: Длительность этапа раб.дни | L13: Примечание | R13: ОП | S13: ОК | T13: ОВ
A14: 1. Обследование/аудит по направлению "Безопасность КИИ" | B14: 1.1 Подготовка опросных листов и методики для аудита/обследования | C14: Методика проведения аудита/обследования; Заполненные ОЛ по аудиту/обследованию; | D14: Инженер ОК | E14: =IF(D14="Инженер ОК",ТрЗ_ОКиА!$K$28,IF(D14="Старший инженер ОК",ТрЗ_ОКиА!$L$28,IF(D14="Ведущий инженер ОК",ТрЗ_ОКиА!$M$28,""))) -> 0.6 | K14: *Экспертно определяем и указываем длительность этапа | M14: Очное/заочное обследование площадок Заполненные опросные листы | Q14: 1 | R14: 0 | S14: 1.45 | T14: 0
D15: Старший инженер ОК | E15: =IF(D15="Инженер ОК",ТрЗ_ОКиА!$K$28,IF(D15="Старший инженер ОК",ТрЗ_ОКиА!$L$28,IF(D15="Ведущий инженер ОК",ТрЗ_ОКиА!$M$28,""))) -> 0.3 | M15: ОП | N15: 0 | O15: 15 | Q15: 2 | R15: 0 | S15: 0.25 | T15: 0
D16: Ведущий инженер ОК | E16: =IF(D16="Инженер ОК",ТрЗ_ОКиА!$K$28,IF(D16="Старший инженер ОК",ТрЗ_ОКиА!$L$28,IF(D16="Ведущий инженер ОК",ТрЗ_ОКиА!$M$28,""))) -> 0.1 | M16: ОК | N16: 22
D17: Инженер ОП | M17: ОВ | N17: 0
D18: Инженер ОП
D19: Старший инженер ОП | M19: Отчет по обследованию
D20: Старший инженер ОП | M20: ОП | N20: 0 | O20: 11
D21: Ведущий инженер ОП
D22: Ведущий инженер ОП | M22: ОК | N22: 15,4
B23: 1.2 Очное/заочное обследование площадок | C23: Заполненные ОЛ по аудиту/обследованию; | D23: Инженер ОК | E23: =ROUNDUP(IF(D23="Инженер ОК",ТрЗ_ОКиА!$K$31,IF(D23="Старший инженер ОК",ТрЗ_ОКиА!$L$31,IF(D23="Ведущий инженер ОК",ТрЗ_ОКиА!$M$31,""))),0) -> 4 | F23: 1 | G23: 4.1 | H23: 1 | J23: =F23*G23*H23 -> 4.1 | M23: ОВ | N23: 0
D24: Старший инженер ОК | E24: =ROUNDUP(IF(D24="Инженер ОК",ТрЗ_ОКиА!$K$31,IF(D24="Старший инженер ОК",ТрЗ_ОКиА!$L$31,IF(D24="Ведущий инженер ОК",ТрЗ_ОКиА!$M$31,""))),0) -> 4 | F24: 1 | G24: 3.2 | H24: 1 | J24: =F24*G24*H24 -> 3.2
D25: Ведущий инженер ОК | E25: =ROUNDUP(IF(D25="Инженер ОК",ТрЗ_ОКиА!$K$31,IF(D25="Старший инженер ОК",ТрЗ_ОКиА!$L$31,IF(D25="Ведущий инженер ОК",ТрЗ_ОКиА!$M$31,""))),0) -> 2 | F25: 1 | G25: 2 | H25: 1 | J25: =F25*G25*H25 -> 2 | M25: ОП | N25: 0
D26: Инженер ОП | M26: ОК | N26: 0
D27: Старший инженер ОП
D28: Ведущий инженер ОП | M28: ОВ | N28: 0
D29: Нормоконтроль ОП | L29: НК=Инженер
B30: 1.3 Разработка отчета по обследованию/аудиту | C30: Отчет по результатам аудита/обследования | D30: Инженер ОК | E30: =IF(D30="Инженер ОК",ТрЗ_ОКиА!$K$35,IF(D30="Старший инженер ОК",ТрЗ_ОКиА!$L$35,IF(D30="Ведущий инженер ОК",ТрЗ_ОКиА!$M$35,""))) -> 4 | M30: ОВ | N30: 0
D31: Старший инженер ОК | E31: =IF(D31="Инженер ОК",ТрЗ_ОКиА!$K$35,IF(D31="Старший инженер ОК",ТрЗ_ОКиА!$L$35,IF(D31="Ведущий инженер ОК",ТрЗ_ОКиА!$M$35,""))) -> 3.2 | M31: Перечень угроз и нарушителей
D32: Ведущий инженер ОК | E32: =IF(D32="Инженер ОК",ТрЗ_ОКиА!$K$35,IF(D32="Старший инженер ОК",ТрЗ_ОКиА!$L$35,IF(D32="Ведущий инженер ОК",ТрЗ_ОКиА!$M$35,""))) -> 0.8 | M32: ОП | N32: 0
D33: Инженер ОП | M33: ОК | N33: 0
D34: Старший инженер ОП
D35: Ведущий инженер ОП | M35: ОВ | N35: 0
D36: Нормоконтроль ОП | L36: НК=Инженер
B37: 1.3 Техническое управление проектом | D37: ГИП ОП | E37: =SUM(E14:E36)*0.1 -> 1.9 | M37: ЧМУиН
B38: 1.4 Администрирование проекта | D38: Ведущий РП | E38: =SUM(E14:E36)*0.2 -> 3.8 | M38: ОП | N38: 0
A39: 1. Обследование/аудит по направлению "Безопасность ПДн" | B39: 1.1 Подготовка опросных листов и методики для аудита/обследования | C39: Методика проведения аудита/обследования; Заполненные ОЛ по аудиту/обследованию; | D39: Инженер ОК | E39: =IF(D39="Инженер ОК",ТрЗ_ОКиА!$K$92,IF(D39="Старший инженер ОК",ТрЗ_ОКиА!$L$92,IF(D39="Ведущий инженер ОК",ТрЗ_ОКиА!$M$92,""))) -> 0.6 | K39: *Экспертно определяем и указываем длительность этапа
D40: Старший инженер ОК | E40: =IF(D40="Инженер ОК",ТрЗ_ОКиА!$K$92,IF(D40="Старший инженер ОК",ТрЗ_ОКиА!$L$92,IF(D40="Ведущий инженер ОК",ТрЗ_ОКиА!$M$92,""))) -> 0.3 | M40: ОП | N40: 0
D41: Ведущий инженер ОК | E41: =IF(D41="Инженер ОК",ТрЗ_ОКиА!$K$92,IF(D41="Старший инженер ОК",ТрЗ_ОКиА!$L$92,IF(D41="Ведущий инженер ОК",ТрЗ_ОКиА!$M$92,""))) -> 0.1 | M41: ОК | N41: 22
D42: Инженер ОП | M42: ОВ | N42: 0
D43: Инженер ОП
D44: Старший инженер ОП
D45: Старший инженер ОП | M45: ОП | N45: 0
D46: Ведущий инженер ОП
D47: Ведущий инженер ОП | M47: ОК | N47: 15,4
B48: 1.2 Очное/заочное обследование площадок | C48: Заполненные ОЛ по аудиту/обследованию; | D48: Инженер ОК | E48: =ROUNDUP(IF(D48="Инженер ОК",ТрЗ_ОКиА!$K$95,IF(D48="Старший инженер ОК",ТрЗ_ОКиА!$L$95,IF(D48="Ведущий инженер ОК",ТрЗ_ОКиА!$M$95,""))),0) -> 3 | F48: 1 | G48: 3 | H48: 1 | J48: =F48*G48*H48 -> 3 | M48: ОВ | N48: 0
D49: Старший инженер ОК | E49: =ROUNDUP(IF(D49="Инженер ОК",ТрЗ_ОКиА!$K$95,IF(D49="Старший инженер ОК",ТрЗ_ОКиА!$L$95,IF(D49="Ведущий инженер ОК",ТрЗ_ОКиА!$M$95,""))),0) -> 3 | F49: 1 | G49: 3 | H49: 1 | J49: =F49*G49*H49 -> 3
D50: Ведущий инженер ОК | E50: =ROUNDUP(IF(D50="Инженер ОК",ТрЗ_ОКиА!$K$95,IF(D50="Старший инженер ОК",ТрЗ_ОКиА!$L$95,IF(D50="Ведущий инженер ОК",ТрЗ_ОКиА!$M$95,""))),0) -> 2 | F50: 1 | G50: 2 | H50: 1 | J50: =F50*G50*H50 -> 2 | M50: ОП | N50: 0
D51: Инженер ОП | M51: ОК | N51: 0
D52: Старший инженер ОП
D53: Ведущий инженер ОП | M53: ОВ | N53: 0
D54: Нормоконтроль ОП | L54: НК=Инженер
B55: 1.3 Разработка отчета по обследованию/аудиту | C55: Отчет по результатам аудита/обследования | D55: Инженер ОК | E55: =IF(D55="Инженер ОК",ТрЗ_ОКиА!$K$101,IF(D55="Старший инженер ОК",ТрЗ_ОКиА!$L$101,IF(D55="Ведущий инженер ОК",ТрЗ_ОКиА!$M$101,""))) -> 3.15 | M55: ОВ | N55: 0
D56: Старший инженер ОК | E56: =IF(D56="Инженер ОК",ТрЗ_ОКиА!$K$101,IF(D56="Старший инженер ОК",ТрЗ_ОКиА!$L$101,IF(D56="Ведущий инженер ОК",ТрЗ_ОКиА!$M$101,""))) -> 2.52
D57: Ведущий инженер ОК | E57: =IF(D57="Инженер ОК",ТрЗ_ОКиА!$K$101,IF(D57="Старший инженер ОК",ТрЗ_ОКиА!$L$101,IF(D57="Ведущий инженер ОК",ТрЗ_ОКиА!$M$101,""))) -> 0.63 | M57: ОП | N57: 0
D58: Инженер ОП | M58: ОК | N58: 0
D59: Старший инженер ОП
D60: Ведущий инженер ОП | M60: ОВ | N60: 0
D61: Нормоконтроль ОП | L61: НК=Инженер
B62: 1.3 Техническое управление проектом | D62: ГИП ОП | E62: =SUM(E39:E61)*0.1 -> 1.53
B63: 1.4 Администрирование проекта | D63: Ведущий РП | E63: =SUM(E39:E61)*0.2 -> 3.06 | M63: ОП | N63: 0
A64: 1. Обследование/аудит по направлению "Безопасность ГИС" | B64: 1.1 Подготовка опросных листов и методики для аудита/обследования | C64: Методика проведения аудита/обследования; Заполненные ОЛ по аудиту/обследованию; | D64: Инженер ОК | E64: =IF(D64="Инженер ОК",ТрЗ_ОКиА!$K$170,IF(D64="Старший инженер ОК",ТрЗ_ОКиА!$L$170,IF(D64="Ведущий инженер ОК",ТрЗ_ОКиА!$M$170,""))) -> 1 | K64: *Экспертно определяем и указываем длительность этапа
D65: Старший инженер ОК | E65: =IF(D65="Инженер ОК",ТрЗ_ОКиА!$K$170,IF(D65="Старший инженер ОК",ТрЗ_ОКиА!$L$170,IF(D65="Ведущий инженер ОК",ТрЗ_ОКиА!$M$170,""))) -> 0.45 | M65: ОП | N65: 0
D66: Ведущий инженер ОК | E66: =IF(D66="Инженер ОК",ТрЗ_ОКиА!$K$170,IF(D66="Старший инженер ОК",ТрЗ_ОКиА!$L$170,IF(D66="Ведущий инженер ОК",ТрЗ_ОКиА!$M$170,""))) -> 0.15 | M66: ОК | N66: 22
D67: Инженер ОП | M67: ОВ | N67: 0
D68: Инженер ОП
D69: Старший инженер ОП
D70: Старший инженер ОП | M70: ОП | N70: 0
D71: Ведущий инженер ОП
D72: Ведущий инженер ОП | M72: ОК | N72: 15,4
B73: 1.2 Очное/заочное обследование площадок | C73: Заполненные ОЛ по аудиту/обследованию; | D73: Инженер ОК | E73: =ROUNDUP(IF(D73="Инженер ОК",ТрЗ_ОКиА!$K$173,IF(D73="Старший инженер ОК",ТрЗ_ОКиА!$L$173,IF(D73="Ведущий инженер ОК",ТрЗ_ОКиА!$M$173,""))),0) -> 3 | F73: 1 | G73: 3 | H73: 1 | J73: =F73*G73*H73 -> 3 | M73: ОВ | N73: 0
D74: Старший инженер ОК | E74: =ROUNDUP(IF(D74="Инженер ОК",ТрЗ_ОКиА!$K$173,IF(D74="Старший инженер ОК",ТрЗ_ОКиА!$L$173,IF(D74="Ведущий инженер ОК",ТрЗ_ОКиА!$M$173,""))),0) -> 3 | F74: 1 | G74: 3 | H74: 1 | J74: =F74*G74*H74 -> 3
D75: Ведущий инженер ОК | E75: =ROUNDUP(IF(D75="Инженер ОК",ТрЗ_ОКиА!$K$173,IF(D75="Старший инженер ОК",ТрЗ_ОКиА!$L$173,IF(D75="Ведущий инженер ОК",ТрЗ_ОКиА!$M$173,""))),0) -> 2 | F75: 1 | G75: 2 | H75: 1 | J75: =F75*G75*H75 -> 2 | M75: ОП | N75: 0
D76: Инженер ОП | M76: ОК | N76: 0
D77: Старший инженер ОП
D78: Ведущий инженер ОП | M78: ОВ | N78: 0
D79: Нормоконтроль ОП | L79: НК=Инженер
B80: 1.3 Разработка отчета по обследованию/аудиту | C80: Отчет по результатам аудита/обследования | D80: Инженер ОК | E80: =IF(D80="Инженер ОК",ТрЗ_ОКиА!$K$179,IF(D80="Старший инженер ОК",ТрЗ_ОКиА!$L$179,IF(D80="Ведущий инженер ОК",ТрЗ_ОКиА!$M$179,""))) -> 4.01875 | M80: ОВ | N80: 0
D81: Старший инженер ОК | E81: =IF(D81="Инженер ОК",ТрЗ_ОКиА!$K$179,IF(D81="Старший инженер ОК",ТрЗ_ОКиА!$L$179,IF(D81="Ведущий инженер ОК",ТрЗ_ОКиА!$M$179,""))) -> 3.215
D82: Ведущий инженер ОК | E82: =IF(D82="Инженер ОК",ТрЗ_ОКиА!$K$179,IF(D82="Старший инженер ОК",ТрЗ_ОКиА!$L$179,IF(D82="Ведущий инженер ОК",ТрЗ_ОКиА!$M$179,""))) -> 0.80375 | M82: ОП | N82: 0
D83: Инженер ОП | M83: ОК | N83: 0
D84: Старший инженер ОП
D85: Ведущий инженер ОП | M85: ОВ | N85: 0
D86: Нормоконтроль ОП | L86: НК=Инженер
B87: 1.3 Техническое управление проектом | D87: ГИП ОП | E87: =SUM(E64:E86)*0.1 -> 1.76375
B88: 1.4 Администрирование проекта | D88: Ведущий РП | E88: =SUM(E64:E86)*0.2 -> 3.5275 | M88: ОП | N88: 0
A89: 1. Обследование/аудит по направлению "Безопасность КТ" | B89: 1.1 Подготовка опросных листов и методики для аудита/обследования | C89: Методика проведения аудита/обследования; Заполненные ОЛ по аудиту/обследованию; | D89: Инженер ОК | E89: =IF(D89="Инженер ОК",ТрЗ_ОКиА!$K$241,IF(D89="Старший инженер ОК",ТрЗ_ОКиА!$L$241,IF(D89="Ведущий инженер ОК",ТрЗ_ОКиА!$M$241,""))) -> 0.6 | K89: *Экспертно определяем и указываем длительность этапа
D90: Старший инженер ОК | E90: =IF(D90="Инженер ОК",ТрЗ_ОКиА!$K$241,IF(D90="Старший инженер ОК",ТрЗ_ОКиА!$L$241,IF(D90="Ведущий инженер ОК",ТрЗ_ОКиА!$M$241,""))) -> 0.3 | M90: ОП | N90: 0
D91: Ведущий инженер ОК | E91: =IF(D91="Инженер ОК",ТрЗ_ОКиА!$K$241,IF(D91="Старший инженер ОК",ТрЗ_ОКиА!$L$241,IF(D91="Ведущий инженер ОК",ТрЗ_ОКиА!$M$241,""))) -> 0.1 | M91: ОК | N91: 22
D92: Инженер ОП | M92: ОВ | N92: 0
D93: Инженер ОП
B94: 1.2 Очное/заочное обследование площадок | C94: Заполненные ОЛ по аудиту/обследованию; | D94: Инженер ОК | E94: =ROUNDUP(IF(D94="Инженер ОК",ТрЗ_ОКиА!$K$244,IF(D94="Старший инженер ОК",ТрЗ_ОКиА!$L$244,IF(D94="Ведущий инженер ОК",ТрЗ_ОКиА!$M$244,""))),0) -> 1 | F94: 1 | G94: 1 | H94: 1 | J94: =F94*G94*H94 -> 1 | M94: ОВ | N94: 0
D95: Старший инженер ОК | E95: =ROUNDUP(IF(D95="Инженер ОК",ТрЗ_ОКиА!$K$244,IF(D95="Старший инженер ОК",ТрЗ_ОКиА!$L$244,IF(D95="Ведущий инженер ОК",ТрЗ_ОКиА!$M$244,""))),0) -> 2 | F95: 1 | G95: 2 | H95: 1 | J95: =F95*G95*H95 -> 2
D96: Ведущий инженер ОК | E96: =ROUNDUP(IF(D96="Инженер ОК",ТрЗ_ОКиА!$K$244,IF(D96="Старший инженер ОК",ТрЗ_ОКиА!$L$244,IF(D96="Ведущий инженер ОК",ТрЗ_ОКиА!$M$244,""))),0) -> 1 | F96: 1 | G96: 1 | H96: 1 | J96: =F96*G96*H96 -> 1 | M96: ОП | N96: 0
D97: Инженер ОП | M97: ОК | N97: 0
D98: Старший инженер ОП
D99: Ведущий инженер ОП | M99: ОВ | N99: 0
D100: Нормоконтроль ОП | L100: НК=Инженер
...

Sheet ТрЗ_ОП
B1: Исходные данные: | C1: Исходные данные | D1: Выбор набора СрЗИ (КИИ, ИСПДн, ГИС) | F1: Значения | G1: Командировки | W1: Документы: | AE1: номер столбца | AF1: простой Пресейл | AG1: обычный Пресейл | AH1: сложный Пресейл | AI1: простое ЭП | AJ1: обычное ЭП | AK1: сложное ЭП | AL1: простое ТРП | AM1: обычное ТРП | AN1: сложное ТРП | AO1: простое ТП | AP1: обычное ТП | AQ1: сложное ТП
B2: Тип разрабатываемой документации | D2: Уровень зрелости | F2: =W5 -> ТРП | G2: Кол-во площадок | H2: 666 | I2: количество | V2: 2 | W2: 2 | AE2: =IF(A11,MATCH(C11,'Документы АСУТП'!$E$3:$CI$3,0),"") + 4 -> 5 | AF2: =INDIRECT(ADDRESS(107,AE2,1,1,"Документы АСУТП")) -> 5 | AG2: =INDIRECT(ADDRESS(108,AE2,1,1,"Документы АСУТП")) -> 1 | AH2: =INDIRECT(ADDRESS(109,AE2,1,1,"Документы АСУТП")) -> 1 | AI2: =INDIRECT(ADDRESS(110,$AE2,1,1,"Документы АСУТП")) -> 3.5 | AJ2: =INDIRECT(ADDRESS(111,$AE2,1,1,"Документы АСУТП")) -> 2 | AK2: =INDIRECT(ADDRESS(112,$AE2,1,1,"Документы АСУТП")) -> 2.5 | AL2: =INDIRECT(ADDRESS(113,$AE2,1,1,"Документы АСУТП")) -> 44.25 | AM2: =INDIRECT(ADDRESS(114,$AE2,1,1,"Документы АСУТП")) -> 17.5 | AN2: =INDIRECT(ADDRESS(115,$AE2,1,1,"Документы АСУТП")) -> 28 | AO2: =INDIRECT(ADDRESS(116,$AE2,1,1,"Документы АСУТП")) -> 11.25 | AP2: =INDIRECT(ADDRESS(117,$AE2,1,1,"Документы АСУТП")) -> 10 | AQ2: =INDIRECT(ADDRESS(118,$AE2,1,1,"Документы АСУТП")) -> 15.5
B3: Техническая грамотность Заказчика* | D3: ГИС | F3: =W42 -> 1 | G3: Геораспределенность | H3: Нет | I3: да/нет
B4: Лояльность Заказчика** | D4: ИСПДн | F4: =W41 -> 1 | G4: Кол-во систем | H4: 3 | I4: количество
B5: Архитектура СОИБ | D5: КИИ | F5: =W13 -> 1 | G5: масштаб систем | H5: Маленькая | I5: маленька/средняя/большая | W5: =INDEX('Служебный АСУТП'!C12:C19,MATCH(W2,'Служебный АСУТП'!D12:D19,0)) -> ТРП | AE5: =IF(A12,MATCH(C12,'Документы АСУТП'!$E$3:$CU$3,0),"") + 4 -> 14 | AF5: =INDIRECT(ADDRESS(107,AE5,1,1,"Документы АСУТП")) -> 3 | AG5: =INDIRECT(ADDRESS(108,AE5,1,1,"Документы АСУТП")) -> 2 | AH5: =INDIRECT(ADDRESS(109,AE5,1,1,"Документы АСУТП")) -> 2 | AI5: =INDIRECT(ADDRESS(110,$AE5,1,1,"Документы АСУТП")) -> 3.5 | AJ5: =INDIRECT(ADDRESS(111,$AE5,1,1,"Документы АСУТП")) -> 3 | AK5: =INDIRECT(ADDRESS(112,$AE5,1,1,"Документы АСУТП")) -> 5 | AL5: =INDIRECT(ADDRESS(113,$AE5,1,1,"Документы АСУТП")) -> 57.25 | AM5: =INDIRECT(ADDRESS(114,$AE5,1,1,"Документы АСУТП")) -> 25.5 | AN5: =INDIRECT(ADDRESS(115,$AE5,1,1,"Документы АСУТП")) -> 43.5 | AO5: =INDIRECT(ADDRESS(116,$AE5,1,1,"Документы АСУТП")) -> 16.75 | AP5: =INDIRECT(ADDRESS(117,$AE5,1,1,"Документы АСУТП")) -> 12.5 | AQ5: =INDIRECT(ADDRESS(118,$AE5,1,1,"Документы АСУТП")) -> 20.5
B6: Уровень типизации проекта | C6: =INDEX('Служебный АСУТП'!C23:C25,MATCH(W7,'Служебный АСУТП'!D23:D25,0)) -> Обычный | F6: =W7 -> 2 | G6: тип проекта | H6: ЭП | I6: ЭП/ТРП/Пресейл/ТП | W6: Типизация | AE6: =IF(A13,MATCH(C13,'Документы АСУТП'!$E$3:$CU$3,0),"") + 4 -> #VALUE! | AF6: =INDIRECT(ADDRESS(107,AE6,1,1,"Документы АСУТП")) -> #VALUE! | AG6: =INDIRECT(ADDRESS(108,AE6,1,1,"Документы АСУТП")) -> #VALUE! | AH6: =INDIRECT(ADDRESS(109,AE6,1,1,"Документы АСУТП")) -> #VALUE! | AI6: =INDIRECT(ADDRESS(110,$AE6,1,1,"Документы АСУТП")) -> #VALUE! | AJ6: =INDIRECT(ADDRESS(111,$AE6,1,1,"Документы АСУТП")) -> #VALUE! | AK6: =INDIRECT(ADDRESS(112,$AE6,1,1,"Документы АСУТП")) -> #VALUE! | AL6: =INDIRECT(ADDRESS(113,$AE6,1,1,"Документы АСУТП")) -> #VALUE! | AM6: =INDIRECT(ADDRESS(114,$AE6,1,1,"Документы АСУТП")) -> #VALUE! | AN6: =INDIRECT(ADDRESS(115,$AE6,1,1,"Документы АСУТП")) -> #VALUE! | AO6: =INDIRECT(ADDRESS(116,$AE6,1,1,"Документы АСУТП")) -> #VALUE! | AP6: =INDIRECT(ADDRESS(117,$AE6,1,1,"Документы АСУТП")) -> #VALUE! | AQ6: =INDIRECT(ADDRESS(118,$AE6,1,1,"Документы АСУТП")) -> #VALUE!
B7: *Тех грамотность: высокая - упрощает реализацию, т.к. Заказчик сможет принимать решения, согласовывать подходы и корректно и полноценно предоставлять ИД для проектирования | W7: 2 | AE7: =IF(A14,MATCH(C14,'Документы АСУТП'!$E$3:$CU$3,0),"") + 4 -> #VALUE! | AF7: =INDIRECT(ADDRESS(107,AE7,1,1,"Документы АСУТП")) -> #VALUE! | AG7: =INDIRECT(ADDRESS(108,AE7,1,1,"Документы АСУТП")) -> #VALUE! | AH7: =INDIRECT(ADDRESS(109,AE7,1,1,"Документы АСУТП")) -> #VALUE! | AI7: =INDIRECT(ADDRESS(110,$AE7,1,1,"Документы АСУТП")) -> #VALUE! | AJ7: =INDIRECT(ADDRESS(111,$AE7,1,1,"Документы АСУТП")) -> #VALUE! | AK7: =INDIRECT(ADDRESS(112,$AE7,1,1,"Документы АСУТП")) -> #VALUE! | AL7: =INDIRECT(ADDRESS(113,$AE7,1,1,"Документы АСУТП")) -> #VALUE! | AM7: =INDIRECT(ADDRESS(114,$AE7,1,1,"Документы АСУТП")) -> #VALUE! | AN7: =INDIRECT(ADDRESS(115,$AE7,1,1,"Документы АСУТП")) -> #VALUE! | AO7: =INDIRECT(ADDRESS(116,$AE7,1,1,"Документы АСУТП")) -> #VALUE! | AP7: =INDIRECT(ADDRESS(117,$AE7,1,1,"Документы АСУТП")) -> #VALUE! | AQ7: =INDIRECT(ADDRESS(118,$AE7,1,1,"Документы АСУТП")) -> #VALUE!
B8: ** Лояльность: высокая - упрощает реализацию, значит Заказчик лояльный и замечания будут конструктивные | W8: =INDEX('Служебный АСУТП'!C23:C25,MATCH(W7,'Служебный АСУТП'!D23:D25,0)) -> Обычный | AE8: =IF(A15,MATCH(C15,'Документы АСУТП'!$E$3:$CU$3,0),"") + 4 -> #VALUE! | AF8: =INDIRECT(ADDRESS(107,AE8,1,1,"Документы АСУТП")) -> #VALUE! | AG8: =INDIRECT(ADDRESS(108,AE8,1,1,"Документы АСУТП")) -> #VALUE! | AH8: =INDIRECT(ADDRESS(109,AE8,1,1,"Документы АСУТП")) -> #VALUE! | AI8: =INDIRECT(ADDRESS(110,$AE8,1,1,"Документы АСУТП")) -> #VALUE! | AJ8: =INDIRECT(ADDRESS(111,$AE8,1,1,"Документы АСУТП")) -> #VALUE! | AK8: =INDIRECT(ADDRESS(112,$AE8,1,1,"Документы АСУТП")) -> #VALUE! | AL8: =INDIRECT(ADDRESS(113,$AE8,1,1,"Документы АСУТП")) -> #VALUE! | AM8: =INDIRECT(ADDRESS(114,$AE8,1,1,"Документы АСУТП")) -> #VALUE! | AN8: =INDIRECT(ADDRESS(115,$AE8,1,1,"Документы АСУТП")) -> #VALUE! | AO8: =INDIRECT(ADDRESS(116,$AE8,1,1,"Документы АСУТП")) -> #VALUE! | AP8: =INDIRECT(ADDRESS(117,$AE8,1,1,"Документы АСУТП")) -> #VALUE! | AQ8: =INDIRECT(ADDRESS(118,$AE8,1,1,"Документы АСУТП")) -> #VALUE!
AA9: 1 | AE9: =IF(A16,MATCH(C16,'Документы АСУТП'!$E$3:$CU$3,0),"") + 4 -> #VALUE! | AF9: =INDIRECT(ADDRESS(107,AE9,1,1,"Документы АСУТП")) -> #VALUE! | AG9: =INDIRECT(ADDRESS(108,AE9,1,1,"Документы АСУТП")) -> #VALUE! | AH9: =INDIRECT(ADDRESS(109,AE9,1,1,"Документы АСУТП")) -> #VALUE! | AI9: =INDIRECT(ADDRESS(110,$AE9,1,1,"Документы АСУТП")) -> #VALUE! | AJ9: =INDIRECT(ADDRESS(111,$AE9,1,1,"Документы АСУТП")) -> #VALUE! | AK9: =INDIRECT(ADDRESS(112,$AE9,1,1,"Документы АСУТП")) -> #VALUE! | AL9: =INDIRECT(ADDRESS(113,$AE9,1,1,"Документы АСУТП")) -> #VALUE! | AM9: =INDIRECT(ADDRESS(114,$AE9,1,1,"Документы АСУТП")) -> #VALUE! | AN9: =INDIRECT(ADDRESS(115,$AE9,1,1,"Документы АСУТП")) -> #VALUE! | AO9: =INDIRECT(ADDRESS(116,$AE9,1,1,"Документы АСУТП")) -> #VALUE! | AP9: =INDIRECT(ADDRESS(117,$AE9,1,1,"Документы АСУТП")) -> #VALUE! | AQ9: =INDIRECT(ADDRESS(118,$AE9,1,1,"Документы АСУТП")) -> #VALUE!
B10: Применяемые подсистемы | D10: Параметр 1 | E10: Значение | F10: Параметр 2 | H10: Параметр 3 | I10: Значение | J10: Пресейл | K10: ЭП | L10: ТРП | M10: ТП | N10: Сумма (часы) | O10: Исходные параметры АСУТП | P10: Значения | T10: Трудозатраты АСУ ТП | W10: Значение | Y10: Значение | AA10: 1 | AE10: =IF(A17,MATCH(C17,'Документы АСУТП'!$E$3:$CU$3,0),"") + 4 -> #VALUE! | AF10: =INDIRECT(ADDRESS(107,AE10,1,1,"Документы АСУТП")) -> #VALUE! | AG10: =INDIRECT(ADDRESS(108,AE10,1,1,"Документы АСУТП")) -> #VALUE! | AH10: =INDIRECT(ADDRESS(109,AE10,1,1,"Документы АСУТП")) -> #VALUE! | AI10: =INDIRECT(ADDRESS(110,$AE10,1,1,"Документы АСУТП")) -> #VALUE! | AJ10: =INDIRECT(ADDRESS(111,$AE10,1,1,"Документы АСУТП")) -> #VALUE! | AK10: =INDIRECT(ADDRESS(112,$AE10,1,1,"Документы АСУТП")) -> #VALUE! | AL10: =INDIRECT(ADDRESS(113,$AE10,1,1,"Документы АСУТП")) -> #VALUE! | AM10: =INDIRECT(ADDRESS(114,$AE10,1,1,"Документы АСУТП")) -> #VALUE! | AN10: =INDIRECT(ADDRESS(115,$AE10,1,1,"Документы АСУТП")) -> #VALUE! | AO10: =INDIRECT(ADDRESS(116,$AE10,1,1,"Документы АСУТП")) -> #VALUE! | AP10: =INDIRECT(ADDRESS(117,$AE10,1,1,"Документы АСУТП")) -> #VALUE! | AQ10: =INDIRECT(ADDRESS(118,$AE10,1,1,"Документы АСУТП")) -> #VALUE!
A11: TRUE | B11: =IF(A11, "АВЗ","") -> АВЗ | C11: Kaspersky Security для виртуальных и облачных сред | D11: =IF(A11,INDIRECT(ADDRESS(2,MATCH(C11,'АВЗ АСУТП'!1:1),1,1,"АВЗ АСУТП")),"") -> АВЗ Кол-во серверов управления | E11: 2 | F11: =IF(A11,INDIRECT(ADDRESS(2,MATCH(C11,'АВЗ АСУТП'!1:1)+1,1,1,"АВЗ АСУТП")),"") -> АВЗ Кол-во смежных систем для интеграции | G11: 1 | H11: =IF(A11,INDIRECT(ADDRESS(2,MATCH(C11,'АВЗ АСУТП'!1:1)+2,1,1,"АВЗ АСУТП")),"") -> АВЗ Проектируется только АВЗ (нет=0; да=1) | J11: =IF(AND(A11=TRUE,'Тип разраб-ой док-ции'!$J$4=1),ROUNDUP(IF($F$5 =1,AF2,IF($F$5=2,AG2,IF($F$5 =3,AH2,"-")))/8,2),"-") -> #REF! | K11: =IF(AND(A11=TRUE,'Тип разраб-ой док-ции'!$J$3=1),ROUNDUP(IF($F$5 =1,AI2,IF($F$5=2,AJ2,IF($F$5 =3,AK2,"-")))/8,2),"-") -> #REF! | L11: =IF(AND(A11=TRUE,'Тип разраб-ой док-ции'!$J$2=1),ROUNDUP(IF($F$5 =1,AL2,IF($F$5=2,AM2,IF($F$5 =3,AN2,"-")))/8,2),"-") -> #REF! | M11: =IF(AND(A11=TRUE,'Тип разраб-ой док-ции'!$J$5=1),ROUNDUP(IF($F$5 =1,AO2,IF($F$5=2,AP2,IF($F$5 =3,AQ2,"-")))/8,2),"-") -> #REF! | N11: =SUM('Итоговый расчет АСУТП'!CO4:CO41) -> 17.5 | O11: ='АВЗ АСУТП'!$D$2 -> АВЗ Кол-во серверов управления | P11: =E11 -> 2 | S11: ТЗ | AA11: 0 | AE11: =IF(A18,MATCH(C18,'Документы АСУТП'!$E$3:$CU$3,0),"") + 4 -> #VALUE! | AF11: =INDIRECT(ADDRESS(107,AE11,1,1,"Документы АСУТП")) -> #VALUE! | AG11: =INDIRECT(ADDRESS(108,AE11,1,1,"Документы АСУТП")) -> #VALUE! | AH11: =INDIRECT(ADDRESS(109,AE11,1,1,"Документы АСУТП")) -> #VALUE! | AI11: =INDIRECT(ADDRESS(110,$AE11,1,1,"Документы АСУТП")) -> #VALUE! | AJ11: =INDIRECT(ADDRESS(111,$AE11,1,1,"Документы АСУТП")) -> #VALUE! | AK11: =INDIRECT(ADDRESS(112,$AE11,1,1,"Документы АСУТП")) -> #VALUE! | AL11: =INDIRECT(ADDRESS(113,$AE11,1,1,"Документы АСУТП")) -> #VALUE! | AM11: =INDIRECT(ADDRESS(114,$AE11,1,1,"Документы АСУТП")) -> #VALUE! | AN11: =INDIRECT(ADDRESS(115,$AE11,1,1,"Документы АСУТП")) -> #VALUE! | AO11: =INDIRECT(ADDRESS(116,$AE11,1,1,"Документы АСУТП")) -> #VALUE! | AP11: =INDIRECT(ADDRESS(117,$AE11,1,1,"Документы АСУТП")) -> #VALUE! | AQ11: =INDIRECT(ADDRESS(118,$AE11,1,1,"Документы АСУТП")) -> #VALUE!
A12: TRUE | B12: =IF(A12, "SIEM","") -> SIEM | C12: Kaspersky Unified Monitoring and Analysis Platform (KUMA) | D12: =IF(A12,INDIRECT(ADDRESS(2,MATCH(C12,'SIEM АСУТП'!1:1),1,1,"SIEM АСУТП")),"") -> SIEM Кол-во площадок с компонентами подсистемы | E12: 1 | F12: =IF(A12,INDIRECT(ADDRESS(2,MATCH(C12,'SIEM АСУТП'!1:1)+1,1,1,"SIEM АСУТП")),"") -> SIEM Кол-во типов источников | G12: 1 | H12: =IF(A12,INDIRECT(ADDRESS(2,MATCH(C12,'SIEM АСУТП'!1:1)+2,1,1,"SIEM АСУТП")),"") -> SIEM Проектируется только SIEM (нет=0; да=1) | J12: =IF(AND(A12=TRUE,'Тип разраб-ой док-ции'!$J$4=1),ROUNDUP(IF($F$5 =1,AF5,IF($F$5=2,AG5,IF($F$5 =3,AH5,"-")))/8,2),"-") -> #REF! | K12: =IF(AND(A12=TRUE,'Тип разраб-ой док-ции'!$J$3=1),ROUNDUP(IF($F$5 =1,AI5,IF($F$5=2,AJ5,IF($F$5 =3,AK5,"-")))/8,2),"-") -> #REF! | L12: =IF(AND(A12=TRUE,'Тип разраб-ой док-ции'!$J$2=1),ROUNDUP(IF($F$5 =1,AL5,IF($F$5=2,AM5,IF($F$5 =3,AN5,"-")))/8,2),"-") -> #REF! | M12: =IF(AND(A12=TRUE,'Тип разраб-ой док-ции'!$J$5=1),ROUNDUP(IF($F$5 =1,AO5,IF($F$5=2,AP5,IF($F$5 =3,AQ5,"-")))/8,2),"-") -> #REF! | N12: =SUM('Итоговый расчет АСУТП'!CQ4:CQ41) -> 25.5 | O12: ='АВЗ АСУТП'!$E$2 -> АВЗ Кол-во смежных систем для интеграции | P12: =G11 -> 1 | R12: - | S12: ТЗ | T12: =ROUNDUP('Итоговый расчет АСУТП'!EZ5/8,2) -> 0 | AA12: 0 | AE12: =IF(A20,MATCH(C20,'Документы АСУТП'!$E$3:$CU$3,0),"") + 4 -> #VALUE! | AF12: =INDIRECT(ADDRESS(107,AE12,1,1,"Документы АСУТП")) -> #VALUE! | AG12: =INDIRECT(ADDRESS(108,AE12,1,1,"Документы АСУТП")) -> #VALUE! | AH12: =INDIRECT(ADDRESS(109,AE12,1,1,"Документы АСУТП")) -> #VALUE! | AI12: =INDIRECT(ADDRESS(110,$AE12,1,1,"Документы АСУТП")) -> #VALUE! | AJ12: =INDIRECT(ADDRESS(111,$AE12,1,1,"Документы АСУТП")) -> #VALUE! | AK12: =INDIRECT(ADDRESS(112,$AE12,1,1,"Документы АСУТП")) -> #VALUE! | AL12: =INDIRECT(ADDRESS(113,$AE12,1,1,"Документы АСУТП")) -> #VALUE! | AM12: =INDIRECT(ADDRESS(114,$AE12,1,1,"Документы АСУТП")) -> #VALUE! | AN12: =INDIRECT(ADDRESS(115,$AE12,1,1,"Документы АСУТП")) -> #VALUE! | AO12: =INDIRECT(ADDRESS(116,$AE12,1,1,"Документы АСУТП")) -> #VALUE! | AP12: =INDIRECT(ADDRESS(117,$AE12,1,1,"Документы АСУТП")) -> #VALUE! | AQ12: =INDIRECT(ADDRESS(118,$AE12,1,1,"Документы АСУТП")) -> #VALUE!
A13: FALSE | B13: =IF(A13, "МСЭ","") | D13: =IF(A13,INDIRECT(ADDRESS(2,MATCH(C13,'МСЭ АСУТП'!1:1),1,1,"МСЭ АСУТП")),"") | F13: =IF(A13,INDIRECT(ADDRESS(2,MATCH(C13,'МСЭ АСУТП'!1:1)+1,1,1,"МСЭ АСУТП")),"") | H13: =IF(A13,INDIRECT(ADDRESS(2,MATCH(C13,'МСЭ АСУТП'!1:1)+2,1,1,"МСЭ АСУТП")),"") | J13: =IF(AND(A13=TRUE,'Тип разраб-ой док-ции'!$J$4=1),ROUNDUP(IF($F$5 =1,AF6,IF($F$5=2,AG6,IF($F$5 =3,AH6,"-")))/8,2),"-") -> #REF! | K13: =IF(AND(A13=TRUE,'Тип разраб-ой док-ции'!$J$3=1),ROUNDUP(IF($F$5 =1,AI6,IF($F$5=2,AJ6,IF($F$5 =3,AK6,"-")))/8,2),"-") -> #REF! | L13: =IF(AND(A13=TRUE,'Тип разраб-ой док-ции'!$J$2=1),ROUNDUP(IF($F$5 =1,AL6,IF($F$5=2,AM6,IF($F$5 =3,AN6,"-")))/8,2),"-") -> #REF! | M13: =IF(AND(A13=TRUE,'Тип разраб-ой док-ции'!$J$5=1),ROUNDUP(IF($F$5 =1,AO6,IF($F$5=2,AP6,IF($F$5 =3,AQ6,"-")))/8,2),"-") -> #REF! | N13: =SUM('Итоговый расчет АСУТП'!CS4:CS41) -> 0 | O13: ='АВЗ АСУТП'!$F$2 -> АВЗ Проектируется только АВЗ (нет=0; да=1) | P13: =I11 -> 0 | R13: 0 | S13: ФТТ | T13: =ROUNDUP('Итоговый расчет АСУТП'!EZ6/8,2) -> 0 | V13: 2 | W13: 1 | AA13: 1 | AE13: =IF(A21,MATCH(C21,'Документы АСУТП'!$E$3:$CU$3,0),"") + 4 -> #VALUE! | AF13: =INDIRECT(ADDRESS(107,AE13,1,1,"Документы АСУТП")) -> #VALUE! | AG13: =INDIRECT(ADDRESS(108,AE13,1,1,"Документы АСУТП")) -> #VALUE! | AH13: =INDIRECT(ADDRESS(109,AE13,1,1,"Документы АСУТП")) -> #VALUE! | AI13: =INDIRECT(ADDRESS(110,$AE13,1,1,"Документы АСУТП")) -> #VALUE! | AJ13: =INDIRECT(ADDRESS(111,$AE13,1,1,"Документы АСУТП")) -> #VALUE! | AK13: =INDIRECT(ADDRESS(112,$AE13,1,1,"Документы АСУТП")) -> #VALUE! | AL13: =INDIRECT(ADDRESS(113,$AE13,1,1,"Документы АСУТП")) -> #VALUE! | AM13: =INDIRECT(ADDRESS(114,$AE13,1,1,"Документы АСУТП")) -> #VALUE! | AN13: =INDIRECT(ADDRESS(115,$AE13,1,1,"Документы АСУТП")) -> #VALUE! | AO13: =INDIRECT(ADDRESS(116,$AE13,1,1,"Документы АСУТП")) -> #VALUE! | AP13: =INDIRECT(ADDRESS(117,$AE13,1,1,"Документы АСУТП")) -> #VALUE! | AQ13: =INDIRECT(ADDRESS(118,$AE13,1,1,"Документы АСУТП")) -> #VALUE!
A14: FALSE | B14: =IF(A14, "PIM / PAM / PUM ","") | D14: =IF(A14,INDIRECT(ADDRESS(2,MATCH(C14,'PAM АСУТП'!1:1),1,1,"PAM АСУТП")),"") | F14: =IF(A14,INDIRECT(ADDRESS(2,MATCH(C14,'PAM АСУТП'!1:1)+1,1,1,"PAM АСУТП")),"") | H14: =IF(A14,INDIRECT(ADDRESS(2,MATCH(C14,'PAM АСУТП'!1:1)+2,1,1,"PAM АСУТП")),"") | J14: =IF(AND(A14=TRUE,'Тип разраб-ой док-ции'!$J$4=1),ROUNDUP(IF($F$5 =1,AF7,IF($F$5=2,AG7,IF($F$5 =3,AH7,"-")))/8,2),"-") -> #REF! | K14: =IF(AND(A14=TRUE,'Тип разраб-ой док-ции'!$J$3=1),ROUNDUP(IF($F$5 =1,AI7,IF($F$5=2,AJ7,IF($F$5 =3,AK7,"-")))/8,2),"-") -> #REF! | L14: =IF(AND(A14=TRUE,'Тип разраб-ой док-ции'!$J$2=1),ROUNDUP(IF($F$5 =1,AL7,IF($F$5=2,AM7,IF($F$5 =3,AN7,"-")))/8,2),"-") -> #REF! | M14: =IF(AND(A14=TRUE,'Тип разраб-ой док-ции'!$J$5=1),ROUNDUP(IF($F$5 =1,AO7,IF($F$5=2,AP7,IF($F$5 =3,AQ7,"-")))/8,2),"-") -> #REF! | N14: =SUM('Итоговый расчет АСУТП'!CU4:CU41) -> 0 | O14: ='SIEM АСУТП'!$D$2 -> SIEM Кол-во площадок с компонентами подсистемы | P14: =E12 -> 1 | S14: ЭП | AA14: 1 | AE14: =IF(A22,MATCH(C22,'Документы АСУТП'!$E$3:$CU$3,0),"") + 4 -> #VALUE! | AF14: =INDIRECT(ADDRESS(107,AE14,1,1,"Документы АСУТП")) -> #VALUE! | AG14: =INDIRECT(ADDRESS(108,AE14,1,1,"Документы АСУТП")) -> #VALUE! | AH14: =INDIRECT(ADDRESS(109,AE14,1,1,"Документы АСУТП")) -> #VALUE! | AI14: =INDIRECT(ADDRESS(110,$AE14,1,1,"Документы АСУТП")) -> #VALUE! | AJ14: =INDIRECT(ADDRESS(111,$AE14,1,1,"Документы АСУТП")) -> #VALUE! | AK14: =INDIRECT(ADDRESS(112,$AE14,1,1,"Документы АСУТП")) -> #VALUE! | AL14: =INDIRECT(ADDRESS(113,$AE14,1,1,"Документы АСУТП")) -> #VALUE! | AM14: =INDIRECT(ADDRESS(114,$AE14,1,1,"Документы АСУТП")) -> #VALUE! | AN14: =INDIRECT(ADDRESS(115,$AE14,1,1,"Документы АСУТП")) -> #VALUE! | AO14: =INDIRECT(ADDRESS(116,$AE14,1,1,"Документы АСУТП")) -> #VALUE! | AP14: =INDIRECT(ADDRESS(117,$AE14,1,1,"Документы АСУТП")) -> #VALUE! | AQ14: =INDIRECT(ADDRESS(118,$AE14,1,1,"Документы АСУТП")) -> #VALUE! | AR14: Оставить
A15: FALSE | B15: =IF(A15, "СКЗИ","") | D15: =IF(A15,INDIRECT(ADDRESS(2,MATCH(C15,'СКЗИ АСУТП'!1:1,0),1,1,"СКЗИ АСУТП")),"") | F15: =IF(A15,INDIRECT(ADDRESS(2,MATCH(C15,'СКЗИ АСУТП'!1:1,0)+1,1,1,"СКЗИ АСУТП")),"") | H15: =IF(A15,INDIRECT(ADDRESS(2,MATCH(C15,'СКЗИ АСУТП'!1:1,0)+2,1,1,"СКЗИ АСУТП")),"") | J15: =IF(AND(A15=TRUE,'Тип разраб-ой док-ции'!$J$4=1),ROUNDUP(IF($F$5 =1,AF8,IF($F$5=2,AG8,IF($F$5 =3,AH8,"-")))/8,2),"-") -> #REF! | K15: =IF(AND(A15=TRUE,'Тип разраб-ой док-ции'!$J$3=1),ROUNDUP(IF($F$5 =1,AI8,IF($F$5=2,AJ8,IF($F$5 =3,AK8,"-")))/8,2),"-") -> #REF! | L15: =IF(AND(A15=TRUE,'Тип разраб-ой док-ции'!$J$2=1),ROUNDUP(IF($F$5 =1,AL8,IF($F$5=2,AM8,IF($F$5 =3,AN8,"-")))/8,2),"-") -> #REF! | M15: =IF(AND(A15=TRUE,'Тип разраб-ой док-ции'!$J$5=1),ROUNDUP(IF($F$5 =1,AO8,IF($F$5=2,AP8,IF($F$5 =3,AQ8,"-")))/8,2),"-") -> #REF! | N15: =SUM('Итоговый расчет АСУТП'!CW4:CW41) -> 0 | O15: ='SIEM АСУТП'!$E$2 -> SIEM Кол-во типов источников | P15: =G12 -> 1 | R15: 0 | S15: Пояснительная записка к эскизному проекту | T15: =ROUNDUP('Итоговый расчет АСУТП'!EZ8/8,2) -> 0 | AA15: 0 | AE15: =IF(A23,MATCH(C23,'Документы АСУТП'!$E$3:$CU$3,0),"") + 4 -> #VALUE! | AF15: =INDIRECT(ADDRESS(107,AE15,1,1,"Документы АСУТП")) -> #VALUE! | AG15: =INDIRECT(ADDRESS(108,AE15,1,1,"Документы АСУТП")) -> #VALUE! | AH15: =INDIRECT(ADDRESS(109,AE15,1,1,"Документы АСУТП")) -> #VALUE! | AI15: =INDIRECT(ADDRESS(110,$AE15,1,1,"Документы АСУТП")) -> #VALUE! | AJ15: =INDIRECT(ADDRESS(111,$AE15,1,1,"Документы АСУТП")) -> #VALUE! | AK15: =INDIRECT(ADDRESS(112,$AE15,1,1,"Документы АСУТП")) -> #VALUE! | AL15: =INDIRECT(ADDRESS(113,$AE15,1,1,"Документы АСУТП")) -> #VALUE! | AM15: =INDIRECT(ADDRESS(114,$AE15,1,1,"Документы АСУТП")) -> #VALUE! | AN15: =INDIRECT(ADDRESS(115,$AE15,1,1,"Документы АСУТП")) -> #VALUE! | AO15: =INDIRECT(ADDRESS(116,$AE15,1,1,"Документы АСУТП")) -> #VALUE! | AP15: =INDIRECT(ADDRESS(117,$AE15,1,1,"Документы АСУТП")) -> #VALUE! | AQ15: =INDIRECT(ADDRESS(118,$AE15,1,1,"Документы АСУТП")) -> #VALUE!
A16: FALSE | B16: =IF(A16, "АЗ","") | D16: =IF(A16,INDIRECT(ADDRESS(2,MATCH(C16,'АЗ АСУТП'!1:1,0),1,1,"АЗ АСУТП")),"") | F16: =IF(A16,INDIRECT(ADDRESS(2,MATCH(C16,'АЗ АСУТП'!1:1,0)+1,1,1,"АЗ АСУТП")),"") | H16: =IF(A16,INDIRECT(ADDRESS(2,MATCH(C16,'АЗ АСУТП'!1:1,0)+2,1,1,"АЗ АСУТП")),"") | J16: =IF(AND(A16=TRUE,'Тип разраб-ой док-ции'!$J$4=1),ROUNDUP(IF($F$5 =1,AF9,IF($F$5=2,AG9,IF($F$5 =3,AH9,"-")))/8,2),"-") -> #REF! | K16: =IF(AND(A16=TRUE,'Тип разраб-ой док-ции'!$J$3=1),ROUNDUP(IF($F$5 =1,AI9,IF($F$5=2,AJ9,IF($F$5 =3,AK9,"-")))/8,2),"-") -> #REF! | L16: =IF(AND(A16=TRUE,'Тип разраб-ой док-ции'!$J$2=1),ROUNDUP(IF($F$5 =1,AL9,IF($F$5=2,AM9,IF($F$5 =3,AN9,"-")))/8,2),"-") -> #REF! | M16: =IF(AND(A16=TRUE,'Тип разраб-ой док-ции'!$J$5=1),ROUNDUP(IF($F$5 =1,AO9,IF($F$5=2,AP9,IF($F$5 =3,AQ9,"-")))/8,2),"-") -> #REF! | N16: =SUM('Итоговый расчет АСУТП'!CY4:CY41) -> 0 | O16: ='SIEM АСУТП'!$F$2 -> SIEM Проектируется только SIEM (нет=0; да=1) | P16: =I12 -> 0 | S16: ТП | AA16: 0 | AE16: =IF(A24,MATCH(C24,'Документы АСУТП'!$E$3:$CU$3,0),"") + 4 -> #VALUE! | AF16: =INDIRECT(ADDRESS(107,AE16,1,1,"Документы АСУТП")) -> #VALUE! | AG16: =INDIRECT(ADDRESS(108,AE16,1,1,"Документы АСУТП")) -> #VALUE! | AH16: =INDIRECT(ADDRESS(109,AE16,1,1,"Документы АСУТП")) -> #VALUE! | AI16: =INDIRECT(ADDRESS(110,$AE16,1,1,"Документы АСУТП")) -> #VALUE! | AJ16: =INDIRECT(ADDRESS(111,$AE16,1,1,"Документы АСУТП")) -> #VALUE! | AK16: =INDIRECT(ADDRESS(112,$AE16,1,1,"Документы АСУТП")) -> #VALUE! | AL16: =INDIRECT(ADDRESS(113,$AE16,1,1,"Документы АСУТП")) -> #VALUE! | AM16: =INDIRECT(ADDRESS(114,$AE16,1,1,"Документы АСУТП")) -> #VALUE! | AN16: =INDIRECT(ADDRESS(115,$AE16,1,1,"Документы АСУТП")) -> #VALUE! | AO16: =INDIRECT(ADDRESS(116,$AE16,1,1,"Документы АСУТП")) -> #VALUE! | AP16: =INDIRECT(ADDRESS(117,$AE16,1,1,"Документы АСУТП")) -> #VALUE! | AQ16: =INDIRECT(ADDRESS(118,$AE16,1,1,"Документы АСУТП")) -> #VALUE!
A17: FALSE | B17: =IF(A17, "СРК","") | D17: =IF(A17,INDIRECT(ADDRESS(2,MATCH(C17,'РК АСУТП'!1:1),1,1,"РК АСУТП")),"") | F17: =IF(A17,INDIRECT(ADDRESS(2,MATCH(C17,'РК АСУТП'!1:1)+1,1,1,"РК АСУТП")),"") | H17: =IF(A17,INDIRECT(ADDRESS(2,MATCH(C17,'РК АСУТП'!1:1)+2,1,1,"РК АСУТП")),"") | J17: =IF(AND(A17=TRUE,'Тип разраб-ой док-ции'!$J$4=1),ROUNDUP(IF($F$5 =1,AF10,IF($F$5=2,AG10,IF($F$5 =3,AH10,"-")))/8,2),"-") -> #REF! | K17: =IF(AND(A17=TRUE,'Тип разраб-ой док-ции'!$J$3=1),ROUNDUP(IF($F$5 =1,AI10,IF($F$5=2,AJ10,IF($F$5 =3,AK10,"-")))/8,2),"-") -> #REF! | L17: =IF(AND(A17=TRUE,'Тип разраб-ой док-ции'!$J$2=1),ROUNDUP(IF($F$5 =1,AL10,IF($F$5=2,AM10,IF($F$5 =3,AN10,"-")))/8,2),"-") -> #REF! | M17: =IF(AND(A17=TRUE,'Тип разраб-ой док-ции'!$J$5=1),ROUNDUP(IF($F$5 =1,AO10,IF($F$5=2,AP10,IF($F$5 =3,AQ10,"-")))/8,2),"-") -> #REF! | N17: =SUM('Итоговый расчет АСУТП'!DA4:DA41) -> 0 | O17: ='МСЭ АСУТП'!$D$2 -> МЭ Кол-во площадок | P17: =E13 -> 0 | R17: 1 | S17: Ведомость технического проекта | T17: =ROUNDUP('Итоговый расчет АСУТП'!EZ10/8,2) -> #REF! | AA17: 1 | AE17: =IF(A25,MATCH(C25,'Документы АСУТП'!$E$3:$CU$3,0),"") + 4 -> #VALUE! | AF17: =INDIRECT(ADDRESS(107,AE17,1,1,"Документы АСУТП")) -> #VALUE! | AG17: =INDIRECT(ADDRESS(108,AE17,1,1,"Документы АСУТП")) -> #VALUE! | AH17: =INDIRECT(ADDRESS(109,AE17,1,1,"Документы АСУТП")) -> #VALUE! | AI17: =INDIRECT(ADDRESS(110,$AE17,1,1,"Документы АСУТП")) -> #VALUE! | AJ17: =INDIRECT(ADDRESS(111,$AE17,1,1,"Документы АСУТП")) -> #VALUE! | AK17: =INDIRECT(ADDRESS(112,$AE17,1,1,"Документы АСУТП")) -> #VALUE! | AL17: =INDIRECT(ADDRESS(113,$AE17,1,1,"Документы АСУТП")) -> #VALUE! | AM17: =INDIRECT(ADDRESS(114,$AE17,1,1,"Документы АСУТП")) -> #VALUE! | AN17: =INDIRECT(ADDRESS(115,$AE17,1,1,"Документы АСУТП")) -> #VALUE! | AO17: =INDIRECT(ADDRESS(116,$AE17,1,1,"Документы АСУТП")) -> #VALUE! | AP17: =INDIRECT(ADDRESS(117,$AE17,1,1,"Документы АСУТП")) -> #VALUE! | AQ17: =INDIRECT(ADDRESS(118,$AE17,1,1,"Документы АСУТП")) -> #VALUE!
A18: FALSE | B18: =IF(A18, "Обнаружение вторжений (IDS/IPS)","") | D18: =IF(A18,INDIRECT(ADDRESS(2,MATCH(C18,'IDS АСУТП'!1:1),1,1,"IDS АСУТП")),"") | F18: =IF(A18,INDIRECT(ADDRESS(2,MATCH(C18,'IDS АСУТП'!1:1)+1,1,1,"IDS АСУТП")),"") | H18: =IF(A18,INDIRECT(ADDRESS(2,MATCH(C18,'IDS АСУТП'!1:1)+2,1,1,"IDS АСУТП")),"") | J18: =IF(AND(A18=TRUE,'Тип разраб-ой док-ции'!$J$4=1),ROUNDUP(IF($F$5 =1,AF11,IF($F$5=2,AG11,IF($F$5 =3,AH11,"-")))/8,2),"-") -> #REF! | K18: =IF(AND(A18=TRUE,'Тип разраб-ой док-ции'!$J$3=1),ROUNDUP(IF($F$5 =1,AI11,IF($F$5=2,AJ11,IF($F$5 =3,AK11,"-")))/8,2),"-") -> #REF! | L18: =IF(AND(A18=TRUE,'Тип разраб-ой док-ции'!$J$2=1),ROUNDUP(IF($F$5 =1,AL11,IF($F$5=2,AM11,IF($F$5 =3,AN11,"-")))/8,2),"-") -> #REF! | M18: =IF(AND(A18=TRUE,'Тип разраб-ой док-ции'!$J$5=1),ROUNDUP(IF($F$5 =1,AO11,IF($F$5=2,AP11,IF($F$5 =3,AQ11,"-")))/8,2),"-") -> #REF! | N18: =SUM('Итоговый расчет АСУТП'!DC4:DC41) -> 0 | O18: ='МСЭ АСУТП'!$E$2 -> МЭ Кол-во серверов управления | P18: =G13 -> 0 | R18: - | S18: Ведомость покупных изделий | T18: =ROUNDUP('Итоговый расчет АСУТП'!EZ11/8,2) -> 0 | AA18: 1 | AE18: =IF(A26,MATCH(C26,'Документы АСУТП'!$E$3:$CU$3,0),"") + 4 -> #VALUE! | AF18: =INDIRECT(ADDRESS(107,AE18,1,1,"Документы АСУТП")) -> #VALUE! | AG18: =INDIRECT(ADDRESS(108,AE18,1,1,"Документы АСУТП")) -> #VALUE! | AH18: =INDIRECT(ADDRESS(109,AE18,1,1,"Документы АСУТП")) -> #VALUE! | AI18: =INDIRECT(ADDRESS(110,$AE18,1,1,"Документы АСУТП")) -> #VALUE! | AJ18: =INDIRECT(ADDRESS(111,$AE18,1,1,"Документы АСУТП")) -> #VALUE! | AK18: =INDIRECT(ADDRESS(112,$AE18,1,1,"Документы АСУТП")) -> #VALUE! | AL18: =INDIRECT(ADDRESS(113,$AE18,1,1,"Документы АСУТП")) -> #VALUE! | AM18: =INDIRECT(ADDRESS(114,$AE18,1,1,"Документы АСУТП")) -> #VALUE! | AN18: =INDIRECT(ADDRESS(115,$AE18,1,1,"Документы АСУТП")) -> #VALUE! | AO18: =INDIRECT(ADDRESS(116,$AE18,1,1,"Документы АСУТП")) -> #VALUE! | AP18: =INDIRECT(ADDRESS(117,$AE18,1,1,"Документы АСУТП")) -> #VALUE! | AQ18: =INDIRECT(ADDRESS(118,$AE18,1,1,"Документы АСУТП")) -> #VALUE!
A19: FALSE | B19: =IF(A19, "НСД","") | D19: =IF(A19,INDIRECT(ADDRESS(2,MATCH(C19,'НСД АСУТП'!1:1),1,1,"НСД АСУТП")),"") | F19: =IF(A19,INDIRECT(ADDRESS(2,MATCH(C19,'НСД АСУТП'!1:1)+1,1,1,"НСД АСУТП")),"") | H19: =IF(A19,INDIRECT(ADDRESS(2,MATCH(C19,'НСД АСУТП'!1:1)+2,1,1,"НСД АСУТП")),"") | J19: =IF(AND(A19=TRUE,'Тип разраб-ой док-ции'!$J$4=1),ROUNDUP(IF($F$5 =1,AF33,IF($F$5=2,AG33,IF($F$5 =3,AH33,"-")))/8,2),"-") -> #REF! | K19: =IF(AND(A19=TRUE,'Тип разраб-ой док-ции'!$J$3=1),ROUNDUP(IF($F$5 =1,AI33,IF($F$5=2,AJ33,IF($F$5 =3,AK33,"-")))/8,2),"-") -> #REF! | L19: =IF(AND(A19=TRUE,'Тип разраб-ой док-ции'!$J$2=1),ROUNDUP(IF($F$5 =1,AL33,IF($F$5=2,AM33,IF($F$5 =3,AN33,"-")))/8,2),"-") -> #REF! | M19: =IF(AND(A19=TRUE,'Тип разраб-ой док-ции'!$J$5=1),ROUNDUP(IF($F$5 =1,AO33,IF($F$5=2,AP33,IF($F$5 =3,AQ33,"-")))/8,2),"-") -> #REF! | N19: =SUM('Итоговый расчет АСУТП'!DE3:DE40) -> 0 | O19: ='МСЭ АСУТП'!$F$2 -> МЭ Кол-во модулей | P19: =I13 -> 0 | R19: 1 | S19: Пояснительная записка к техническому проекту | T19: =ROUNDUP('Итоговый расчет АСУТП'!EZ12/8,2) -> #REF! | AA19: 0 | AE19: =IF(A27,MATCH(C27,'Документы АСУТП'!$E$3:$CU$3,0),"") + 4 -> #VALUE! | AF19: =INDIRECT(ADDRESS(107,AE19,1,1,"Документы АСУТП")) -> #VALUE! | AG19: =INDIRECT(ADDRESS(108,AE19,1,1,"Документы АСУТП")) -> #VALUE! | AH19: =INDIRECT(ADDRESS(109,AE19,1,1,"Документы АСУТП")) -> #VALUE! | AI19: =INDIRECT(ADDRESS(110,$AE19,1,1,"Документы АСУТП")) -> #VALUE! | AJ19: =INDIRECT(ADDRESS(111,$AE19,1,1,"Документы АСУТП")) -> #VALUE! | AK19: =INDIRECT(ADDRESS(112,$AE19,1,1,"Документы АСУТП")) -> #VALUE! | AL19: =INDIRECT(ADDRESS(113,$AE19,1,1,"Документы АСУТП")) -> #VALUE! | AM19: =INDIRECT(ADDRESS(114,$AE19,1,1,"Документы АСУТП")) -> #VALUE! | AN19: =INDIRECT(ADDRESS(115,$AE19,1,1,"Документы АСУТП")) -> #VALUE! | AO19: =INDIRECT(ADDRESS(116,$AE19,1,1,"Документы АСУТП")) -> #VALUE! | AP19: =INDIRECT(ADDRESS(117,$AE19,1,1,"Документы АСУТП")) -> #VALUE! | AQ19: =INDIRECT(ADDRESS(118,$AE19,1,1,"Документы АСУТП")) -> #VALUE!
A20: FALSE | B20: =IF(A20, "АПДМЗ","") | D20: =IF(A20,INDIRECT(ADDRESS(2,MATCH(C20,'АПМДЗ АСУТП'!1:1),1,1,"АПМДЗ АСУТП")),"") | F20: =IF(A20,INDIRECT(ADDRESS(2,MATCH(C20,'АПМДЗ АСУТП'!1:1)+1,1,1,"АПМДЗ АСУТП")),"") | H20: =IF(A20,INDIRECT(ADDRESS(2,MATCH(C20,'АПМДЗ АСУТП'!1:1)+2,1,1,"АПМДЗ АСУТП")),"") | J20: =IF(AND(A20=TRUE,'Тип разраб-ой док-ции'!$J$4=1),ROUNDUP(IF($F$5 =1,AF12,IF($F$5=2,AG12,IF($F$5 =3,AH12,"-")))/8,2),"-") -> #REF! | K20: =IF(AND(A20=TRUE,'Тип разраб-ой док-ции'!$J$3=1),ROUNDUP(IF($F$5 =1,AI12,IF($F$5=2,AJ12,IF($F$5 =3,AK12,"-")))/8,2),"-") -> #REF! | L20: =IF(AND(A20=TRUE,'Тип разраб-ой док-ции'!$J$2=1),ROUNDUP(IF($F$5 =1,AL12,IF($F$5=2,AM12,IF($F$5 =3,AN12,"-")))/8,2),"-") -> #REF! | M20: =IF(AND(A20=TRUE,'Тип разраб-ой док-ции'!$J$5=1),ROUNDUP(IF($F$5 =1,AO12,IF($F$5=2,AP12,IF($F$5 =3,AQ12,"-")))/8,2),"-") -> #REF! | N20: =SUM('Итоговый расчет АСУТП'!DG3:DG40) -> 0 | O20: ='PAM АСУТП'!$D$2 -> PAM Кол-во инсталляций | P20: =E14 -> 0 | R20: 1 | S20: Описание комплекса технических средств | T20: =ROUNDUP('Итоговый расчет АСУТП'!EZ13/8,2) -> #REF! | AA20: 1 | AE20: =IF(A28,MATCH(C28,'Документы АСУТП'!$E$3:$CU$3,0),"") + 4 -> #VALUE! | AF20: =INDIRECT(ADDRESS(107,AE20,1,1,"Документы АСУТП")) -> #VALUE! | AG20: =INDIRECT(ADDRESS(108,AE20,1,1,"Документы АСУТП")) -> #VALUE! | AH20: =INDIRECT(ADDRESS(109,AE20,1,1,"Документы АСУТП")) -> #VALUE! | AI20: =INDIRECT(ADDRESS(110,$AE20,1,1,"Документы АСУТП")) -> #VALUE! | AJ20: =INDIRECT(ADDRESS(111,$AE20,1,1,"Документы АСУТП")) -> #VALUE! | AK20: =INDIRECT(ADDRESS(112,$AE20,1,1,"Документы АСУТП")) -> #VALUE! | AL20: =INDIRECT(ADDRESS(113,$AE20,1,1,"Документы АСУТП")) -> #VALUE! | AM20: =INDIRECT(ADDRESS(114,$AE20,1,1,"Документы АСУТП")) -> #VALUE! | AN20: =INDIRECT(ADDRESS(115,$AE20,1,1,"Документы АСУТП")) -> #VALUE! | AO20: =INDIRECT(ADDRESS(116,$AE20,1,1,"Документы АСУТП")) -> #VALUE! | AP20: =INDIRECT(ADDRESS(117,$AE20,1,1,"Документы АСУТП")) -> #VALUE! | AQ20: =INDIRECT(ADDRESS(118,$AE20,1,1,"Документы АСУТП")) -> #VALUE!
A21: FALSE | B21: =IF(A21, "MFA","") | D21: =IF(A21,INDIRECT(ADDRESS(2,MATCH(C21,'MFA АСУТП'!1:1,0),1,1,"MFA АСУТП")),"") | F21: =IF(A21,INDIRECT(ADDRESS(2,MATCH(C21,'MFA АСУТП'!1:1,0)+1,1,1,"MFA АСУТП")),"") | H21: =IF(A21,INDIRECT(ADDRESS(2,MATCH(C21,'MFA АСУТП'!1:1,0)+2,1,1,"MFA АСУТП")),"") | J21: =IF(AND(A21=TRUE,'Тип разраб-ой док-ции'!$J$4=1),ROUNDUP(IF($F$5 =1,AF13,IF($F$5=2,AG13,IF($F$5 =3,AH13,"-")))/8,2),"-") -> #REF! | K21: =IF(AND(A21=TRUE,'Тип разраб-ой док-ции'!$J$3=1),ROUNDUP(IF($F$5 =1,AI13,IF($F$5=2,AJ13,IF($F$5 =3,AK13,"-")))/8,2),"-") -> #REF! | L21: =IF(AND(A21=TRUE,'Тип разраб-ой док-ции'!$J$2=1),ROUNDUP(IF($F$5 =1,AL13,IF($F$5=2,AM13,IF($F$5 =3,AN13,"-")))/8,2),"-") -> #REF! | M21: =IF(AND(A21=TRUE,'Тип разраб-ой док-ции'!$J$5=1),ROUNDUP(IF($F$5 =1,AO13,IF($F$5=2,AP13,IF($F$5 =3,AQ13,"-")))/8,2),"-") -> #REF! | N21: =SUM('Итоговый расчет АСУТП'!DI4:DI41) -> 0 | O21: ='PAM АСУТП'!$E$2 -> PAM Кол-во типов протоколов подключения | P21: =G14 -> 0 | R21: 1 | S21: Описание программного обеспечения | T21: =ROUNDUP('Итоговый расчет АСУТП'!EZ14/8,2) -> #REF! | AA21: 0 | AE21: =IF(A29,MATCH(C29,'Документы АСУТП'!$E$3:$CU$3,0),"") + 4 -> #VALUE! | AF21: =INDIRECT(ADDRESS(107,AE21,1,1,"Документы АСУТП")) -> #VALUE! | AG21: =INDIRECT(ADDRESS(108,AE21,1,1,"Документы АСУТП")) -> #VALUE! | AH21: =INDIRECT(ADDRESS(109,AE21,1,1,"Документы АСУТП")) -> #VALUE! | AI21: =INDIRECT(ADDRESS(110,$AE21,1,1,"Документы АСУТП")) -> #VALUE! | AJ21: =INDIRECT(ADDRESS(111,$AE21,1,1,"Документы АСУТП")) -> #VALUE! | AK21: =INDIRECT(ADDRESS(112,$AE21,1,1,"Документы АСУТП")) -> #VALUE! | AL21: =INDIRECT(ADDRESS(113,$AE21,1,1,"Документы АСУТП")) -> #VALUE! | AM21: =INDIRECT(ADDRESS(114,$AE21,1,1,"Документы АСУТП")) -> #VALUE! | AN21: =INDIRECT(ADDRESS(115,$AE21,1,1,"Документы АСУТП")) -> #VALUE! | AO21: =INDIRECT(ADDRESS(116,$AE21,1,1,"Документы АСУТП")) -> #VALUE! | AP21: =INDIRECT(ADDRESS(117,$AE21,1,1,"Документы АСУТП")) -> #VALUE! | AQ21: =INDIRECT(ADDRESS(118,$AE21,1,1,"Документы АСУТП")) -> #VALUE!
A22: FALSE | B22: =IF(A22, "ДИОД","") | D22: =IF(A22,INDIRECT(ADDRESS(2,MATCH(C22,'ДИОД АСУТП'!1:1,0),1,1,"ДИОД АСУТП")),"") | F22: =IF(A22,INDIRECT(ADDRESS(2,MATCH(C22,'ДИОД АСУТП'!1:1,0)+1,1,1,"ДИОД АСУТП")),"") | H22: =IF(A22,INDIRECT(ADDRESS(2,MATCH(C22,'ДИОД АСУТП'!1:1,0)+2,1,1,"ДИОД АСУТП")),"") | J22: =IF(AND(A22=TRUE,'Тип разраб-ой док-ции'!$J$4=1),ROUNDUP(IF($F$5 =1,AF14,IF($F$5=2,AG14,IF($F$5 =3,AH14,"-")))/8,2),"-") -> #REF! | K22: =IF(AND(A22=TRUE,'Тип разраб-ой док-ции'!$J$3=1),ROUNDUP(IF($F$5 =1,AI14,IF($F$5=2,AJ14,IF($F$5 =3,AK14,"-")))/8,2),"-") -> #REF! | L22: =IF(AND(A22=TRUE,'Тип разраб-ой док-ции'!$J$2=1),ROUNDUP(IF($F$5 =1,AL14,IF($F$5=2,AM14,IF($F$5 =3,AN14,"-")))/8,2),"-") -> #REF! | M22: =IF(AND(A22=TRUE,'Тип разраб-ой док-ции'!$J$5=1),ROUNDUP(IF($F$5 =1,AO14,IF($F$5=2,AP14,IF($F$5 =3,AQ14,"-")))/8,2),"-") -> #REF! | N22: =SUM('Итоговый расчет АСУТП'!DK4:DK41) -> 0 | O22: ='PAM АСУТП'!$F$2 -> PAM Неиспользуемый параметр | P22: =I14 -> 0 | R22: 1 | S22: Схема структурная | T22: =ROUNDUP('Итоговый расчет АСУТП'!EZ15/8,2) -> #REF! | AA22: 1 | AE22: =IF(A30,MATCH(C30,'Документы АСУТП'!$E$3:$CU$3,0),"") + 4 -> #VALUE! | AF22: =INDIRECT(ADDRESS(107,AE22,1,1,"Документы АСУТП")) -> #VALUE! | AG22: =INDIRECT(ADDRESS(108,AE22,1,1,"Документы АСУТП")) -> #VALUE! | AH22: =INDIRECT(ADDRESS(109,AE22,1,1,"Документы АСУТП")) -> #VALUE! | AI22: =INDIRECT(ADDRESS(110,$AE22,1,1,"Документы АСУТП")) -> #VALUE! | AJ22: =INDIRECT(ADDRESS(111,$AE22,1,1,"Документы АСУТП")) -> #VALUE! | AK22: =INDIRECT(ADDRESS(112,$AE22,1,1,"Документы АСУТП")) -> #VALUE! | AL22: =INDIRECT(ADDRESS(113,$AE22,1,1,"Документы АСУТП")) -> #VALUE! | AM22: =INDIRECT(ADDRESS(114,$AE22,1,1,"Документы АСУТП")) -> #VALUE! | AN22: =INDIRECT(ADDRESS(115,$AE22,1,1,"Документы АСУТП")) -> #VALUE! | AO22: =INDIRECT(ADDRESS(116,$AE22,1,1,"Документы АСУТП")) -> #VALUE! | AP22: =INDIRECT(ADDRESS(117,$AE22,1,1,"Документы АСУТП")) -> #VALUE! | AQ22: =INDIRECT(ADDRESS(118,$AE22,1,1,"Документы АСУТП")) -> #VALUE!
A23: FALSE | B23: =IF(A23, "СЗВ","") | D23: =IF(A23,INDIRECT(ADDRESS(2,MATCH(C23,'СЗВ АСУТП'!1:1),1,1,"СЗВ АСУТП")),"") | F23: =IF(A23,INDIRECT(ADDRESS(2,MATCH(C23,'СЗВ АСУТП'!1:1)+1,1,1,"СЗВ АСУТП")),"") | H23: =IF(A23,INDIRECT(ADDRESS(2,MATCH(C23,'СЗВ АСУТП'!1:1)+2,1,1,"СЗВ АСУТП")),"") | J23: =IF(AND(A23=TRUE,'Тип разраб-ой док-ции'!$J$4=1),ROUNDUP(IF($F$5 =1,AF15,IF($F$5=2,AG15,IF($F$5 =3,AH15,"-")))/8,2),"-") -> #REF! | K23: =IF(AND(A23=TRUE,'Тип разраб-ой док-ции'!$J$3=1),ROUNDUP(IF($F$5 =1,AI15,IF($F$5=2,AJ15,IF($F$5 =3,AK15,"-")))/8,2),"-") -> #REF! | L23: =IF(AND(A23=TRUE,'Тип разраб-ой док-ции'!$J$2=1),ROUNDUP(IF($F$5 =1,AL15,IF($F$5=2,AM15,IF($F$5 =3,AN15,"-")))/8,2),"-") -> #REF! | M23: =IF(AND(A23=TRUE,'Тип разраб-ой док-ции'!$J$5=1),ROUNDUP(IF($F$5 =1,AO15,IF($F$5=2,AP15,IF($F$5 =3,AQ15,"-")))/8,2),"-") -> #REF! | N23: =SUM('Итоговый расчет АСУТП'!DM4:DM41) -> 0 | O23: ='СКЗИ АСУТП'!D$2 -> СКЗИ Количество площадок | P23: =E15 -> 0 | R23: 1 | S23: Схема функциональная | T23: =ROUNDUP('Итоговый расчет АСУТП'!EZ16/8,2) -> #REF! | AA23: 0 | AE23: =IF(A31,MATCH(C31,'Документы АСУТП'!$E$3:$CU$3,0),"") + 4 -> #VALUE! | AF23: =INDIRECT(ADDRESS(107,AE23,1,1,"Документы АСУТП")) -> #VALUE! | AG23: =INDIRECT(ADDRESS(108,AE23,1,1,"Документы АСУТП")) -> #VALUE! | AH23: =INDIRECT(ADDRESS(109,AE23,1,1,"Документы АСУТП")) -> #VALUE! | AI23: =INDIRECT(ADDRESS(110,$AE23,1,1,"Документы АСУТП")) -> #VALUE! | AJ23: =INDIRECT(ADDRESS(111,$AE23,1,1,"Документы АСУТП")) -> #VALUE! | AK23: =INDIRECT(ADDRESS(112,$AE23,1,1,"Документы АСУТП")) -> #VALUE! | AL23: =INDIRECT(ADDRESS(113,$AE23,1,1,"Документы АСУТП")) -> #VALUE! | AM23: =INDIRECT(ADDRESS(114,$AE23,1,1,"Документы АСУТП")) -> #VALUE! | AN23: =INDIRECT(ADDRESS(115,$AE23,1,1,"Документы АСУТП")) -> #VALUE! | AO23: =INDIRECT(ADDRESS(116,$AE23,1,1,"Документы АСУТП")) -> #VALUE! | AP23: =INDIRECT(ADDRESS(117,$AE23,1,1,"Документы АСУТП")) -> #VALUE! | AQ23: =INDIRECT(ADDRESS(118,$AE23,1,1,"Документы АСУТП")) -> #VALUE!
A24: FALSE | B24: =IF(A24, "SOAR/IRP+SGRC","") | D24: =IF(A24,INDIRECT(ADDRESS(2,MATCH(C24,'SOAR АСУТП'!1:1),1,1,"SOAR АСУТП")),"") | F24: =IF(A24,INDIRECT(ADDRESS(2,MATCH(C24,'SOAR АСУТП'!1:1)+1,1,1,"SOAR АСУТП")),"") | H24: =IF(A24,INDIRECT(ADDRESS(2,MATCH(C24,'SOAR АСУТП'!1:1)+2,1,1,"SOAR АСУТП")),"") | J24: =IF(AND(A24=TRUE,'Тип разраб-ой док-ции'!$J$4=1),ROUNDUP(IF($F$5 =1,AF16,IF($F$5=2,AG16,IF($F$5 =3,AH16,"-")))/8,2),"-") -> #REF! | K24: =IF(AND(A24=TRUE,'Тип разраб-ой док-ции'!$J$3=1),ROUNDUP(IF($F$5 =1,AI16,IF($F$5=2,AJ16,IF($F$5 =3,AK16,"-")))/8,2),"-") -> #REF! | L24: =IF(AND(A24=TRUE,'Тип разраб-ой док-ции'!$J$2=1),ROUNDUP(IF($F$5 =1,AL16,IF($F$5=2,AM16,IF($F$5 =3,AN16,"-")))/8,2),"-") -> #REF! | M24: =IF(AND(A24=TRUE,'Тип разраб-ой док-ции'!$J$5=1),ROUNDUP(IF($F$5 =1,AO16,IF($F$5=2,AP16,IF($F$5 =3,AQ16,"-")))/8,2),"-") -> #REF! | N24: =SUM('Итоговый расчет АСУТП'!DO4:DO41) -> #REF! | O24: ='СКЗИ АСУТП'!E$2 -> СКЗИ Кол-во ЦУС | P24: =G15 -> 0 | S24: ТРП (дополнительно к ПЗ нужно выбрать документы из состава РД) | AA24: 0 | AE24: =IF(A32,MATCH(C32,'Документы АСУТП'!$E$3:$CU$3,0),"") + 4 -> #VALUE! | AF24: =INDIRECT(ADDRESS(107,AE24,1,1,"Документы АСУТП")) -> #VALUE! | AG24: =INDIRECT(ADDRESS(108,AE24,1,1,"Документы АСУТП")) -> #VALUE! | AH24: =INDIRECT(ADDRESS(109,AE24,1,1,"Документы АСУТП")) -> #VALUE! | AI24: =INDIRECT(ADDRESS(110,$AE24,1,1,"Документы АСУТП")) -> #VALUE! | AJ24: =INDIRECT(ADDRESS(111,$AE24,1,1,"Документы АСУТП")) -> #VALUE! | AK24: =INDIRECT(ADDRESS(112,$AE24,1,1,"Документы АСУТП")) -> #VALUE! | AL24: =INDIRECT(ADDRESS(113,$AE24,1,1,"Документы АСУТП")) -> #VALUE! | AM24: =INDIRECT(ADDRESS(114,$AE24,1,1,"Документы АСУТП")) -> #VALUE! | AN24: =INDIRECT(ADDRESS(115,$AE24,1,1,"Документы АСУТП")) -> #VALUE! | AO24: =INDIRECT(ADDRESS(116,$AE24,1,1,"Документы АСУТП")) -> #VALUE! | AP24: =INDIRECT(ADDRESS(117,$AE24,1,1,"Документы АСУТП")) -> #VALUE! | AQ24: =INDIRECT(ADDRESS(118,$AE24,1,1,"Документы АСУТП")) -> #VALUE!
A25: FALSE | B25: =IF(A25, "Виртуализация рабочих мест (VDI)","") | D25: =IF(A25,INDIRECT(ADDRESS(2,MATCH(C25,'VDI АСУТП'!1:1,0),1,1,"VDI АСУТП")),"") | F25: =IF(A25,INDIRECT(ADDRESS(2,MATCH(C25,'VDI АСУТП'!1:1,0)+1,1,1,"VDI АСУТП")),"") | H25: =IF(A25,INDIRECT(ADDRESS(2,MATCH(C25,'VDI АСУТП'!1:1,0)+2,1,1,"VDI АСУТП")),"") | J25: =IF(AND(A25=TRUE,'Тип разраб-ой док-ции'!$J$4=1),ROUNDUP(IF($F$5 =1,AF17,IF($F$5=2,AG17,IF($F$5 =3,AH17,"-")))/8,2),"-") -> #REF! | K25: =IF(AND(A25=TRUE,'Тип разраб-ой док-ции'!$J$3=1),ROUNDUP(IF($F$5 =1,AI17,IF($F$5=2,AJ17,IF($F$5 =3,AK17,"-")))/8,2),"-") -> #REF! | L25: =IF(AND(A25=TRUE,'Тип разраб-ой док-ции'!$J$2=1),ROUNDUP(IF($F$5 =1,AL17,IF($F$5=2,AM17,IF($F$5 =3,AN17,"-")))/8,2),"-") -> #REF! | M25: =IF(AND(A25=TRUE,'Тип разраб-ой док-ции'!$J$5=1),ROUNDUP(IF($F$5 =1,AO17,IF($F$5=2,AP17,IF($F$5 =3,AQ17,"-")))/8,2),"-") -> #REF! | N25: =SUM('Итоговый расчет АСУТП'!DQ4:DQ41) -> 0 | O25: ='СКЗИ АСУТП'!F$2 -> СКЗИ Количество пользователей | P25: =I15 -> 0 | R25: - | S25: Пояснительная записка к техническому проекту | T25: =ROUNDUP('Итоговый расчет АСУТП'!EZ18/8,2) -> 0 | AA25: 1 | AE25: =IF(A33,MATCH(C33,'Документы АСУТП'!$E$3:$CU$3,0),"") + 4 -> #VALUE! | AF25: =INDIRECT(ADDRESS(107,AE25,1,1,"Документы АСУТП")) -> #VALUE! | AG25: =INDIRECT(ADDRESS(108,AE25,1,1,"Документы АСУТП")) -> #VALUE! | AH25: =INDIRECT(ADDRESS(109,AE25,1,1,"Документы АСУТП")) -> #VALUE! | AI25: =INDIRECT(ADDRESS(110,$AE25,1,1,"Документы АСУТП")) -> #VALUE! | AJ25: =INDIRECT(ADDRESS(111,$AE25,1,1,"Документы АСУТП")) -> #VALUE! | AK25: =INDIRECT(ADDRESS(112,$AE25,1,1,"Документы АСУТП")) -> #VALUE! | AL25: =INDIRECT(ADDRESS(113,$AE25,1,1,"Документы АСУТП")) -> #VALUE! | AM25: =INDIRECT(ADDRESS(114,$AE25,1,1,"Документы АСУТП")) -> #VALUE! | AN25: =INDIRECT(ADDRESS(115,$AE25,1,1,"Документы АСУТП")) -> #VALUE! | AO25: =INDIRECT(ADDRESS(116,$AE25,1,1,"Документы АСУТП")) -> #VALUE! | AP25: =INDIRECT(ADDRESS(117,$AE25,1,1,"Документы АСУТП")) -> #VALUE! | AQ25: =INDIRECT(ADDRESS(118,$AE25,1,1,"Документы АСУТП")) -> #VALUE!
A26: FALSE | B26: =IF(A26, "СУБД","") | D26: =IF(A26,INDIRECT(ADDRESS(2,MATCH(C26,'СУБД АСУТП'!1:1,0),1,1,"СУБД АСУТП")),"") | F26: =IF(A26,INDIRECT(ADDRESS(2,MATCH(C26,'СУБД АСУТП'!1:1,0)+1,1,1,"СУБД АСУТП")),"") | H26: =IF(A26,INDIRECT(ADDRESS(2,MATCH(C26,'СУБД АСУТП'!1:1,0)+2,1,1,"СУБД АСУТП")),"") | J26: =IF(AND(A26=TRUE,'Тип разраб-ой док-ции'!$J$4=1),ROUNDUP(IF($F$5 =1,AF18,IF($F$5=2,AG18,IF($F$5 =3,AH18,"-")))/8,2),"-") -> #REF! | K26: =IF(AND(A26=TRUE,'Тип разраб-ой док-ции'!$J$3=1),ROUNDUP(IF($F$5 =1,AI18,IF($F$5=2,AJ18,IF($F$5 =3,AK18,"-")))/8,2),"-") -> #REF! | L26: =IF(AND(A26=TRUE,'Тип разраб-ой док-ции'!$J$2=1),ROUNDUP(IF($F$5 =1,AL18,IF($F$5=2,AM18,IF($F$5 =3,AN18,"-")))/8,2),"-") -> #REF! | M26: =IF(AND(A26=TRUE,'Тип разраб-ой док-ции'!$J$5=1),ROUNDUP(IF($F$5 =1,AO18,IF($F$5=2,AP18,IF($F$5 =3,AQ18,"-")))/8,2),"-") -> #REF! | N26: =SUM('Итоговый расчет АСУТП'!DS4:DS41) -> 0 | O26: ='АЗ АСУТП'!D$2 -> АЗ Кол-во серверных компонентов | P26: =E16 -> 0 | S26: РД | AA26: 1 | AE26: =IF(A34,MATCH(C34,'Документы АСУТП'!$E$3:$CU$3,0),"") + 4 -> #VALUE! | AF26: =INDIRECT(ADDRESS(107,AE26,1,1,"Документы АСУТП")) -> #VALUE! | AG26: =INDIRECT(ADDRESS(108,AE26,1,1,"Документы АСУТП")) -> #VALUE! | AH26: =INDIRECT(ADDRESS(109,AE26,1,1,"Документы АСУТП")) -> #VALUE! | AI26: =INDIRECT(ADDRESS(110,$AE26,1,1,"Документы АСУТП")) -> #VALUE! | AJ26: =INDIRECT(ADDRESS(111,$AE26,1,1,"Документы АСУТП")) -> #VALUE! | AK26: =INDIRECT(ADDRESS(112,$AE26,1,1,"Документы АСУТП")) -> #VALUE! | AL26: =INDIRECT(ADDRESS(113,$AE26,1,1,"Документы АСУТП")) -> #VALUE! | AM26: =INDIRECT(ADDRESS(114,$AE26,1,1,"Документы АСУТП")) -> #VALUE! | AN26: =INDIRECT(ADDRESS(115,$AE26,1,1,"Документы АСУТП")) -> #VALUE! | AO26: =INDIRECT(ADDRESS(116,$AE26,1,1,"Документы АСУТП")) -> #VALUE! | AP26: =INDIRECT(ADDRESS(117,$AE26,1,1,"Документы АСУТП")) -> #VALUE! | AQ26: =INDIRECT(ADDRESS(118,$AE26,1,1,"Документы АСУТП")) -> #VALUE!
A27: FALSE | B27: =IF(A27, "Платформа взаимодействия с главным центром ГосСОПКА","") | D27: =IF(A27,INDIRECT(ADDRESS(2,MATCH(C27,'ГОССОПКА АСУТП'!1:1),1,1,"ГОССОПКА АСУТП")),"") | F27: =IF(A27,INDIRECT(ADDRESS(2,MATCH(C27,'ГОССОПКА АСУТП'!1:1)+1,1,1,"ГОССОПКА АСУТП")),"") | H27: =IF(A27,INDIRECT(ADDRESS(2,MATCH(C27,'ГОССОПКА АСУТП'!1:1)+2,1,1,"ГОССОПКА АСУТП")),"") | J27: =IF(AND(A27=TRUE,'Тип разраб-ой док-ции'!$J$4=1),ROUNDUP(IF($F$5 =1,AF19,IF($F$5=2,AG19,IF($F$5 =3,AH19,"-")))/8,2),"-") -> #REF! | K27: =IF(AND(A27=TRUE,'Тип разраб-ой док-ции'!$J$3=1),ROUNDUP(IF($F$5 =1,AI19,IF($F$5=2,AJ19,IF($F$5 =3,AK19,"-")))/8,2),"-") -> #REF! | L27: =IF(AND(A27=TRUE,'Тип разраб-ой док-ции'!$J$2=1),ROUNDUP(IF($F$5 =1,AL19,IF($F$5=2,AM19,IF($F$5 =3,AN19,"-")))/8,2),"-") -> #REF! | M27: =IF(AND(A27=TRUE,'Тип разраб-ой док-ции'!$J$5=1),ROUNDUP(IF($F$5 =1,AO19,IF($F$5=2,AP19,IF($F$5 =3,AQ19,"-")))/8,2),"-") -> #REF! | N27: =SUM('Итоговый расчет АСУТП'!DU4:DU41) -> 0 | O27: ='АЗ АСУТП'!E$2 -> АЗ Кол-во профилей | P27: =G16 -> 0 | R27: 1 | S27: Спецификация оборудования | T27: =ROUNDUP('Итоговый расчет АСУТП'!EZ20/8,2) -> #REF! | AA27: 1 | AE27: =IF(A35,MATCH(C35,'Документы АСУТП'!$E$3:$CU$3,0),"") + 4 -> #VALUE! | AF27: =INDIRECT(ADDRESS(107,AE27,1,1,"Документы АСУТП")) -> #VALUE! | AG27: =INDIRECT(ADDRESS(108,AE27,1,1,"Документы АСУТП")) -> #VALUE! | AH27: =INDIRECT(ADDRESS(109,AE27,1,1,"Документы АСУТП")) -> #VALUE! | AI27: =INDIRECT(ADDRESS(110,$AE27,1,1,"Документы АСУТП")) -> #VALUE! | AJ27: =INDIRECT(ADDRESS(111,$AE27,1,1,"Документы АСУТП")) -> #VALUE! | AK27: =INDIRECT(ADDRESS(112,$AE27,1,1,"Документы АСУТП")) -> #VALUE! | AL27: =INDIRECT(ADDRESS(113,$AE27,1,1,"Документы АСУТП")) -> #VALUE! | AM27: =INDIRECT(ADDRESS(114,$AE27,1,1,"Документы АСУТП")) -> #VALUE! | AN27: =INDIRECT(ADDRESS(115,$AE27,1,1,"Документы АСУТП")) -> #VALUE! | AO27: =INDIRECT(ADDRESS(116,$AE27,1,1,"Документы АСУТП")) -> #VALUE! | AP27: =INDIRECT(ADDRESS(117,$AE27,1,1,"Документы АСУТП")) -> #VALUE! | AQ27: =INDIRECT(ADDRESS(118,$AE27,1,1,"Документы АСУТП")) -> #VALUE!
A28: FALSE | B28: =IF(A28, "TLS шлюз","") | D28: =IF(A28,INDIRECT(ADDRESS(2,MATCH(C28,'TLS АСУТП'!1:1),1,1,"TLS АСУТП")),"") | F28: =IF(A28,INDIRECT(ADDRESS(2,MATCH(C28,'TLS АСУТП'!1:1,0)+1,1,1,"TLS АСУТП")),"") | H28: =IF(A28,INDIRECT(ADDRESS(2,MATCH(C28,'TLS АСУТП'!1:1)+2,1,1,"TLS АСУТП")),"") | J28: =IF(AND(A28=TRUE,'Тип разраб-ой док-ции'!$J$4=1),ROUNDUP(IF($F$5 =1,AF20,IF($F$5=2,AG20,IF($F$5 =3,AH20,"-")))/8,2),"-") -> #REF! | K28: =IF(AND(A28=TRUE,'Тип разраб-ой док-ции'!$J$3=1),ROUNDUP(IF($F$5 =1,AI20,IF($F$5=2,AJ20,IF($F$5 =3,AK20,"-")))/8,2),"-") -> #REF! | L28: =IF(AND(A28=TRUE,'Тип разраб-ой док-ции'!$J$2=1),ROUNDUP(IF($F$5 =1,AL20,IF($F$5=2,AM20,IF($F$5 =3,AN20,"-")))/8,2),"-") -> #REF! | M28: =IF(AND(A28=TRUE,'Тип разраб-ой док-ции'!$J$5=1),ROUNDUP(IF($F$5 =1,AO20,IF($F$5=2,AP20,IF($F$5 =3,AQ20,"-")))/8,2),"-") -> #REF! | N28: =SUM('Итоговый расчет АСУТП'!DW4:DW41) -> 0 | O28: ='АЗ АСУТП'!F$2 -> АЗ Кол-во сканируемых узлов | P28: =I16 -> 0 | R28: 1 | S28: Инструкция по установке и настройке | T28: =ROUNDUP('Итоговый расчет АСУТП'!EZ21/8,2) -> #REF! | AA28: 0 | AE28: =IF(A36,MATCH(C36,'Документы АСУТП'!$E$3:$CU$3,0),"") + 4 -> #VALUE! | AF28: =INDIRECT(ADDRESS(107,AE28,1,1,"Документы АСУТП")) -> #VALUE! | AG28: =INDIRECT(ADDRESS(108,AE28,1,1,"Документы АСУТП")) -> #VALUE! | AH28: =INDIRECT(ADDRESS(109,AE28,1,1,"Документы АСУТП")) -> #VALUE! | AI28: =INDIRECT(ADDRESS(110,$AE28,1,1,"Документы АСУТП")) -> #VALUE! | AJ28: =INDIRECT(ADDRESS(111,$AE28,1,1,"Документы АСУТП")) -> #VALUE! | AK28: =INDIRECT(ADDRESS(112,$AE28,1,1,"Документы АСУТП")) -> #VALUE! | AL28: =INDIRECT(ADDRESS(113,$AE28,1,1,"Документы АСУТП")) -> #VALUE! | AM28: =INDIRECT(ADDRESS(114,$AE28,1,1,"Документы АСУТП")) -> #VALUE! | AN28: =INDIRECT(ADDRESS(115,$AE28,1,1,"Документы АСУТП")) -> #VALUE! | AO28: =INDIRECT(ADDRESS(116,$AE28,1,1,"Документы АСУТП")) -> #VALUE! | AP28: =INDIRECT(ADDRESS(117,$AE28,1,1,"Документы АСУТП")) -> #VALUE! | AQ28: =INDIRECT(ADDRESS(118,$AE28,1,1,"Документы АСУТП")) -> #VALUE!
A29: FALSE | B29: =IF(A29, "DCAP / DAG","") | D29: =IF(A29,INDIRECT(ADDRESS(2,MATCH(C29,'DCAP АСУТП'!1:1),1,1,"DCAP АСУТП")),"") | F29: =IF(A29,INDIRECT(ADDRESS(2,MATCH(C29,'DCAP АСУТП'!1:1)+1,1,1,"DCAP АСУТП")),"") | H29: =IF(A29,INDIRECT(ADDRESS(2,MATCH(C29,'DCAP АСУТП'!1:1)+2,1,1,"DCAP АСУТП")),"") | J29: =IF(AND(A29=TRUE,'Тип разраб-ой док-ции'!$J$4=1),ROUNDUP(IF($F$5 =1,AF21,IF($F$5=2,AG21,IF($F$5 =3,AH21,"-")))/8,2),"-") -> #REF! | K29: =IF(AND(A29=TRUE,'Тип разраб-ой док-ции'!$J$3=1),ROUNDUP(IF($F$5 =1,AI21,IF($F$5=2,AJ21,IF($F$5 =3,AK21,"-")))/8,2),"-") -> #REF! | L29: =IF(AND(A29=TRUE,'Тип разраб-ой док-ции'!$J$2=1),ROUNDUP(IF($F$5 =1,AL21,IF($F$5=2,AM21,IF($F$5 =3,AN21,"-")))/8,2),"-") -> #REF! | M29: =IF(AND(A29=TRUE,'Тип разраб-ой док-ции'!$J$5=1),ROUNDUP(IF($F$5 =1,AO21,IF($F$5=2,AP21,IF($F$5 =3,AQ21,"-")))/8,2),"-") -> #REF! | N29: =SUM('Итоговый расчет АСУТП'!DY4:DY41) -> 0 | O29: ='РК АСУТП'!D$2 -> РК Кол-во площадок с серверными компонентами | P29: =E17 -> 0 | R29: - | S29: Схема соединений внешних проводок | T29: =ROUNDUP('Итоговый расчет АСУТП'!EZ22/8,2) -> 0 | AA29: 1 | AE29: =IF(A37,MATCH(C37,'Документы АСУТП'!$E$3:$CU$3,0),"") + 4 -> #VALUE! | AF29: =INDIRECT(ADDRESS(107,AE29,1,1,"Документы АСУТП")) -> #VALUE! | AG29: =INDIRECT(ADDRESS(108,AE29,1,1,"Документы АСУТП")) -> #VALUE! | AH29: =INDIRECT(ADDRESS(109,AE29,1,1,"Документы АСУТП")) -> #VALUE! | AI29: =INDIRECT(ADDRESS(110,$AE29,1,1,"Документы АСУТП")) -> #VALUE! | AJ29: =INDIRECT(ADDRESS(111,$AE29,1,1,"Документы АСУТП")) -> #VALUE! | AK29: =INDIRECT(ADDRESS(112,$AE29,1,1,"Документы АСУТП")) -> #VALUE! | AL29: =INDIRECT(ADDRESS(113,$AE29,1,1,"Документы АСУТП")) -> #VALUE! | AM29: =INDIRECT(ADDRESS(114,$AE29,1,1,"Документы АСУТП")) -> #VALUE! | AN29: =INDIRECT(ADDRESS(115,$AE29,1,1,"Документы АСУТП")) -> #VALUE! | AO29: =INDIRECT(ADDRESS(116,$AE29,1,1,"Документы АСУТП")) -> #VALUE! | AP29: =INDIRECT(ADDRESS(117,$AE29,1,1,"Документы АСУТП")) -> #VALUE! | AQ29: =INDIRECT(ADDRESS(118,$AE29,1,1,"Документы АСУТП")) -> #VALUE!
A30: FALSE | B30: =IF(A30, "Контроль конфигураций","") | D30: =IF(A30,INDIRECT(ADDRESS(2,MATCH(C30,'DO АСУТП'!1:1),1,1,"КОНФИГ АСУТП")),"") | F30: =IF(A30,INDIRECT(ADDRESS(2,MATCH(C30,'DO АСУТП'!1:1)+1,1,1,"КОНФИГ АСУТП")),"") | H30: =IF(A30,INDIRECT(ADDRESS(2,MATCH(C30,'DO АСУТП'!1:1)+2,1,1,"КОНФИГ АСУТП")),"") | J30: =IF(AND(A30=TRUE,'Тип разраб-ой док-ции'!$J$4=1),ROUNDUP(IF($F$5 =1,AF22,IF($F$5=2,AG22,IF($F$5 =3,AH22,"-")))/8,2),"-") -> #REF! | K30: =IF(AND(A30=TRUE,'Тип разраб-ой док-ции'!$J$3=1),ROUNDUP(IF($F$5 =1,AI22,IF($F$5=2,AJ22,IF($F$5 =3,AK22,"-")))/8,2),"-") -> #REF! | L30: =IF(AND(A30=TRUE,'Тип разраб-ой док-ции'!$J$2=1),ROUNDUP(IF($F$5 =1,AL22,IF($F$5=2,AM22,IF($F$5 =3,AN22,"-")))/8,2),"-") -> #REF! | M30: =IF(AND(A30=TRUE,'Тип разраб-ой док-ции'!$J$5=1),ROUNDUP(IF($F$5 =1,AO22,IF($F$5=2,AP22,IF($F$5 =3,AQ22,"-")))/8,2),"-") -> #REF! | N30: =SUM('Итоговый расчет АСУТП'!EA4:EA41) -> 0 | O30: ='РК АСУТП'!E$2 -> РК Кол-во типов целевых систем для РК | P30: =G17 -> 0 | R30: - | S30: Таблица соединений и подключений | T30: =ROUNDUP('Итоговый расчет АСУТП'!EZ23/8,2) -> 0 | AA30: 1 | AE30: =IF(A38,MATCH(C38,'Документы АСУТП'!$E$3:$CU$3,0),"") + 4 -> #VALUE! | AF30: =INDIRECT(ADDRESS(107,AE30,1,1,"Документы АСУТП")) -> #VALUE! | AG30: =INDIRECT(ADDRESS(108,AE30,1,1,"Документы АСУТП")) -> #VALUE! | AH30: =INDIRECT(ADDRESS(109,AE30,1,1,"Документы АСУТП")) -> #VALUE! | AI30: =INDIRECT(ADDRESS(110,$AE30,1,1,"Документы АСУТП")) -> #VALUE! | AJ30: =INDIRECT(ADDRESS(111,$AE30,1,1,"Документы АСУТП")) -> #VALUE! | AK30: =INDIRECT(ADDRESS(112,$AE30,1,1,"Документы АСУТП")) -> #VALUE! | AL30: =INDIRECT(ADDRESS(113,$AE30,1,1,"Документы АСУТП")) -> #VALUE! | AM30: =INDIRECT(ADDRESS(114,$AE30,1,1,"Документы АСУТП")) -> #VALUE! | AN30: =INDIRECT(ADDRESS(115,$AE30,1,1,"Документы АСУТП")) -> #VALUE! | AO30: =INDIRECT(ADDRESS(116,$AE30,1,1,"Документы АСУТП")) -> #VALUE! | AP30: =INDIRECT(ADDRESS(117,$AE30,1,1,"Документы АСУТП")) -> #VALUE! | AQ30: =INDIRECT(ADDRESS(118,$AE30,1,1,"Документы АСУТП")) -> #VALUE!
A31: FALSE | B31: =IF(A31, "NTA","") | D31: =IF(A31,INDIRECT(ADDRESS(2,MATCH(C31,'NTA АСУТП'!1:1),1,1,"NTA АСУТП")),"") | F31: =IF(A31,INDIRECT(ADDRESS(2,MATCH(C31,'NTA АСУТП'!1:1)+1,1,1,"NTA АСУТП")),"") | H31: =IF(A31,INDIRECT(ADDRESS(2,MATCH(C31,'NTA АСУТП'!1:1)+2,1,1,"NTA АСУТП")),"") | J31: =IF(AND(A31=TRUE,'Тип разраб-ой док-ции'!$J$4=1),ROUNDUP(IF($F$5 =1,AF23,IF($F$5=2,AG23,IF($F$5 =3,AH23,"-")))/8,2),"-") -> #REF! | K31: =IF(AND(A31=TRUE,'Тип разраб-ой док-ции'!$J$3=1),ROUNDUP(IF($F$5 =1,AI23,IF($F$5=2,AJ23,IF($F$5 =3,AK23,"-")))/8,2),"-") -> #REF! | L31: =IF(AND(A31=TRUE,'Тип разраб-ой док-ции'!$J$2=1),ROUNDUP(IF($F$5 =1,AL23,IF($F$5=2,AM23,IF($F$5 =3,AN23,"-")))/8,2),"-") -> #REF! | M31: =IF(AND(A31=TRUE,'Тип разраб-ой док-ции'!$J$5=1),ROUNDUP(IF($F$5 =1,AO23,IF($F$5=2,AP23,IF($F$5 =3,AQ23,"-")))/8,2),"-") -> #REF! | N31: =SUM('Итоговый расчет АСУТП'!EC4:EC41) -> 0 | O31: ='РК АСУТП'!F$2 -> Количество мест хранения РК | P31: =I17 -> 0 | R31: - | S31: План расположения | T31: =ROUNDUP('Итоговый расчет АСУТП'!EZ24/8,2) -> 0 | AA31: 0 | AE31: =IF(A39,MATCH(C39,'Документы АСУТП'!$E$3:$CU$3,0),"") + 4 -> #VALUE! | AF31: =INDIRECT(ADDRESS(107,AE31,1,1,"Документы АСУТП")) -> #VALUE! | AG31: =INDIRECT(ADDRESS(108,AE31,1,1,"Документы АСУТП")) -> #VALUE! | AH31: =INDIRECT(ADDRESS(109,AE31,1,1,"Документы АСУТП")) -> #VALUE! | AI31: =INDIRECT(ADDRESS(110,$AE31,1,1,"Документы АСУТП")) -> #VALUE! | AJ31: =INDIRECT(ADDRESS(111,$AE31,1,1,"Документы АСУТП")) -> #VALUE! | AK31: =INDIRECT(ADDRESS(112,$AE31,1,1,"Документы АСУТП")) -> #VALUE! | AL31: =INDIRECT(ADDRESS(113,$AE31,1,1,"Документы АСУТП")) -> #VALUE! | AM31: =INDIRECT(ADDRESS(114,$AE31,1,1,"Документы АСУТП")) -> #VALUE! | AN31: =INDIRECT(ADDRESS(115,$AE31,1,1,"Документы АСУТП")) -> #VALUE! | AO31: =INDIRECT(ADDRESS(116,$AE31,1,1,"Документы АСУТП")) -> #VALUE! | AP31: =INDIRECT(ADDRESS(117,$AE31,1,1,"Документы АСУТП")) -> #VALUE! | AQ31: =INDIRECT(ADDRESS(118,$AE31,1,1,"Документы АСУТП")) -> #VALUE!
A32: FALSE | B32: =IF(A32, "SEG","") | D32: =IF(A32,INDIRECT(ADDRESS(2,MATCH(C32,'SEG АСУТП'!1:1),1,1,"SEG АСУТП")),"") | F32: =IF(A32,INDIRECT(ADDRESS(2,MATCH(C32,'SEG АСУТП'!1:1)+1,1,1,"SEG АСУТП")),"") | H32: =IF(A32,INDIRECT(ADDRESS(2,MATCH(C32,'SEG АСУТП'!1:1)+2,1,1,"SEG АСУТП")),"") | J32: =IF(AND(A32=TRUE,'Тип разраб-ой док-ции'!$J$4=1),ROUNDUP(IF($F$5 =1,AF24,IF($F$5=2,AG24,IF($F$5 =3,AH24,"-")))/8,2),"-") -> #REF! | K32: =IF(AND(A32=TRUE,'Тип разраб-ой док-ции'!$J$3=1),ROUNDUP(IF($F$5 =1,AI24,IF($F$5=2,AJ24,IF($F$5 =3,AK24,"-")))/8,2),"-") -> #REF! | L32: =IF(AND(A32=TRUE,'Тип разраб-ой док-ции'!$J$2=1),ROUNDUP(IF($F$5 =1,AL24,IF($F$5=2,AM24,IF($F$5 =3,AN24,"-")))/8,2),"-") -> #REF! | M32: =IF(AND(A32=TRUE,'Тип разраб-ой док-ции'!$J$5=1),ROUNDUP(IF($F$5 =1,AO24,IF($F$5=2,AP24,IF($F$5 =3,AQ24,"-")))/8,2),"-") -> #REF! | N32: =SUM('Итоговый расчет АСУТП'!EE4:EE41) -> 0 | O32: ='IDS АСУТП'!D$2 -> IDS Кол-во центров управления | P32: =E18 -> 0 | R32: - | S32: Паспорт | T32: =ROUNDUP('Итоговый расчет АСУТП'!EZ25/8,2) -> 0 | AA32: 1 | AE32: =IF(A40,MATCH(C40,'Документы АСУТП'!$E$3:$CU$3,0),"") + 4 -> #VALUE! | AF32: =INDIRECT(ADDRESS(107,AE32,1,1,"Документы АСУТП")) -> #VALUE! | AG32: =INDIRECT(ADDRESS(108,AE32,1,1,"Документы АСУТП")) -> #VALUE! | AH32: =INDIRECT(ADDRESS(109,AE32,1,1,"Документы АСУТП")) -> #VALUE! | AI32: =INDIRECT(ADDRESS(110,$AE32,1,1,"Документы АСУТП")) -> #VALUE! | AJ32: =INDIRECT(ADDRESS(111,$AE32,1,1,"Документы АСУТП")) -> #VALUE! | AK32: =INDIRECT(ADDRESS(112,$AE32,1,1,"Документы АСУТП")) -> #VALUE! | AL32: =INDIRECT(ADDRESS(113,$AE32,1,1,"Документы АСУТП")) -> #VALUE! | AM32: =INDIRECT(ADDRESS(114,$AE32,1,1,"Документы АСУТП")) -> #VALUE! | AN32: =INDIRECT(ADDRESS(115,$AE32,1,1,"Документы АСУТП")) -> #VALUE! | AO32: =INDIRECT(ADDRESS(116,$AE32,1,1,"Документы АСУТП")) -> #VALUE! | AP32: =INDIRECT(ADDRESS(117,$AE32,1,1,"Документы АСУТП")) -> #VALUE! | AQ32: =INDIRECT(ADDRESS(118,$AE32,1,1,"Документы АСУТП")) -> #VALUE!
A33: FALSE | B33: =IF(A33, "APT","") | D33: =IF(A33,INDIRECT(ADDRESS(2,MATCH(C33,'APT АСУТП'!1:1),1,1,"APT АСУТП")),"") | F33: =IF(A33,INDIRECT(ADDRESS(2,MATCH(C33,'APT АСУТП'!1:1)+1,1,1,"APT АСУТП")),"") | H33: =IF(A33,INDIRECT(ADDRESS(2,MATCH(C33,'APT АСУТП'!1:1)+2,1,1,"APT АСУТП")),"") | J33: =IF(AND(A33=TRUE,'Тип разраб-ой док-ции'!$J$4=1),ROUNDUP(IF($F$5 =1,AF25,IF($F$5=2,AG25,IF($F$5 =3,AH25,"-")))/8,2),"-") -> #REF! | K33: =IF(AND(A33=TRUE,'Тип разраб-ой док-ции'!$J$3=1),ROUNDUP(IF($F$5 =1,AI25,IF($F$5=2,AJ25,IF($F$5 =3,AK25,"-")))/8,2),"-") -> #REF! | L33: =IF(AND(A33=TRUE,'Тип разраб-ой док-ции'!$J$2=1),ROUNDUP(IF($F$5 =1,AL25,IF($F$5=2,AM25,IF($F$5 =3,AN25,"-")))/8,2),"-") -> #REF! | M33: =IF(AND(A33=TRUE,'Тип разраб-ой док-ции'!$J$5=1),ROUNDUP(IF($F$5 =1,AO25,IF($F$5=2,AP25,IF($F$5 =3,AQ25,"-")))/8,2),"-") -> #REF! | N33: =SUM('Итоговый расчет АСУТП'!EG4:EG41) -> 0 | O33: ='IDS АСУТП'!E$2 -> IDS Кол-во сенсоров | P33: =G18 -> 0 | R33: 1 | S33: ПиМИ | T33: =ROUNDUP('Итоговый расчет АСУТП'!EZ26/8,2) -> #REF! | AA33: 1 | AD33: НСД | AE33: =IF(A19,MATCH(C19,'Документы АСУТП'!$E$3:$CU$3,0),"") + 4 -> #VALUE! | AF33: =INDIRECT(ADDRESS(107,AE33,1,1,"Документы АСУТП")) -> #VALUE! | AG33: =INDIRECT(ADDRESS(108,AE33,1,1,"Документы АСУТП")) -> #VALUE! | AH33: =INDIRECT(ADDRESS(109,AE33,1,1,"Документы АСУТП")) -> #VALUE! | AI33: =INDIRECT(ADDRESS(110,$AE33,1,1,"Документы АСУТП")) -> #VALUE! | AJ33: =INDIRECT(ADDRESS(111,$AE33,1,1,"Документы АСУТП")) -> #VALUE! | AK33: =INDIRECT(ADDRESS(112,$AE33,1,1,"Документы АСУТП")) -> #VALUE! | AL33: =INDIRECT(ADDRESS(113,$AE33,1,1,"Документы АСУТП")) -> #VALUE! | AM33: =INDIRECT(ADDRESS(114,$AE33,1,1,"Документы АСУТП")) -> #VALUE! | AN33: =INDIRECT(ADDRESS(115,$AE33,1,1,"Документы АСУТП")) -> #VALUE! | AO33: =INDIRECT(ADDRESS(116,$AE33,1,1,"Документы АСУТП")) -> #VALUE! | AP33: =INDIRECT(ADDRESS(117,$AE33,1,1,"Документы АСУТП")) -> #VALUE! | AQ33: =INDIRECT(ADDRESS(118,$AE33,1,1,"Документы АСУТП")) -> #VALUE!
A34: FALSE | B34: =IF(A34, "NAC","") | D34: =IF(A34,INDIRECT(ADDRESS(2,MATCH(C34,'NAC АСУТП'!1:1),1,1,"NAC АСУТП")),"") | F34: =IF(A34,INDIRECT(ADDRESS(2,MATCH(C34,'NAC АСУТП'!1:1)+1,1,1,"NAC АСУТП")),"") | H34: =IF(A34,INDIRECT(ADDRESS(2,MATCH(C34,'NAC АСУТП'!1:1)+2,1,1,"NAC АСУТП")),"") | J34: =IF(AND(A34=TRUE,'Тип разраб-ой док-ции'!$J$4=1),ROUNDUP(IF($F$5 =1,AF26,IF($F$5=2,AG26,IF($F$5 =3,AH26,"-")))/8,2),"-") -> #REF! | K34: =IF(AND(A34=TRUE,'Тип разраб-ой док-ции'!$J$3=1),ROUNDUP(IF($F$5 =1,AI26,IF($F$5=2,AJ26,IF($F$5 =3,AK26,"-")))/8,2),"-") -> #REF! | L34: =IF(AND(A34=TRUE,'Тип разраб-ой док-ции'!$J$2=1),ROUNDUP(IF($F$5 =1,AL26,IF($F$5=2,AM26,IF($F$5 =3,AN26,"-")))/8,2),"-") -> #REF! | M34: =IF(AND(A34=TRUE,'Тип разраб-ой док-ции'!$J$5=1),ROUNDUP(IF($F$5 =1,AO26,IF($F$5=2,AP26,IF($F$5 =3,AQ26,"-")))/8,2),"-") -> #REF! | N34: =SUM('Итоговый расчет АСУТП'!EI4:EI41) -> 0 | O34: ='IDS АСУТП'!F$2 -> IDS Кол-во точек мониторинга | P34: =I18 -> 0 | R34: 1 | S34: Технические условия для монтажа оборудования | T34: =ROUNDUP('Итоговый расчет АСУТП'!EZ27/8,2) -> #REF! | AA34: 0
A35: FALSE | B35: =IF(A35, "Sandbox","") | D35: =IF(A35,INDIRECT(ADDRESS(2,MATCH(C35,'SANDBOX АСУТП'!1:1),1,1,"SANDBOX АСУТП")),"") | F35: =IF(A35,INDIRECT(ADDRESS(2,MATCH(C35,'SANDBOX АСУТП'!1:1)+1,1,1,"SANDBOX АСУТП")),"") | H35: =IF(A35,INDIRECT(ADDRESS(2,MATCH(C35,'SANDBOX АСУТП'!1:1)+2,1,1,"SANDBOX АСУТП")),"") | J35: =IF(AND(A35=TRUE,'Тип разраб-ой док-ции'!$J$4=1),ROUNDUP(IF($F$5 =1,AF27,IF($F$5=2,AG27,IF($F$5 =3,AH27,"-")))/8,2),"-") -> #REF! | K35: =IF(AND(A35=TRUE,'Тип разраб-ой док-ции'!$J$3=1),ROUNDUP(IF($F$5 =1,AI27,IF($F$5=2,AJ27,IF($F$5 =3,AK27,"-")))/8,2),"-") -> #REF! | L35: =IF(AND(A35=TRUE,'Тип разраб-ой док-ции'!$J$2=1),ROUNDUP(IF($F$5 =1,AL27,IF($F$5=2,AM27,IF($F$5 =3,AN27,"-")))/8,2),"-") -> #REF! | M35: =IF(AND(A35=TRUE,'Тип разраб-ой док-ции'!$J$5=1),ROUNDUP(IF($F$5 =1,AO27,IF($F$5=2,AP27,IF($F$5 =3,AQ27,"-")))/8,2),"-") -> #REF! | N35: =SUM('Итоговый расчет АСУТП'!EK4:EK41) -> 0 | O35: ='НСД АСУТП'!$D$2 -> НСД Количество площадок с серверными компонентами подсистемы | P35: =E19 -> 0 | R35: 1 | S35: Эскизная схема расположения оборудования | T35: =ROUNDUP('Итоговый расчет АСУТП'!EZ28/8,2) -> #REF! | AA35: 1
A36: FALSE | B36: =IF(A36, "EDR","") | D36: =IF(A36,INDIRECT(ADDRESS(2,MATCH(C36,'EDR АСУТП'!1:1),1,1,"EDR АСУТП")),"") | F36: =IF(A36,INDIRECT(ADDRESS(2,MATCH(C36,'EDR АСУТП'!1:1)+1,1,1,"EDR АСУТП")),"") | H36: =IF(A36,INDIRECT(ADDRESS(2,MATCH(C36,'EDR АСУТП'!1:1)+2,1,1,"EDR АСУТП")),"") | J36: =IF(AND(A36=TRUE,'Тип разраб-ой док-ции'!$J$4=1),ROUNDUP(IF($F$5 =1,AF28,IF($F$5=2,AG28,IF($F$5 =3,AH28,"-")))/8,2),"-") -> #REF! | K36: =IF(AND(A36=TRUE,'Тип разраб-ой док-ции'!$J$3=1),ROUNDUP(IF($F$5 =1,AI28,IF($F$5=2,AJ28,IF($F$5 =3,AK28,"-")))/8,2),"-") -> #REF! | L36: =IF(AND(A36=TRUE,'Тип разраб-ой док-ции'!$J$2=1),ROUNDUP(IF($F$5 =1,AL28,IF($F$5=2,AM28,IF($F$5 =3,AN28,"-")))/8,2),"-") -> #REF! | M36: =IF(AND(A36=TRUE,'Тип разраб-ой док-ции'!$J$5=1),ROUNDUP(IF($F$5 =1,AO28,IF($F$5=2,AP28,IF($F$5 =3,AQ28,"-")))/8,2),"-") -> #REF! | N36: =SUM('Итоговый расчет АСУТП'!EM4:EM41) -> 0 | O36: ='НСД АСУТП'!$E$2 -> НСД Кол-во типов агентов | P36: =G19 -> 0 | R36: 1 | S36: Сетевая схема L2 | T36: =ROUNDUP('Итоговый расчет АСУТП'!EZ29/8,2) -> #REF! | AA36: 0
A37: FALSE | B37: =IF(A37, "WAF","") | D37: =IF(A37,INDIRECT(ADDRESS(2,MATCH(C37,'WAF АСУТП'!1:1),1,1,"WAF АСУТП")),"") | F37: =IF(A37,INDIRECT(ADDRESS(2,MATCH(C37,'WAF АСУТП'!1:1)+1,1,1,"WAF АСУТП")),"") | H37: =IF(A37,INDIRECT(ADDRESS(2,MATCH(C37,'WAF АСУТП'!1:1)+2,1,1,"WAF АСУТП")),"") | J37: =IF(AND(A37=TRUE,'Тип разраб-ой док-ции'!$J$4=1),ROUNDUP(IF($F$5 =1,AF29,IF($F$5=2,AG29,IF($F$5 =3,AH29,"-")))/8,2),"-") -> #REF! | K37: =IF(AND(A37=TRUE,'Тип разраб-ой док-ции'!$J$3=1),ROUNDUP(IF($F$5 =1,AI29,IF($F$5=2,AJ29,IF($F$5 =3,AK29,"-")))/8,2),"-") -> #REF! | L37: =IF(AND(A37=TRUE,'Тип разраб-ой док-ции'!$J$2=1),ROUNDUP(IF($F$5 =1,AL29,IF($F$5=2,AM29,IF($F$5 =3,AN29,"-")))/8,2),"-") -> #REF! | M37: =IF(AND(A37=TRUE,'Тип разраб-ой док-ции'!$J$5=1),ROUNDUP(IF($F$5 =1,AO29,IF($F$5=2,AP29,IF($F$5 =3,AQ29,"-")))/8,2),"-") -> #REF! | N37: =SUM('Итоговый расчет АСУТП'!EO4:EO41) -> 0 | O37: ='НСД АСУТП'!$F$2 -> НСД Кол-во серверов безопасности | P37: =I19 -> 0 | R37: 1 | S37: Сетевая схема L3 | T37: =ROUNDUP('Итоговый расчет АСУТП'!EZ30/8,2) -> #REF! | AA37: 1
A38: FALSE | B38: =IF(A38, "ВМ ЗСВ","") | D38: =IF(A38,INDIRECT(ADDRESS(2,MATCH(C38,'ВМ ЗСВ'!1:1,0),1,1,"ВМ ЗСВ")),"") | F38: =IF(A38,INDIRECT(ADDRESS(2,MATCH(C38,'ВМ ЗСВ'!1:1,0)+1,1,1,"ВМ ЗСВ")),"") | H38: =IF(A38,INDIRECT(ADDRESS(2,MATCH(C38,'ВМ ЗСВ'!1:1,0)+2,1,1,"ВМ ЗСВ")),"") | J38: =IF(AND(A38=TRUE,'Тип разраб-ой док-ции'!$J$4=1),ROUNDUP(IF($F$5 =1,AF30,IF($F$5=2,AG30,IF($F$5 =3,AH30,"-")))/8,2),"-") -> #REF! | K38: =IF(AND(A38=TRUE,'Тип разраб-ой док-ции'!$J$3=1),ROUNDUP(IF($F$5 =1,AI30,IF($F$5=2,AJ30,IF($F$5 =3,AK30,"-")))/8,2),"-") -> #REF! | L38: =IF(AND(A38=TRUE,'Тип разраб-ой док-ции'!$J$2=1),ROUNDUP(IF($F$5 =1,AL30,IF($F$5=2,AM30,IF($F$5 =3,AN30,"-")))/8,2),"-") -> #REF! | M38: =IF(AND(A38=TRUE,'Тип разраб-ой док-ции'!$J$5=1),ROUNDUP(IF($F$5 =1,AO30,IF($F$5=2,AP30,IF($F$5 =3,AQ30,"-")))/8,2),"-") -> #REF! | N38: =SUM('Итоговый расчет АСУТП'!EQ4:EQ41) -> 0 | O38: ='MFA АСУТП'!$D$2 -> MFA Кол-во серверных компонентов | P38: =E21 -> 0 | R38: - | S38: Смета | T38: =ROUNDUP('Итоговый расчет АСУТП'!EZ31/8,2) -> 0 | AA38: 0
A39: FALSE | B39: =IF(A39, "ВМ СПО","") | D39: =IF(A39,INDIRECT(ADDRESS(2,MATCH(C39,'ВМ СПО'!1:1,0),1,1,"ВМ СПО")),"") | F39: =IF(A39,INDIRECT(ADDRESS(2,MATCH(C39,'ВМ СПО'!1:1,0)+1,1,1,"ВМ СПО")),"") | H39: =IF(A39,INDIRECT(ADDRESS(2,MATCH(C39,'ВМ СПО'!1:1,0)+2,1,1,"ВМ СПО")),"") | J39: =IF(AND(A39=TRUE,'Тип разраб-ой док-ции'!$J$4=1),ROUNDUP(IF($F$5 =1,AF31,IF($F$5=2,AG31,IF($F$5 =3,AH31,"-")))/8,2),"-") -> #REF! | K39: =IF(AND(A39=TRUE,'Тип разраб-ой док-ции'!$J$3=1),ROUNDUP(IF($F$5 =1,AI31,IF($F$5=2,AJ31,IF($F$5 =3,AK31,"-")))/8,2),"-") -> #REF! | L39: =IF(AND(A39=TRUE,'Тип разраб-ой док-ции'!$J$2=1),ROUNDUP(IF($F$5 =1,AL31,IF($F$5=2,AM31,IF($F$5 =3,AN31,"-")))/8,2),"-") -> #REF! | M39: =IF(AND(A39=TRUE,'Тип разраб-ой док-ции'!$J$5=1),ROUNDUP(IF($F$5 =1,AO31,IF($F$5=2,AP31,IF($F$5 =3,AQ31,"-")))/8,2),"-") -> #REF! | N39: =SUM('Итоговый расчет АСУТП'!ES4:ES41) -> 0 | O39: ='MFA АСУТП'!$E$2 -> MFA Количество используемых типов агентов аутентификации | P39: =G21 -> 0 | R39: - | S39: Принципиальная схема электропитания оборудования | T39: =ROUNDUP('Итоговый расчет АСУТП'!EZ32/8,2) -> 0 | AA39: 0
A40: FALSE | B40: =IF(A40, "ВМ АСО","") | D40: =IF(A40,INDIRECT(ADDRESS(2,MATCH(C40,'ВМ АСО'!1:1),1,1,"ВМ АСО")),"") | F40: =IF(A40,INDIRECT(ADDRESS(2,MATCH(C40,'ВМ АСО'!1:1)+1,1,1,"ВМ АСО")),"") | H40: =IF(A40,INDIRECT(ADDRESS(2,MATCH(C40,'ВМ АСО'!1:1)+2,1,1,"ВМ АСО")),"") | J40: =IF(AND(A40=TRUE,'Тип разраб-ой док-ции'!$J$4=1),ROUNDUP(IF($F$5 =1,AF32,IF($F$5=2,AG32,IF($F$5 =3,AH32,"-")))/8,2),"-") -> #REF! | K40: =IF(AND(A40=TRUE,'Тип разраб-ой док-ции'!$J$3=1),ROUNDUP(IF($F$5 =1,AI32,IF($F$5=2,AJ32,IF($F$5 =3,AK32,"-")))/8,2),"-") -> #REF! | L40: =IF(AND(A40=TRUE,'Тип разраб-ой док-ции'!$J$2=1),ROUNDUP(IF($F$5 =1,AL32,IF($F$5=2,AM32,IF($F$5 =3,AN32,"-")))/8,2),"-") -> #REF! | M40: =IF(AND(A40=TRUE,'Тип разраб-ой док-ции'!$J$5=1),ROUNDUP(IF($F$5 =1,AO32,IF($F$5=2,AP32,IF($F$5 =3,AQ32,"-")))/8,2),"-") -> #REF! | N40: =SUM('Итоговый расчет АСУТП'!EU4:EU41) -> 0 | O40: ='MFA АСУТП'!$F$2 -> MFA неиспользуемый параметр | P40: =I21 -> 0 | R40: - | S40: Схема подключения внешних проводок | T40: =ROUNDUP('Итоговый расчет АСУТП'!EZ33/8,2) -> 0 | AA40: 1
B41: Нормоконтроль | N41: =SUM('Итоговый расчет АСУТП'!EY4:EY41)/8 -> #REF! | O41: ='ДИОД АСУТП'!$D$2 -> ДИОД Кол-во диодов/брокеров | P41: =E22 -> 0 | R41: - | S41: Чертеж установки технических средств | T41: =ROUNDUP('Итоговый расчет АСУТП'!EZ34/8,2) -> 0 | V41: 1 | W41: 1 | AA41: 0
B42: Сумма по документам | N42: =SUM(N11:N40) -> #REF! | O42: ='ДИОД АСУТП'!$E$2 -> ДИОД Кол-во типов источников | P42: =G22 -> 0 | S42: ЭД | V42: 1 | W42: 1 | AA42: 0
B43: ИТОГО | N43: =SUM(N41:N42) -> #REF! | O43: ='ДИОД АСУТП'!$F$2 -> ДИОД Кол-во систем назначения | P43: =I22 -> 0 | R43: - | S43: Ведомость эксплуатационных документов | T43: =ROUNDUP('Итоговый расчет АСУТП'!EZ36/8,2) -> 0 | AA43: 0
O44: ='СЗВ АСУТП'!$D$2 -> СЗВ Количество площадок с серверными компонентами подсистемы | P44: =E23 -> 0 | R44: 1 | S44: Руководство администратора | T44: =ROUNDUP('Итоговый расчет АСУТП'!EZ37/8,2) -> #REF! | AA44: 0
B45: Таблица доп средств | N45: =G131+G132+G133 -> #REF! | O45: ='СЗВ АСУТП'!$E$2 -> СЗВ Кол-во серверов в кластере | P45: =G23 -> 0 | R45: 1 | S45: Руководство пользователя | T45: =ROUNDUP('Итоговый расчет АСУТП'!EZ38/8,2) -> #REF! | AA45: 0
B46: Назначение | C46: Отдел | D46: ТрЗ И (часы) | E46: ТрЗ СИ (часы) | F46: ТрЗ ВИ (часы) | G46: ТрЗ НК (часы) | O46: ='СЗВ АСУТП'!$F$2 -> СЗВ Кол-во виртуальных машин | P46: =I23 -> 0 | R46: - | S46: Руководство по мониторингу | T46: =ROUNDUP('Итоговый расчет АСУТП'!EZ39/8,2) -> 0 | AA46: 0
O47: ='SOAR АСУТП'!$D$2 -> SOAR Кол-во используемых дополнительных модулей | P47: =E24 -> 0 | R47: - | S47: План резервного копирования | T47: =ROUNDUP('Итоговый расчет АСУТП'!EZ40/8,2) -> 0 | AA47: 0
O48: ='SOAR АСУТП'!$E$2 -> SOAR Кол-во коллекторов/серверов оркестрации | P48: =G24 -> 0 | R48: - | S48: План опытной эксплуатации | T48: =ROUNDUP('Итоговый расчет АСУТП'!EZ41/8,2) -> 0 | AA48: 0
O49: ='SOAR АСУТП'!$F$2 -> SOAR Проектируется только SOAR (нет=0; да=1) | P49: =I24 -> 0 | AA49: 0
O50: ='VDI АСУТП'!$E$2 -> VDI Кол-во протоколов подключения | P50: =E25 -> 0 | AA50: 0
O51: ='VDI АСУТП'!$D$2 -> VDI Количество площадок с серверными компонентами | P51: =G25 -> 0
O52: ='VDI АСУТП'!$F$2 -> VDI Кол-во пулов виртуальных машин | P52: =I25 -> 0
O53: ='СУБД АСУТП'!D2 -> СУБД Неиспользуемый параметр | P53: =E26 -> 0 | AA53: 0 | AF53: =SUM(J62:J72) -> 0
O54: ='СУБД АСУТП'!E2 -> СУБД Неиспользуемый параметр | P54: =G26 -> 0
O55: ='СУБД АСУТП'!F2 -> СУБД Неиспользуемый параметр | P55: =I26 -> 0
O56: ='ГОССОПКА АСУТП'!D$2 -> ГосСопка количество серверных компонентов | P56: =E27 -> 0
O57: ='ГОССОПКА АСУТП'!E$2 -> ГосСопка кол-во используемых компонент | P57: =G27 -> 0 | R57: 1 | AE57: История изменений автоматическая
O58: ='ГОССОПКА АСУТП'!F$2 -> ГосСопка неиспользуемый параметр | P58: =I27 -> 0 | R58: 0
O59: ='TLS АСУТП'!D$2 -> TLS Кол-во площадок | P59: =E28 -> 0 | R59: FALSE | AA59: 1
O60: ='TLS АСУТП'!E$2 -> TLC Кол-во типов агентов | P60: =G28 -> 0 | R60: FALSE | AA60: 1 | AE60: АСУТП | AF60: ОП
O61: ='TLS АСУТП'!F$2 -> TLC Неиспользуемый параметр | P61: =I28 -> 0 | R61: FALSE | AA61: 1 | AE61: =IF(C72 = "АСУТП",1,0) -> 0 | AF61: =IF(C72= "ОП",1,0) -> 0
O62: ='DCAP АСУТП'!D$2 -> DCAP Количество площадок с серверными компонентами подсистемы | P62: =E29 -> 0 | R62: 1 | AA62: 1 | AE62: =IF(C73 = "АСУТП",1,0) -> 0 | AF62: =IF(C73= "ОП",1,0) -> 0
O63: ='DCAP АСУТП'!E$2 -> DCAP Кол-во типов хранилищ | P63: =G29 -> 0 | R63: 0 | AA63: 1 | AE63: =IF(C74 = "АСУТП",1,0) -> 0 | AF63: =IF(C74= "ОП",1,0) -> 0
O64: ='DCAP АСУТП'!F$2 -> DCAP Неиспользуемый параметр | P64: =I29 -> 0 | R64: FALSE | AA64: 1 | AE64: =IF(C75 = "АСУТП",1,0) -> 0 | AF64: =IF(C75= "ОП",1,0) -> 0
O65: ='DO АСУТП'!D$2 -> DO Количество серверных компонентов | P65: =E30 -> 0 | R65: FALSE | AA65: 1 | AE65: =IF(C76 = "АСУТП",1,0) -> 0 | AF65: =IF(C76= "ОП",1,0) -> 0
O66: ='DO АСУТП'!E$2 -> DO Кол-во используемых модулей | P66: =G30 -> 0 | R66: FALSE | AA66: 0 | AE66: =IF(C77 = "АСУТП",1,0) -> 0 | AF66: =IF(C77= "ОП",1,0) -> 0
O67: ='DO АСУТП'!F$2 -> DO Проектируется только DO (нет=0; да=1) | P67: =I30 -> 0 | R67: FALSE | AA67: 1 | AE67: =IF(C78 = "АСУТП",1,0) -> 0 | AF67: =IF(C78= "ОП",1,0) -> 0
O68: ='NTA АСУТП'!D$2 -> NTA Количество площадок с серверными компонентами | P68: =E31 -> 0 | R68: 0 | AA68: 1 | AE68: =IF(C79 = "АСУТП",1,0) -> 0 | AF68: =IF(C79= "ОП",1,0) -> 0
O69: ='NTA АСУТП'!E$2 -> NTA Кол-во точек мониторинга | P69: =G31 -> 0 | R69: 0 | AA69: 1 | AE69: =IF(C80 = "АСУТП",1,0) -> 0 | AF69: =IF(C80= "ОП",1,0) -> 0
B70: Таблица доп услуг | O70: ='NTA АСУТП'!F$2 -> NTA Неиспользуемый параметр | P70: =I31 -> 0 | R70: 0 | AA70: 0 | AE70: =IF(C81 = "АСУТП",1,0) -> 0 | AF70: =IF(C81= "ОП",1,0) -> 0
B71: Назначение | C71: Отдел | D71: ТрЗ И (часы) | E71: ТрЗ СИ (часы) | F71: ТрЗ ВИ (часы) | G71: ТрЗ НК (часы) | O71: ='SEG АСУТП'!D$2 -> SEG Количество площадок с серверными компонентами подсистемы | P71: =E32 -> 0 | R71: FALSE | W71: 1 | X71: 4 | Y71: 1 | AA71: 0 | AE71: =IF(C82 = "АСУТП",1,0) -> 0 | AF71: =IF(C82= "ОП",1,0) -> 0
O72: ='SEG АСУТП'!E$2 -> SEG Кол-во почтовых серверов | P72: =G32 -> 0 | R72: FALSE | W72: 1 | X72: 1 | Y72: 3 | AA72: 0 | AE72: =IF(C83 = "АСУТП",1,0) -> 0 | AF72: =IF(C83= "ОП",1,0) -> 0
O73: ='SEG АСУТП'!F$2 -> SEG Неиспользуемый параметр | P73: =I32 -> 0 | R73: FALSE | AE73: =IF(C84 = "АСУТП",1,0) -> 0 | AF73: =IF(C84= "ОП",1,0) -> 0
O74: ='APT АСУТП'!D$2 -> APT Количество типовых площадок | P74: =E33 -> 0 | R74: FALSE | AE74: =IF(C85 = "АСУТП",1,0) -> 0 | AF74: =IF(C85= "ОП",1,0) -> 0
O75: ='APT АСУТП'!E$2 -> APT Количество сенсоров | P75: =G33 -> 0 | R75: FALSE | AE75: =IF(C86 = "АСУТП",1,0) -> 0 | AF75: =IF(C86= "ОП",1,0) -> 0
O76: ='APT АСУТП'!F$2 -> APT Количество Sandbox | P76: =I33 -> 0 | R76: FALSE | AE76: =IF(C87 = "АСУТП",1,0) -> 0 | AF76: =IF(C87= "ОП",1,0) -> 0
O77: ='NAC АСУТП'!D$2 -> NAC Количество площадок с серверными компонентами | P77: =E34 -> 0 | R77: 0
O78: ='NAC АСУТП'!E$2 -> NAC Кол-во типов устройств | P78: =G34 -> 0 | R78: 0
O79: ='NAC АСУТП'!F$2 -> NAC Кол-во систем для интеграции | P79: =I34 -> 0 | R79: FALSE
O80: ='SANDBOX АСУТП'!D$2 -> SANDBOX Кол-во серверных компонентов | P80: =E35 -> 0
O81: ='SANDBOX АСУТП'!E$2 -> SANDBOX Кол-во типов ОС | P81: =G35 -> 0
O82: ='SANDBOX АСУТП'!F$2 -> SANDBOX Неиспользуемый параметр | P82: =I35 -> 0
O83: ='EDR АСУТП'!D$2 -> EDR Кол-во серверов управления | P83: =E36 -> 0
O84: ='EDR АСУТП'!E$2 -> EDR Кол-во серверов Sandbox | P84: =G36 -> 0
O85: ='EDR АСУТП'!F$2 -> EDR Кол-во систем для интеграции | P85: =I36 -> 0
O86: ='WAF АСУТП'!D$2 -> WAF Кол-во площадок | P86: =E37 -> 0
O87: ='WAF АСУТП'!E$2 -> WAF Кол-во защищаемых веб-ресурсов | P87: =G37 -> 0
B88: Итог | C88: АСУТП | D88: =SUM(D72:D87)+SUM(D47:D68) -> 0 | E88: =SUM(E72:E87)+SUM(E47:E68) -> 0 | F88: =SUM(F72:F87)+SUM(F47:F68) -> 0 | G88: =SUM(G72:G87)+SUM(G47:G68) -> 0 | O88: ='WAF АСУТП'!F$2 -> WAF Кол-во узлов | P88: =I37 -> 0
O89: ='ВМ ЗСВ'!D$2 -> ВМ ЗСВ Количество площадок с серверными компонентами подсистемы | P89: =E38 -> 0
B90: Таблица командировок | O90: ='ВМ ЗСВ'!E$2 -> ВМ ЗСВ Кол-во серверов в кластере | P90: =G38 -> 0
A91: Требуемые работы | B91: Вид работ | C91: Инженер (часы) | D91: Ст. инж. (часы) | E91: Вед. Инж. (часы) | F91: ТрЗ итого (часы) | G91: ТрЗ итого (чд) | O91: ='ВМ ЗСВ'!F$2 -> ВМ ЗСВ Кол-во виртуальных машин | P91: =I38 -> 0
A92: 0 | B92: Подготовка опросных листов и методики для обследования | C92: =IF($A92=1,IF($C$6="Обычный",Командировки_ОП!K9,Командировки_ОП!K10),"-") -> - | D92: =IF($A92=1,IF($C$6="Обычный",Командировки_ОП!L8,Командировки_ОП!L9),"-") -> - | E92: =IF($A92=1,IF($C$6="Обычный",Командировки_ОП!M8,Командировки_ОП!M9),"-") -> - | F92: =SUM(C92:E92) -> 0 | G92: =ROUNDUP((SUM(D92:F92))/8,0) -> 0 | O92: ='ВМ СПО'!D$2 -> ВМ СПО Неиспользуемый параметр | P92: =E39 -> 0
A93: 0 | B93: Разработка методики проведения обследования | C93: =IF($A93=1,IF($C$6="Обычный",Командировки_ОП!K9,Командировки_ОП!K10),"-") -> - | D93: =IF($A93=1,IF($C$6="Обычный",Командировки_ОП!L9,Командировки_ОП!L10),"-") -> - | E93: =IF($A93=1,IF($C$6="Обычный",Командировки_ОП!M9,Командировки_ОП!M10),"-") -> - | F93: =SUM(C93:E93) -> 0 | G93: =ROUNDUP((SUM(D93:F93))/8,0) -> 0
A94: 0 | B94: Обследование | C94: =IF($A94=1,IF($C$6="Обычный",Командировки_ОП!K9,Командировки_ОП!K10),"-") -> - | D94: =IF($A94=1,IF($C$6="Обычный",Командировки_ОП!L9,Командировки_ОП!L10),"-") -> - | E94: =IF($A94=1,IF($C$6="Обычный",Командировки_ОП!M9,Командировки_ОП!M10),"-") -> - | F94: =SUM(C94:E94) -> 0 | G94: =ROUNDUP((SUM(D94:F94))/8,0) -> 0
A95: 0 | B95: Разработка Отчета об обследовании | C95: =IF($A95=1,IF($C$6="Обычный",Командировки_ОП!K10,Командировки_ОП!K11),"-") -> - | D95: =IF($A95=1,IF($C$6="Обычный",Командировки_ОП!L10,Командировки_ОП!L11),"-") -> - | E95: =IF($A95=1,IF($C$6="Обычный",Командировки_ОП!M10,Командировки_ОП!M11),"-") -> - | F95: =SUM(C95:E95) -> 0 | G95: =ROUNDUP((SUM(D95:F95))/8,0) -> 0 | O95: ='ВМ СПО'!E$2 -> ВМ СПО Неиспользуемый параметр | P95: =G39 -> 0
O96: ='ВМ СПО'!F$2 -> ВМ СПО Неиспользуемый параметр | P96: =I39 -> 0
O97: ='ВМ АСО'!D$2 -> ВМ АСО Количество вендоров (типов) | P97: =E40 -> 0
O98: ='ВМ АСО'!E$2 -> ВМ АСО Неиспользуемый параметр | P98: =G40 -> 0
O99: ='ВМ АСО'!F$2 -> ВМ АСО Неиспользуемый параметр | P99: =I40 -> 0
O100: ='АПМДЗ АСУТП'!D$2 -> АПМДЗ Количество площадок с серверными компонентами подсистемы | P100: =E20 -> 0
...

Sheet Итоговый расчет АСУТП
A1: Сложность проекта | B1: =ТрЗ_ОП!F6 -> 2
A2: Классы | B2: =INDIRECT("ТрЗ!B" & 10 + COLUMN(A1)) -> #REF! | E2: =INDIRECT("ТрЗ!B" & 10 + COLUMN(B1)) -> #REF! | H2: =INDIRECT("ТрЗ!B" & 10 + COLUMN(C1)) -> #REF! | K2: =INDIRECT("ТрЗ!B" & 10 + COLUMN(D1)) -> #REF! | N2: =INDIRECT("ТрЗ!B" & 10 + COLUMN(E1)) -> #REF! | Q2: =INDIRECT("ТрЗ!B" & 10 + COLUMN(F1)) -> #REF! | T2: =INDIRECT("ТрЗ!B" & 10 + COLUMN(G1)) -> #REF! | W2: =INDIRECT("ТрЗ!B" & 10 + COLUMN(H1)) -> #REF! | Z2: =INDIRECT("ТрЗ!B" & 10 + COLUMN(I1)) -> #REF! | AC2: =INDIRECT("ТрЗ!B" & 10 + COLUMN(J1)) -> #REF! | AF2: =INDIRECT("ТрЗ!B" & 10 + COLUMN(K1)) -> #REF! | AI2: =INDIRECT("ТрЗ!B" & 10 + COLUMN(L1)) -> #REF! | AL2: =INDIRECT("ТрЗ!B" & 10 + COLUMN(M1)) -> #REF! | AO2: =INDIRECT("ТрЗ!B" & 10 + COLUMN(N1)) -> #REF! | AR2: =INDIRECT("ТрЗ!B" & 10 + COLUMN(O1)) -> #REF! | AU2: =INDIRECT("ТрЗ!B" & 10 + COLUMN(P1)) -> #REF! | AX2: =INDIRECT("ТрЗ!B" & 10 + COLUMN(Q1)) -> #REF! | BA2: =INDIRECT("ТрЗ!B" & 10 + COLUMN(R1)) -> #REF! | BD2: =INDIRECT("ТрЗ!B" & 10 + COLUMN(S1)) -> #REF! | BG2: =INDIRECT("ТрЗ!B" & 10 + COLUMN(T1)) -> #REF! | BJ2: =INDIRECT("ТрЗ!B" & 10 + COLUMN(U1)) -> #REF! | BM2: =INDIRECT("ТрЗ!B" & 10 + COLUMN(V1)) -> #REF! | BP2: =INDIRECT("ТрЗ!B" & 10 + COLUMN(W1)) -> #REF! | BS2: =INDIRECT("ТрЗ!B" & 10 + COLUMN(X1)) -> #REF! | BV2: =INDIRECT("ТрЗ!B" & 10 + COLUMN(Y1)) -> #REF! | BY2: =INDIRECT("ТрЗ!B" & 10 + COLUMN(Z1)) -> #REF! | CB2: =INDIRECT("ТрЗ!B" & 10 + COLUMN(AA1)) -> #REF! | CE2: =INDIRECT("ТрЗ!B" & 10 + COLUMN(AB1)) -> #REF! | CH2: =INDIRECT("ТрЗ!B" & 10 + COLUMN(AC1)) -> #REF! | CK2: =INDIRECT("ТрЗ!B" & 10 + COLUMN(AD1)) -> #REF! | CN2: =CONCATENATE("Выбор ",INDIRECT("'Служебный АСУТП'!" & ADDRESS(ROW('Служебный АСУТП'!E1), COLUMN('Служебный АСУТП'!$E1)))) -> Выбор АВЗ | CO2: =CONCATENATE("Расчет ",INDIRECT("'Служебный АСУТП'!" & ADDRESS(ROW('Служебный АСУТП'!F1), COLUMN('Служебный АСУТП'!$E1)))) -> Расчет АВЗ | CP2: =CONCATENATE("Выбор ",INDIRECT("'Служебный АСУТП'!" & ADDRESS(ROW('Служебный АСУТП'!F1), COLUMN('Служебный АСУТП'!$F1)))) -> Выбор SIEM | CQ2: =CONCATENATE("Расчет ",INDIRECT("'Служебный АСУТП'!" & ADDRESS(ROW('Служебный АСУТП'!H1), COLUMN('Служебный АСУТП'!$F1)))) -> Расчет SIEM | CR2: =CONCATENATE("Выбор ",INDIRECT("'Служебный АСУТП'!" & ADDRESS(ROW('Служебный АСУТП'!G1), COLUMN('Служебный АСУТП'!$G1)))) -> Выбор МСЭ | CS2: =CONCATENATE("Расчет ",INDIRECT("'Служебный АСУТП'!" & ADDRESS(ROW('Служебный АСУТП'!H1), COLUMN('Служебный АСУТП'!$G1)))) -> Расчет МСЭ | CT2: =CONCATENATE("Выбор ",INDIRECT("'Служебный АСУТП'!" & ADDRESS(ROW('Служебный АСУТП'!H1), COLUMN('Служебный АСУТП'!$H1)))) -> Выбор PIM / PAM / PUM | CU2: =CONCATENATE("Расчет ",INDIRECT("'Служебный АСУТП'!" & ADDRESS(ROW('Служебный АСУТП'!I1), COLUMN('Служебный АСУТП'!$H1)))) -> Расчет PIM / PAM / PUM | CV2: =CONCATENATE("Выбор ",INDIRECT("'Служебный АСУТП'!" & ADDRESS(ROW('Служебный АСУТП'!I1), COLUMN('Служебный АСУТП'!$I1)))) -> Выбор СКЗИ | CW2: Расчет СКЗИ | CX2: =CONCATENATE("Выбор ",INDIRECT("'Служебный АСУТП'!" & ADDRESS(ROW('Служебный АСУТП'!J1), COLUMN('Служебный АСУТП'!$J1)))) -> Выбор АЗ | CY2: Расчет АЗ | CZ2: =CONCATENATE("Выбор ",INDIRECT("'Служебный АСУТП'!" & ADDRESS(ROW('Служебный АСУТП'!K1), COLUMN('Служебный АСУТП'!$K1)))) -> Выбор СРК | DA2: Расчет СРК | DB2: =CONCATENATE("Выбор ",INDIRECT("'Служебный АСУТП'!" & ADDRESS(ROW('Служебный АСУТП'!L1), COLUMN('Служебный АСУТП'!$L1)))) -> Выбор IDS | DC2: Расчет IDS | DD2: =CONCATENATE("Выбор ",INDIRECT("'Служебный АСУТП'!" & ADDRESS(ROW('Служебный АСУТП'!M1), COLUMN('Служебный АСУТП'!$M1)))) -> Выбор НСД | DE2: Расчет НСД | DF2: =CONCATENATE("Выбор ",INDIRECT("'Служебный АСУТП'!" & ADDRESS(ROW('Служебный АСУТП'!N1), COLUMN('Служебный АСУТП'!$N1)))) -> Выбор АПМДЗ | DG2: Расчет АПМДЗ | DH2: =CONCATENATE("Выбор ",INDIRECT("'Служебный АСУТП'!" & ADDRESS(ROW('Служебный АСУТП'!O1), COLUMN('Служебный АСУТП'!$O1)))) -> Выбор MFA | DI2: Расчет MFA | DJ2: =CONCATENATE("Выбор ",INDIRECT("'Служебный АСУТП'!" & ADDRESS(ROW('Служебный АСУТП'!P1), COLUMN('Служебный АСУТП'!$P1)))) -> Выбор Диод | DK2: Расчет Диод | DL2: =CONCATENATE("Выбор ",INDIRECT("'Служебный АСУТП'!" & ADDRESS(ROW('Служебный АСУТП'!Q1), COLUMN('Служебный АСУТП'!$Q1)))) -> Выбор СЗВ | DM2: Расчет СЗВ | DN2: =CONCATENATE("Выбор ",INDIRECT("'Служебный АСУТП'!" & ADDRESS(ROW('Служебный АСУТП'!R1), COLUMN('Служебный АСУТП'!$R1)))) -> Выбор SOAR | DO2: Расчет SOAR | DP2: =CONCATENATE("Выбор ",INDIRECT("'Служебный АСУТП'!" & ADDRESS(ROW('Служебный АСУТП'!S1), COLUMN('Служебный АСУТП'!$S1)))) -> Выбор Виртуализация рабочих мест (VDI) | DQ2: Расчет Виртуализация рабочих мест (VDI) | DR2: =CONCATENATE("Выбор ",INDIRECT("'Служебный АСУТП'!" & ADDRESS(ROW('Служебный АСУТП'!T1), COLUMN('Служебный АСУТП'!$T1)))) -> Выбор СУБД | DS2: Расчет СУБД | DT2: =CONCATENATE("Выбор ",INDIRECT("'Служебный АСУТП'!" & ADDRESS(ROW('Служебный АСУТП'!U1), COLUMN('Служебный АСУТП'!$U1)))) -> Выбор Платформа взаимодействия с главным центром ГосСОПКА | DU2: Расчет Платформа взаимодействия с главным центром ГосСОПКА | DV2: =CONCATENATE("Выбор ",INDIRECT("'Служебный АСУТП'!" & ADDRESS(ROW('Служебный АСУТП'!V1), COLUMN('Служебный АСУТП'!$V1)))) -> Выбор TLS шлюз | DW2: Расчет TLS шлюз | DX2: =CONCATENATE("Выбор ",INDIRECT("'Служебный АСУТП'!" & ADDRESS(ROW('Служебный АСУТП'!W1), COLUMN('Служебный АСУТП'!$W1)))) -> Выбор DCAP / DAG | DY2: Расчет DCAP / DAG | DZ2: =CONCATENATE("Выбор ",INDIRECT("'Служебный АСУТП'!" & ADDRESS(ROW('Служебный АСУТП'!X1), COLUMN('Служебный АСУТП'!$X1)))) -> Выбор Контроль конфигураций | EA2: Расчет Контроль конфигураций | EB2: =CONCATENATE("Выбор ",INDIRECT("'Служебный АСУТП'!" & ADDRESS(ROW('Служебный АСУТП'!Y1), COLUMN('Служебный АСУТП'!$Y1)))) -> Выбор NTA | EC2: Расчет NTA | ED2: =CONCATENATE("Выбор ",INDIRECT("'Служебный АСУТП'!" & ADDRESS(ROW('Служебный АСУТП'!Z1), COLUMN('Служебный АСУТП'!$Z1)))) -> Выбор SEG | EE2: Расчет SEG | EF2: =CONCATENATE("Выбор ",INDIRECT("'Служебный АСУТП'!" & ADDRESS(ROW('Служебный АСУТП'!AA1), COLUMN('Служебный АСУТП'!$AA1)))) -> Выбор APT | EG2: Расчет APT | EH2: =CONCATENATE("Выбор ",INDIRECT("'Служебный АСУТП'!" & ADDRESS(ROW('Служебный АСУТП'!AB1), COLUMN('Служебный АСУТП'!$AB1)))) -> Выбор NAC | EI2: Расчет NAC | EJ2: =CONCATENATE("Выбор ",INDIRECT("'Служебный АСУТП'!" & ADDRESS(ROW('Служебный АСУТП'!AC1), COLUMN('Служебный АСУТП'!$AC1)))) -> Выбор Sandbox | EK2: Расчет Sandbox | EL2: =CONCATENATE("Выбор ",INDIRECT("'Служебный АСУТП'!" & ADDRESS(ROW('Служебный АСУТП'!AD1), COLUMN('Служебный АСУТП'!$AD1)))) -> Выбор EDR | EM2: Расчет EDR | EN2: =CONCATENATE("Выбор ",INDIRECT("'Служебный АСУТП'!" & ADDRESS(ROW('Служебный АСУТП'!AE1), COLUMN('Служебный АСУТП'!$AE1)))) -> Выбор WAF | EO2: Расчет WAF | EP2: =CONCATENATE("Выбор ",INDIRECT("'Служебный АСУТП'!" & ADDRESS(ROW('Служебный АСУТП'!AF1), COLUMN('Служебный АСУТП'!$AF1)))) -> Выбор ВМ ЗСВ | EQ2: Расчет ВМ ЗВС | ER2: =CONCATENATE("Выбор ",INDIRECT("'Служебный АСУТП'!" & ADDRESS(ROW('Служебный АСУТП'!AG1), COLUMN('Служебный АСУТП'!$AG1)))) -> Выбор ВМ СПО | ES2: Расчет ВМ СПО | ET2: =CONCATENATE("Выбор ",INDIRECT("'Служебный АСУТП'!" & ADDRESS(ROW('Служебный АСУТП'!AH1), COLUMN('Служебный АСУТП'!$AH1)))) -> Выбор ВМ АСО | EU2: Расчет ВМ АСО | EV2: Итоговый расчет
A3: Роли | B3: %И | C3: %СИ | D3: %ВИ | E3: %И | F3: %СИ | G3: %ВИ | H3: %И | I3: %СИ | J3: %ВИ | K3: %И | L3: %СИ | M3: %ВИ | N3: %И | O3: %СИ | P3: %ВИ | Q3: %И | R3: %СИ | S3: %ВИ | T3: %И | U3: %СИ | V3: %ВИ | W3: %И | X3: %СИ | Y3: %ВИ | Z3: %И | AA3: %СИ | AB3: %ВИ | AC3: %И | AD3: %СИ | AE3: %ВИ | AF3: %И | AG3: %СИ | AH3: %ВИ | AI3: %И | AJ3: %СИ | AK3: %ВИ | AL3: %И | AM3: %СИ | AN3: %ВИ | AO3: %И | AP3: %СИ | AQ3: %ВИ | AR3: %И | AS3: %СИ | AT3: %ВИ | AU3: %И | AV3: %СИ | AW3: %ВИ | AX3: %И | AY3: %СИ | AZ3: %ВИ | BA3: %И | BB3: %СИ | BC3: %ВИ | BD3: %И | BE3: %СИ | BF3: %ВИ | BG3: %И | BH3: %СИ | BI3: %ВИ | BJ3: %И | BK3: %СИ | BL3: %ВИ | BM3: %И | BN3: %СИ | BO3: %ВИ | BP3: %И | BQ3: %СИ | BR3: %ВИ | BS3: %И | BT3: %СИ | BU3: %ВИ | BV3: %И | BW3: %СИ | BX3: %ВИ | BY3: %И | BZ3: %СИ | CA3: %ВИ | CB3: %И | CC3: %СИ | CD3: %ВИ | CE3: %И | CF3: %СИ | CG3: %ВИ | CH3: %И | CI3: %СИ | CJ3: %ВИ | CK3: %И | CL3: %СИ | CM3: %ВИ | EV3: И | EW3: СИ | EX3: ВИ | EY3: НК | EZ3: Общие
A4: ТЗ/ФТТ | CN4: =ТрЗ_ОП!A11 -> TRUE | CP4: =ТрЗ_ОП!A12 -> TRUE | CR4: =ТрЗ_ОП!A13 -> FALSE | CT4: =ТрЗ_ОП!A14 -> FALSE | CV4: =ТрЗ_ОП!A15 -> FALSE | CX4: =ТрЗ_ОП!A16 -> FALSE | CZ4: =ТрЗ_ОП!A17 -> FALSE | DB4: =ТрЗ_ОП!A18 -> FALSE | DD4: =ТрЗ_ОП!A19 -> FALSE | DF4: =ТрЗ_ОП!A20 -> FALSE | DH4: =ТрЗ_ОП!A21 -> FALSE | DJ4: =ТрЗ_ОП!A22 -> FALSE | DL4: =ТрЗ_ОП!A23 -> FALSE | DN4: =ТрЗ_ОП!A24 -> FALSE | DP4: =ТрЗ_ОП!A25 -> FALSE | DR4: =ТрЗ_ОП!A26 -> FALSE | DT4: =ТрЗ_ОП!A27 -> FALSE | DV4: =ТрЗ_ОП!A28 -> FALSE | DX4: =ТрЗ_ОП!A29 -> FALSE | DZ4: =ТрЗ_ОП!A30 -> FALSE | EB4: =ТрЗ_ОП!A31 -> FALSE | ED4: =ТрЗ_ОП!A32 -> FALSE | EF4: =ТрЗ_ОП!A33 -> FALSE | EH4: =ТрЗ_ОП!A34 -> FALSE | EJ4: =ТрЗ_ОП!A35 -> FALSE | EL4: =ТрЗ_ОП!A36 -> FALSE | EN4: =ТрЗ_ОП!A37 -> FALSE | EP4: =ТрЗ_ОП!A38 -> FALSE | ER4: =ТрЗ_ОП!A39 -> FALSE | ET4: =ТрЗ_ОП!A40 -> FALSE
A5: ТЗ | B5: 0.7 | C5: 0.2 | D5: 0.1 | E5: 0.7 | F5: 0.2 | G5: 0.1 | H5: 0.7 | I5: 0.2 | J5: 0.1 | K5: 0.7 | L5: 0.2 | M5: 0.1 | N5: 0.7 | O5: 0.2 | P5: 0.1 | Q5: 0.7 | R5: 0.2 | S5: 0.1 | T5: 0.7 | U5: 0.2 | V5: 0.1 | W5: 0.7 | X5: 0.2 | Y5: 0.1 | Z5: 0.7 | AA5: 0.2 | AB5: 0.1 | AC5: 0.7 | AD5: 0.2 | AE5: 0.1 | AF5: 0.7 | AG5: 0.2 | AH5: 0.1 | AI5: 0.7 | AJ5: 0.2 | AK5: 0.1 | AL5: 0.7 | AM5: 0.2 | AN5: 0.1 | AO5: 0.7 | AP5: 0.2 | AQ5: 0.1 | AR5: 0.7 | AS5: 0.2 | AT5: 0.1 | AU5: 0.7 | AV5: 0.2 | AW5: 0.1 | AX5: 0.7 | AY5: 0.2 | AZ5: 0.1 | BA5: 0.7 | BB5: 0.2 | BC5: 0.1 | BD5: 0.7 | BE5: 0.2 | BF5: 0.1 | BG5: 0.7 | BH5: 0.2 | BI5: 0.1 | BJ5: 0.7 | BK5: 0.2 | BL5: 0.1 | BM5: 0.7 | BN5: 0.2 | BO5: 0.1 | BP5: 0.7 | BQ5: 0.2 | BR5: 0.1 | BS5: 0.7 | BT5: 0.2 | BU5: 0.1 | BV5: 0.7 | BW5: 0.2 | BX5: 0.1 | BY5: 0.7 | BZ5: 0.2 | CA5: 0.1 | CB5: 0.7 | CC5: 0.2 | CD5: 0.1 | CE5: 0.7 | CF5: 0.2 | CG5: 0.1 | CH5: 0.7 | CI5: 0.2 | CJ5: 0.1 | CK5: 0.7 | CL5: 0.2 | CM5: 0.1 | CN5: =ТрЗ_ОП!$R$12 -> - | CO5: =IF(CN5=1,IF($B$1=1,'Документы АСУТП'!CW5,IF($B$1=2,'Документы АСУТП'!CW6,IF($B$1=3,'Документы АСУТП'!CW7,'Документы АСУТП'!CW5))),0) -> 0 | CP5: =ТрЗ_ОП!$R$12 -> - | CQ5: =IF(CP5=1,IF($B$1=1,'Документы АСУТП'!CX5,IF($B$1=2,'Документы АСУТП'!CX6,IF($B$1=3,'Документы АСУТП'!CX7,'Документы АСУТП'!CX5))),0) -> 0 | CR5: =ТрЗ_ОП!$R$12 -> - | CS5: =IF(CR5=1,IF($B$1=1,'Документы АСУТП'!CY5,IF($B$1=2,'Документы АСУТП'!CY6,IF($B$1=3,'Документы АСУТП'!CY7,'Документы АСУТП'!CY5))),0) -> 0 | CT5: =ТрЗ_ОП!$R$12 -> - | CU5: =IF(CT5=1,IF($B$1=1,'Документы АСУТП'!CZ5,IF($B$1=2,'Документы АСУТП'!CZ6,IF($B$1=3,'Документы АСУТП'!CZ7,'Документы АСУТП'!CZ5))),0) -> 0 | CV5: =ТрЗ_ОП!$R$12 -> - | CW5: =IF(CV5=1,IF($B$1=1,'Документы АСУТП'!DA5,IF($B$1=2,'Документы АСУТП'!DA6,IF($B$1=3,'Документы АСУТП'!DA7,'Документы АСУТП'!DA5))),0) -> 0 | CX5: =ТрЗ_ОП!$R$12 -> - | CY5: =IF(CX5=1,IF($B$1=1,'Документы АСУТП'!DB5,IF($B$1=2,'Документы АСУТП'!DB6,IF($B$1=3,'Документы АСУТП'!DB7,'Документы АСУТП'!DB5))),0) -> 0 | CZ5: =ТрЗ_ОП!$R$12 -> - | DA5: =IF(CZ5=1,IF($B$1=1,'Документы АСУТП'!DC5,IF($B$1=2,'Документы АСУТП'!DC6,IF($B$1=3,'Документы АСУТП'!DC7,'Документы АСУТП'!DC5))),0) -> 0 | DB5: =ТрЗ_ОП!$R$12 -> - | DC5: =IF(DB5=1,IF($B$1=1,'Документы АСУТП'!DD5,IF($B$1=2,'Документы АСУТП'!DD6,IF($B$1=3,'Документы АСУТП'!DD7,'Документы АСУТП'!DD5))),0) -> 0 | DD5: =ТрЗ_ОП!$R$12 -> - | DE5: =IF(DD5=1,IF($B$1=1,'Документы АСУТП'!DF5,IF($B$1=2,'Документы АСУТП'!DF6,IF($B$1=3,'Документы АСУТП'!DF7,'Документы АСУТП'!DF5))),0) -> 0 | DF5: =ТрЗ_ОП!$R$12 -> - | DG5: =IF(DF5=1,IF($B$1=1,'Документы АСУТП'!DE5,IF($B$1=2,'Документы АСУТП'!DE6,IF($B$1=3,'Документы АСУТП'!DE7,'Документы АСУТП'!DE5))),0) -> 0 | DH5: =ТрЗ_ОП!$R$12 -> - | DI5: =IF(DH5=1,IF($B$1=1,'Документы АСУТП'!DG5,IF($B$1=2,'Документы АСУТП'!DG6,IF($B$1=3,'Документы АСУТП'!DG7,'Документы АСУТП'!DG5))),0) -> 0 | DJ5: =ТрЗ_ОП!$R$12 -> - | DK5: =IF(DJ5=1,IF($B$1=1,'Документы АСУТП'!DH5,IF($B$1=2,'Документы АСУТП'!DH6,IF($B$1=3,'Документы АСУТП'!DH7,'Документы АСУТП'!DH5))),0) -> 0 | DL5: =ТрЗ_ОП!$R$12 -> - | DM5: =IF(DL5=1,IF($B$1=1,'Документы АСУТП'!DI5,IF($B$1=2,'Документы АСУТП'!DI6,IF($B$1=3,'Документы АСУТП'!DI7,'Документы АСУТП'!DI5))),0) -> 0 | DN5: =ТрЗ_ОП!$R$12 -> - | DO5: =IF(DN5=1,IF($B$1=1,'Документы АСУТП'!DJ5,IF($B$1=2,'Документы АСУТП'!DJ6,IF($B$1=3,'Документы АСУТП'!DJ7,'Документы АСУТП'!DJ5))),0) -> 0 | DP5: =ТрЗ_ОП!$R$12 -> - | DQ5: =IF(DP5=1,IF($B$1=1,'Документы АСУТП'!DK5,IF($B$1=2,'Документы АСУТП'!DK6,IF($B$1=3,'Документы АСУТП'!DK7,'Документы АСУТП'!DK5))),0) -> 0 | DR5: =ТрЗ_ОП!$R$12 -> - | DS5: =IF(DR5=1,IF($B$1=1,'Документы АСУТП'!DL5,IF($B$1=2,'Документы АСУТП'!DL6,IF($B$1=3,'Документы АСУТП'!DL7,'Документы АСУТП'!DL5))),0) -> 0 | DT5: =ТрЗ_ОП!$R$12 -> - | DU5: =IF(DT5=1,IF($B$1=1,'Документы АСУТП'!DM5,IF($B$1=2,'Документы АСУТП'!DM6,IF($B$1=3,'Документы АСУТП'!DM7,'Документы АСУТП'!DM5))),0) -> 0 | DV5: =ТрЗ_ОП!$R$12 -> - | DW5: =IF(DV5=1,IF($B$1=1,'Документы АСУТП'!DN5,IF($B$1=2,'Документы АСУТП'!DN6,IF($B$1=3,'Документы АСУТП'!DN7,'Документы АСУТП'!DN5))),0) -> 0 | DX5: =ТрЗ_ОП!$R$12 -> - | DY5: =IF(DX5=1,IF($B$1=1,'Документы АСУТП'!DO5,IF($B$1=2,'Документы АСУТП'!DO6,IF($B$1=3,'Документы АСУТП'!DO7,'Документы АСУТП'!DO5))),0) -> 0 | DZ5: =ТрЗ_ОП!$R$12 -> - | EA5: =IF(DZ5=1,IF($B$1=1,'Документы АСУТП'!DP5,IF($B$1=2,'Документы АСУТП'!DP6,IF($B$1=3,'Документы АСУТП'!DP7,'Документы АСУТП'!DP5))),0) -> 0 | EB5: =ТрЗ_ОП!$R$12 -> - | EC5: =IF(EB5=1,IF($B$1=1,'Документы АСУТП'!DQ5,IF($B$1=2,'Документы АСУТП'!DQ6,IF($B$1=3,'Документы АСУТП'!DQ7,'Документы АСУТП'!DQ5))),0) -> 0 | ED5: =ТрЗ_ОП!$R$12 -> - | EE5: =IF(ED5=1,IF($B$1=1,'Документы АСУТП'!DR5,IF($B$1=2,'Документы АСУТП'!DR6,IF($B$1=3,'Документы АСУТП'!DR7,'Документы АСУТП'!DR5))),0) -> 0 | EF5: =ТрЗ_ОП!$R$12 -> - | EG5: =IF(EF5=1,IF($B$1=1,'Документы АСУТП'!DS5,IF($B$1=2,'Документы АСУТП'!DS6,IF($B$1=3,'Документы АСУТП'!DS7,'Документы АСУТП'!DS5))),0) -> 0 | EH5: =ТрЗ_ОП!$R$12 -> - | EI5: =IF(EH5=1,IF($B$1=1,'Документы АСУТП'!DT5,IF($B$1=2,'Документы АСУТП'!DT6,IF($B$1=3,'Документы АСУТП'!DT7,'Документы АСУТП'!DT5))),0) -> 0 | EJ5: =ТрЗ_ОП!$R$12 -> - | EK5: =IF(EJ5=1,IF($B$1=1,'Документы АСУТП'!DU5,IF($B$1=2,'Документы АСУТП'!DU6,IF($B$1=3,'Документы АСУТП'!DU7,'Документы АСУТП'!DU5))),0) -> 0 | EL5: =ТрЗ_ОП!$R$12 -> - | EM5: =IF(EL5=1,IF($B$1=1,'Документы АСУТП'!DV5,IF($B$1=2,'Документы АСУТП'!DV6,IF($B$1=3,'Документы АСУТП'!DV7,'Документы АСУТП'!DV5))),0) -> 0 | EN5: =ТрЗ_ОП!$R$12 -> - | EO5: =IF(EN5=1,IF($B$1=1,'Документы АСУТП'!DW5,IF($B$1=2,'Документы АСУТП'!DW6,IF($B$1=3,'Документы АСУТП'!DW7,'Документы АСУТП'!DW5))),0) -> 0 | EP5: =ТрЗ_ОП!$R$12 -> - | EQ5: =IF(EP5=1,IF($B$1=1,'Документы АСУТП'!DX5,IF($B$1=2,'Документы АСУТП'!DX6,IF($B$1=3,'Документы АСУТП'!DX7,'Документы АСУТП'!DX5))),0) -> 0 | ER5: =ТрЗ_ОП!$R$12 -> - | ES5: =IF(ER5=1,IF($B$1=1,'Документы АСУТП'!DY5,IF($B$1=2,'Документы АСУТП'!DY6,IF($B$1=3,'Документы АСУТП'!DY7,'Документы АСУТП'!DY5))),0) -> 0 | ET5: =ТрЗ_ОП!$R$12 -> - | EU5: =IF(ET5=1,IF($B$1=1,'Документы АСУТП'!DZ5,IF($B$1=2,'Документы АСУТП'!DZ6,IF($B$1=3,'Документы АСУТП'!DZ7,'Документы АСУТП'!DZ5))),0) -> 0 | EV5: =B5*$CO5+E5*$CQ5+H5*$CS5+K5*$CU5+N5*$CW5+Q5*$CY5+T5*$DA5+W5*$DC5+Z5*$DE5+AC5*$DG5+AF5*$DI5+AI5*$DK5+AL5*$DM5+AO5*$DO5+AR5*$DQ5+AU5*$DS5+AX5*$DU5+BA5*$DW5+BD5*$DY5+BG5*$EA5+BJ5*$EC5+BM5*$EE5+BP5*$EG5+BS5*$EI5+BV5*$EK5+BY5*$EM5+CB5*$EO5+CE5*$EQ5+CH5*$ES5+$CK5*$EU5 -> 0 | EW5: =C5*$CO5+F5*$CQ5+I5*$CS5+L5*$CU5+O5*$CW5+R5*$CY5+U5*$DA5+X5*$DC5+AA5*$DE5+AD5*$DG5+AG5*$DI5+AJ5*$DK5+AM5*$DM5+AP5*$DO5+AS5*$DQ5+AV5*$DS5+AY5*$DU5+BB5*$DW5+BE5*$DY5+BH5*$EA5+BK5*$EC5+BN5*$EE5+BQ5*$EG5+BT5*$EI5+BW5*$EK5+BZ5*$EM5+CC5*$EO5+CF5*$EQ5+CI5*$ES5+$CK5*$EU5 -> 0 | EX5: =D5*$CO5+G5*$CQ5+J5*$CS5+M5*$CU5+P5*$CW5+S5*$CY5+V5*$DA5+Y5*$DC5+AB5*$DE5+AE5*$DG5+AH5*$DI5+AK5*$DK5+AN5*$DM5+AQ5*$DO5+AT5*$DQ5+AW5*$DS5+AZ5*$DU5+BC5*$DW5+BF5*$DY5+BI5*$EA5+BL5*$EC5+BO5*$EE5+BR5*$EG5+BU5*$EI5+BX5*$EK5+CA5*$EM5+CD5*$EO5+CG5*$EQ5+CJ5*$ES5+$CK5*$EU5 -> 0 | EY5: =SUM(EV5:EX5)*0.05 -> 0 | EZ5: =SUM(EV5:EY5) -> 0
A6: ФТТ | B6: 0.7 | C6: 0.2 | D6: 0.1 | E6: 0.7 | F6: 0.2 | G6: 0.1 | H6: 0.7 | I6: 0.2 | J6: 0.1 | K6: 0.7 | L6: 0.2 | M6: 0.1 | N6: 0.7 | O6: 0.2 | P6: 0.1 | Q6: 0.7 | R6: 0.2 | S6: 0.1 | T6: 0.7 | U6: 0.2 | V6: 0.1 | W6: 0.7 | X6: 0.2 | Y6: 0.1 | Z6: 0.7 | AA6: 0.2 | AB6: 0.1 | AC6: 0.7 | AD6: 0.2 | AE6: 0.1 | AF6: 0.7 | AG6: 0.2 | AH6: 0.1 | AI6: 0.7 | AJ6: 0.2 | AK6: 0.1 | AL6: 0.7 | AM6: 0.2 | AN6: 0.1 | AO6: 0.7 | AP6: 0.2 | AQ6: 0.1 | AR6: 0.7 | AS6: 0.2 | AT6: 0.1 | AU6: 0.7 | AV6: 0.2 | AW6: 0.1 | AX6: 0.7 | AY6: 0.2 | AZ6: 0.1 | BA6: 0.7 | BB6: 0.2 | BC6: 0.1 | BD6: 0.7 | BE6: 0.2 | BF6: 0.1 | BG6: 0.7 | BH6: 0.2 | BI6: 0.1 | BJ6: 0.7 | BK6: 0.2 | BL6: 0.1 | BM6: 0.7 | BN6: 0.2 | BO6: 0.1 | BP6: 0.7 | BQ6: 0.2 | BR6: 0.1 | BS6: 0.7 | BT6: 0.2 | BU6: 0.1 | BV6: 0.7 | BW6: 0.2 | BX6: 0.1 | BY6: 0.7 | BZ6: 0.2 | CA6: 0.1 | CB6: 0.7 | CC6: 0.2 | CD6: 0.1 | CE6: 0.7 | CF6: 0.2 | CG6: 0.1 | CH6: 0.7 | CI6: 0.2 | CJ6: 0.1 | CK6: 0.7 | CL6: 0.2 | CM6: 0.1 | CN6: =ТрЗ_ОП!$R$13 -> 0 | CO6: =IF(CN6=1,IF($B$1=1,'Документы АСУТП'!CW8,IF($B$1=2,'Документы АСУТП'!CW9,IF($B$1=3,'Документы АСУТП'!CW10,'Документы АСУТП'!CW8))),0) -> 0 | CP6: =ТрЗ_ОП!$R$13 -> 0 | CQ6: =IF(CP6=1,IF($B$1=1,'Документы АСУТП'!CX8,IF($B$1=2,'Документы АСУТП'!CX9,IF($B$1=3,'Документы АСУТП'!CX10,'Документы АСУТП'!CX8))),0) -> 0 | CR6: =ТрЗ_ОП!$R$13 -> 0 | CS6: =IF(CR6=1,IF($B$1=1,'Документы АСУТП'!CY8,IF($B$1=2,'Документы АСУТП'!CY9,IF($B$1=3,'Документы АСУТП'!CY10,'Документы АСУТП'!CY8))),0) -> 0 | CT6: =ТрЗ_ОП!$R$13 -> 0 | CU6: =IF(CT6=1,IF($B$1=1,'Документы АСУТП'!CZ8,IF($B$1=2,'Документы АСУТП'!CZ9,IF($B$1=3,'Документы АСУТП'!CZ10,'Документы АСУТП'!CZ8))),0) -> 0 | CV6: =ТрЗ_ОП!$R$13 -> 0 | CW6: =IF(CV6=1,IF($B$1=1,'Документы АСУТП'!DA8,IF($B$1=2,'Документы АСУТП'!DA9,IF($B$1=3,'Документы АСУТП'!DA10,'Документы АСУТП'!DA8))),0) -> 0 | CX6: =ТрЗ_ОП!$R$13 -> 0 | CY6: =IF(CX6=1,IF($B$1=1,'Документы АСУТП'!DB8,IF($B$1=2,'Документы АСУТП'!DB9,IF($B$1=3,'Документы АСУТП'!DB10,'Документы АСУТП'!DB8))),0) -> 0 | CZ6: =ТрЗ_ОП!$R$13 -> 0 | DA6: =IF(CZ6=1,IF($B$1=1,'Документы АСУТП'!DC8,IF($B$1=2,'Документы АСУТП'!DC9,IF($B$1=3,'Документы АСУТП'!DC10,'Документы АСУТП'!DC8))),0) -> 0 | DB6: =ТрЗ_ОП!$R$13 -> 0 | DC6: =IF(DB6=1,IF($B$1=1,'Документы АСУТП'!DD8,IF($B$1=2,'Документы АСУТП'!DD9,IF($B$1=3,'Документы АСУТП'!DD10,'Документы АСУТП'!DD8))),0) -> 0 | DD6: =ТрЗ_ОП!$R$13 -> 0 | DE6: =IF(DD6=1,IF($B$1=1,'Документы АСУТП'!DF8,IF($B$1=2,'Документы АСУТП'!DF9,IF($B$1=3,'Документы АСУТП'!DF10,'Документы АСУТП'!DF8))),0) -> 0 | DF6: =ТрЗ_ОП!$R$13 -> 0 | DG6: =IF(DF6=1,IF($B$1=1,'Документы АСУТП'!DE8,IF($B$1=2,'Документы АСУТП'!DE9,IF($B$1=3,'Документы АСУТП'!DE10,'Документы АСУТП'!DE8))),0) -> 0 | DH6: =ТрЗ_ОП!$R$13 -> 0 | DI6: =IF(DH6=1,IF($B$1=1,'Документы АСУТП'!DG8,IF($B$1=2,'Документы АСУТП'!DG9,IF($B$1=3,'Документы АСУТП'!DG10,'Документы АСУТП'!DG8))),0) -> 0 | DJ6: =ТрЗ_ОП!$R$13 -> 0 | DK6: =IF(DJ6=1,IF($B$1=1,'Документы АСУТП'!DH8,IF($B$1=2,'Документы АСУТП'!DH9,IF($B$1=3,'Документы АСУТП'!DH10,'Документы АСУТП'!DH8))),0) -> 0 | DL6: =ТрЗ_ОП!$R$13 -> 0 | DM6: =IF(DL6=1,IF($B$1=1,'Документы АСУТП'!DI8,IF($B$1=2,'Документы АСУТП'!DI9,IF($B$1=3,'Документы АСУТП'!DI10,'Документы АСУТП'!DI8))),0) -> 0 | DN6: =ТрЗ_ОП!$R$13 -> 0 | DO6: =IF(DN6=1,IF($B$1=1,'Документы АСУТП'!DJ8,IF($B$1=2,'Документы АСУТП'!DJ9,IF($B$1=3,'Документы АСУТП'!DJ10,'Документы АСУТП'!DJ8))),0) -> 0 | DP6: =ТрЗ_ОП!$R$13 -> 0 | DQ6: =IF(DP6=1,IF($B$1=1,'Документы АСУТП'!DK8,IF($B$1=2,'Документы АСУТП'!DK9,IF($B$1=3,'Документы АСУТП'!DK10,'Документы АСУТП'!DK8))),0) -> 0 | DR6: =ТрЗ_ОП!$R$13 -> 0 | DS6: =IF(DR6=1,IF($B$1=1,'Документы АСУТП'!DL8,IF($B$1=2,'Документы АСУТП'!DL9,IF($B$1=3,'Документы АСУТП'!DL10,'Документы АСУТП'!DL8))),0) -> 0 | DT6: =ТрЗ_ОП!$R$13 -> 0 | DU6: =IF(DT6=1,IF($B$1=1,'Документы АСУТП'!DM8,IF($B$1=2,'Документы АСУТП'!DM9,IF($B$1=3,'Документы АСУТП'!DM10,'Документы АСУТП'!DM8))),0) -> 0 | DV6: =ТрЗ_ОП!$R$13 -> 0 | DW6: =IF(DV6=1,IF($B$1=1,'Документы АСУТП'!DN8,IF($B$1=2,'Документы АСУТП'!DN9,IF($B$1=3,'Документы АСУТП'!DN10,'Документы АСУТП'!DN8))),0) -> 0 | DX6: =ТрЗ_ОП!$R$13 -> 0 | DY6: =IF(DX6=1,IF($B$1=1,'Документы АСУТП'!DO8,IF($B$1=2,'Документы АСУТП'!DO9,IF($B$1=3,'Документы АСУТП'!DO10,'Документы АСУТП'!DO8))),0) -> 0 | DZ6: =ТрЗ_ОП!$R$13 -> 0 | EA6: =IF(DZ6=1,IF($B$1=1,'Документы АСУТП'!DP8,IF($B$1=2,'Документы АСУТП'!DP9,IF($B$1=3,'Документы АСУТП'!DP10,'Документы АСУТП'!DP8))),0) -> 0 | EB6: =ТрЗ_ОП!$R$13 -> 0 | EC6: =IF(EB6=1,IF($B$1=1,'Документы АСУТП'!DQ8,IF($B$1=2,'Документы АСУТП'!DQ9,IF($B$1=3,'Документы АСУТП'!DQ10,'Документы АСУТП'!DQ8))),0) -> 0 | ED6: =ТрЗ_ОП!$R$13 -> 0 | EE6: =IF(ED6=1,IF($B$1=1,'Документы АСУТП'!DR8,IF($B$1=2,'Документы АСУТП'!DR9,IF($B$1=3,'Документы АСУТП'!DR10,'Документы АСУТП'!DR8))),0) -> 0 | EF6: =ТрЗ_ОП!$R$13 -> 0 | EG6: =IF(EF6=1,IF($B$1=1,'Документы АСУТП'!DS8,IF($B$1=2,'Документы АСУТП'!DS9,IF($B$1=3,'Документы АСУТП'!DS10,'Документы АСУТП'!DS8))),0) -> 0 | EH6: =ТрЗ_ОП!$R$13 -> 0 | EI6: =IF(EH6=1,IF($B$1=1,'Документы АСУТП'!DT8,IF($B$1=2,'Документы АСУТП'!DT9,IF($B$1=3,'Документы АСУТП'!DT10,'Документы АСУТП'!DT8))),0) -> 0 | EJ6: =ТрЗ_ОП!$R$13 -> 0 | EK6: =IF(EJ6=1,IF($B$1=1,'Документы АСУТП'!DU8,IF($B$1=2,'Документы АСУТП'!DU9,IF($B$1=3,'Документы АСУТП'!DU10,'Документы АСУТП'!DU8))),0) -> 0 | EL6: =ТрЗ_ОП!$R$13 -> 0 | EM6: =IF(EL6=1,IF($B$1=1,'Документы АСУТП'!DV8,IF($B$1=2,'Документы АСУТП'!DV9,IF($B$1=3,'Документы АСУТП'!DV10,'Документы АСУТП'!DV8))),0) -> 0 | EN6: =ТрЗ_ОП!$R$13 -> 0 | EO6: =IF(EN6=1,IF($B$1=1,'Документы АСУТП'!DW8,IF($B$1=2,'Документы АСУТП'!DW9,IF($B$1=3,'Документы АСУТП'!DW10,'Документы АСУТП'!DW8))),0) -> 0 | EP6: =ТрЗ_ОП!$R$13 -> 0 | EQ6: =IF(EP6=1,IF($B$1=1,'Документы АСУТП'!DX8,IF($B$1=2,'Документы АСУТП'!DX9,IF($B$1=3,'Документы АСУТП'!DX10,'Документы АСУТП'!DX8))),0) -> 0 | ER6: =ТрЗ_ОП!$R$13 -> 0 | ES6: =IF(ER6=1,IF($B$1=1,'Документы АСУТП'!DY8,IF($B$1=2,'Документы АСУТП'!DY9,IF($B$1=3,'Документы АСУТП'!DY10,'Документы АСУТП'!DY8))),0) -> 0 | ET6: =ТрЗ_ОП!$R$13 -> 0 | EU6: =IF(ET6=1,IF($B$1=1,'Документы АСУТП'!DZ8,IF($B$1=2,'Документы АСУТП'!DZ9,IF($B$1=3,'Документы АСУТП'!DZ10,'Документы АСУТП'!DZ8))),0) -> 0 | EV6: =B6*$CO6+E6*$CQ6+H6*$CS6+K6*$CU6+N6*$CW6+Q6*$CY6+T6*$DA6+W6*$DC6+Z6*$DE6+AC6*$DG6+AF6*$DI6+AI6*$DK6+AL6*$DM6+AO6*$DO6+AR6*$DQ6+AU6*$DS6+AX6*$DU6+BA6*$DW6+BD6*$DY6+BG6*$EA6+BJ6*$EC6+BM6*$EE6+BP6*$EG6+BS6*$EI6+BV6*$EK6+BY6*$EM6+CB6*$EO6+CE6*$EQ6+CH6*$ES6+$CK6*$EU6 -> 0 | EW6: =C6*$CO6+F6*$CQ6+I6*$CS6+L6*$CU6+O6*$CW6+R6*$CY6+U6*$DA6+X6*$DC6+AA6*$DE6+AD6*$DG6+AG6*$DI6+AJ6*$DK6+AM6*$DM6+AP6*$DO6+AS6*$DQ6+AV6*$DS6+AY6*$DU6+BB6*$DW6+BE6*$DY6+BH6*$EA6+BK6*$EC6+BN6*$EE6+BQ6*$EG6+BT6*$EI6+BW6*$EK6+BZ6*$EM6+CC6*$EO6+CF6*$EQ6+CI6*$ES6+$CL6*$EU6 -> 0 | EX6: =D6*$CO6+G6*$CQ6+J6*$CS6+M6*$CU6+P6*$CW6+S6*$CY6+V6*$DA6+Y6*$DC6+AB6*$DE6+AE6*$DG6+AH6*$DI6+AK6*$DK6+AN6*$DM6+AQ6*$DO6+AT6*$DQ6+AW6*$DS6+AZ6*$DU6+BC6*$DW6+BF6*$DY6+BI6*$EA6+BL6*$EC6+BO6*$EE6+BR6*$EG6+BU6*$EI6+BX6*$EK6+CA6*$EM6+CD6*$EO6+CG6*$EQ6+CJ6*$ES6+$CM6*$EU6 -> 0 | EY6: =SUM(EV6:EX6)*0.05 -> 0 | EZ6: =SUM(EV6:EY6) -> 0
A7: ЭП
A8: Пояснительная записка к эскизному проекту | B8: 0.7 | C8: 0.25 | D8: 0.05 | E8: 0.5 | F8: 0.3 | G8: 0.2 | H8: 0.7 | I8: 0.25 | J8: 0.05 | K8: 0.6 | L8: 0.3 | M8: 0.1 | N8: 0.5 | O8: 0.3 | P8: 0.2 | Q8: 0.6 | R8: 0.3 | S8: 0.1 | T8: 0.7 | U8: 0.25 | V8: 0.05 | W8: 0.6 | X8: 0.3 | Y8: 0.1 | Z8: 0.6 | AA8: 0.3 | AB8: 0.1 | AC8: 0.4 | AD8: 0.3 | AE8: 0.3 | AF8: 0.6 | AG8: 0.3 | AH8: 0.1 | AI8: 0.5 | AJ8: 0.3 | AK8: 0.2 | AL8: 0.4 | AM8: 0.3 | AN8: 0.3 | AO8: 0.4 | AP8: 0.3 | AQ8: 0.3 | AR8: 0.5 | AS8: 0.3 | AT8: 0.2 | AU8: 0.5 | AV8: 0.3 | AW8: 0.2 | AX8: 0.4 | AY8: 0.3 | AZ8: 0.3 | BA8: 0.5 | BB8: 0.3 | BC8: 0.2 | BD8: 0.5 | BE8: 0.3 | BF8: 0.2 | BG8: 0.5 | BH8: 0.3 | BI8: 0.2 | BJ8: 0.4 | BK8: 0.3 | BL8: 0.3 | BM8: 0.4 | BN8: 0.3 | BO8: 0.3 | BP8: 0.4 | BQ8: 0.3 | BR8: 0.3 | BS8: 0.5 | BT8: 0.3 | BU8: 0.2 | BV8: 0.5 | BW8: 0.3 | BX8: 0.2 | BY8: 0.4 | BZ8: 0.3 | CA8: 0.3 | CB8: 0.5 | CC8: 0.3 | CD8: 0.2 | CE8: 0.5 | CF8: 0.3 | CG8: 0.2 | CH8: 0.4 | CI8: 0.3 | CJ8: 0.3 | CK8: 0.4 | CL8: 0.3 | CM8: 0.3 | CN8: =ТрЗ_ОП!$R$15 -> 0 | CO8: =IF(CN8=1,IF($B$1=1,'Документы АСУТП'!CW12,IF($B$1=2,'Документы АСУТП'!CW13,IF($B$1=3,'Документы АСУТП'!CW14,'Документы АСУТП'!CW12))),0) -> 0 | CP8: =ТрЗ_ОП!$R$15 -> 0 | CQ8: =IF(CP8=1,IF($B$1=1,'Документы АСУТП'!CX12,IF($B$1=2,'Документы АСУТП'!CX13,IF($B$1=3,'Документы АСУТП'!CX14,'Документы АСУТП'!CX12))),0) -> 0 | CR8: =ТрЗ_ОП!$R$15 -> 0 | CS8: =IF(CR8=1,IF($B$1=1,'Документы АСУТП'!CY12,IF($B$1=2,'Документы АСУТП'!CY13,IF($B$1=3,'Документы АСУТП'!CY14,'Документы АСУТП'!CY12))),0) -> 0 | CT8: =ТрЗ_ОП!$R$15 -> 0 | CU8: =IF(CT8=1,IF($B$1=1,'Документы АСУТП'!CZ12,IF($B$1=2,'Документы АСУТП'!CZ13,IF($B$1=3,'Документы АСУТП'!CZ14,'Документы АСУТП'!CZ12))),0) -> 0 | CV8: =ТрЗ_ОП!$R$15 -> 0 | CW8: =IF(CV8=1,IF($B$1=1,'Документы АСУТП'!DA12,IF($B$1=2,'Документы АСУТП'!DA13,IF($B$1=3,'Документы АСУТП'!DA14,'Документы АСУТП'!DA12))),0) -> 0 | CX8: =ТрЗ_ОП!$R$15 -> 0 | CY8: =IF(CX8=1,IF($B$1=1,'Документы АСУТП'!DB12,IF($B$1=2,'Документы АСУТП'!DB13,IF($B$1=3,'Документы АСУТП'!DB14,'Документы АСУТП'!DB12))),0) -> 0 | CZ8: =ТрЗ_ОП!$R$15 -> 0 | DA8: =IF(CZ8=1,IF($B$1=1,'Документы АСУТП'!DC12,IF($B$1=2,'Документы АСУТП'!DC13,IF($B$1=3,'Документы АСУТП'!DC14,'Документы АСУТП'!DC12))),0) -> 0 | DB8: =ТрЗ_ОП!$R$15 -> 0 | DC8: =IF(DB8=1,IF($B$1=1,'Документы АСУТП'!DD12,IF($B$1=2,'Документы АСУТП'!DD13,IF($B$1=3,'Документы АСУТП'!DD14,'Документы АСУТП'!DD12))),0) -> 0 | DD8: =ТрЗ_ОП!$R$15 -> 0 | DE8: =IF(DD8=1,IF($B$1=1,'Документы АСУТП'!DF12,IF($B$1=2,'Документы АСУТП'!DF13,IF($B$1=3,'Документы АСУТП'!DF14,'Документы АСУТП'!DF12))),0) -> 0 | DF8: =ТрЗ_ОП!$R$15 -> 0 | DG8: =IF(DF8=1,IF($B$1=1,'Документы АСУТП'!DE12,IF($B$1=2,'Документы АСУТП'!DE13,IF($B$1=3,'Документы АСУТП'!DE14,'Документы АСУТП'!DE12))),0) -> 0 | DH8: =ТрЗ_ОП!$R$15 -> 0 | DI8: =IF(DH8=1,IF($B$1=1,'Документы АСУТП'!DG12,IF($B$1=2,'Документы АСУТП'!DG13,IF($B$1=3,'Документы АСУТП'!DG14,'Документы АСУТП'!DG12))),0) -> 0 | DJ8: =ТрЗ_ОП!$R$15 -> 0 | DK8: =IF(DJ8=1,IF($B$1=1,'Документы АСУТП'!DH12,IF($B$1=2,'Документы АСУТП'!DH13,IF($B$1=3,'Документы АСУТП'!DH14,'Документы АСУТП'!DH12))),0) -> 0 | DL8: =ТрЗ_ОП!$R$15 -> 0 | DM8: =IF(DL8=1,IF($B$1=1,'Документы АСУТП'!DI12,IF($B$1=2,'Документы АСУТП'!DI13,IF($B$1=3,'Документы АСУТП'!DI14,'Документы АСУТП'!DI12))),0) -> 0 | DN8: =ТрЗ_ОП!$R$15 -> 0 | DO8: =IF(DN8=1,IF($B$1=1,'Документы АСУТП'!DJ12,IF($B$1=2,'Документы АСУТП'!DJ13,IF($B$1=3,'Документы АСУТП'!DJ14,'Документы АСУТП'!DJ12))),0) -> 0 | DP8: =ТрЗ_ОП!$R$15 -> 0 | DQ8: =IF(DP8=1,IF($B$1=1,'Документы АСУТП'!DK12,IF($B$1=2,'Документы АСУТП'!DK13,IF($B$1=3,'Документы АСУТП'!DK14,'Документы АСУТП'!DK12))),0) -> 0 | DR8: =ТрЗ_ОП!$R$15 -> 0 | DS8: =IF(DR8=1,IF($B$1=1,'Документы АСУТП'!DL12,IF($B$1=2,'Документы АСУТП'!DL13,IF($B$1=3,'Документы АСУТП'!DL14,'Документы АСУТП'!DL12))),0) -> 0 | DT8: =ТрЗ_ОП!$R$15 -> 0 | DU8: =IF(DT8=1,IF($B$1=1,'Документы АСУТП'!DM12,IF($B$1=2,'Документы АСУТП'!DM13,IF($B$1=3,'Документы АСУТП'!DM14,'Документы АСУТП'!DM12))),0) -> 0 | DV8: =ТрЗ_ОП!$R$15 -> 0 | DW8: =IF(DV8=1,IF($B$1=1,'Документы АСУТП'!DN12,IF($B$1=2,'Документы АСУТП'!DN13,IF($B$1=3,'Документы АСУТП'!DN14,'Документы АСУТП'!DN12))),0) -> 0 | DX8: =ТрЗ_ОП!$R$15 -> 0 | DY8: =IF(DX8=1,IF($B$1=1,'Документы АСУТП'!DO12,IF($B$1=2,'Документы АСУТП'!DO13,IF($B$1=3,'Документы АСУТП'!DO14,'Документы АСУТП'!DO12))),0) -> 0 | DZ8: =ТрЗ_ОП!$R$15 -> 0 | EA8: =IF(DZ8=1,IF($B$1=1,'Документы АСУТП'!DP12,IF($B$1=2,'Документы АСУТП'!DP13,IF($B$1=3,'Документы АСУТП'!DP14,'Документы АСУТП'!DP12))),0) -> 0 | EB8: =ТрЗ_ОП!$R$15 -> 0 | EC8: =IF(EB8=1,IF($B$1=1,'Документы АСУТП'!DQ12,IF($B$1=2,'Документы АСУТП'!DQ13,IF($B$1=3,'Документы АСУТП'!DQ14,'Документы АСУТП'!DQ12))),0) -> 0 | ED8: =ТрЗ_ОП!$R$15 -> 0 | EE8: =IF(ED8=1,IF($B$1=1,'Документы АСУТП'!DR12,IF($B$1=2,'Документы АСУТП'!DR13,IF($B$1=3,'Документы АСУТП'!DR14,'Документы АСУТП'!DR12))),0) -> 0 | EF8: =ТрЗ_ОП!$R$15 -> 0 | EG8: =IF(EF8=1,IF($B$1=1,'Документы АСУТП'!DS12,IF($B$1=2,'Документы АСУТП'!DS13,IF($B$1=3,'Документы АСУТП'!DS14,'Документы АСУТП'!DS12))),0) -> 0 | EH8: =ТрЗ_ОП!$R$15 -> 0 | EI8: =IF(EH8=1,IF($B$1=1,'Документы АСУТП'!DT12,IF($B$1=2,'Документы АСУТП'!DT13,IF($B$1=3,'Документы АСУТП'!DT14,'Документы АСУТП'!DT12))),0) -> 0 | EJ8: =ТрЗ_ОП!$R$15 -> 0 | EK8: =IF(EJ8=1,IF($B$1=1,'Документы АСУТП'!DU12,IF($B$1=2,'Документы АСУТП'!DU13,IF($B$1=3,'Документы АСУТП'!DU14,'Документы АСУТП'!DU12))),0) -> 0 | EL8: =ТрЗ_ОП!$R$15 -> 0 | EM8: =IF(EL8=1,IF($B$1=1,'Документы АСУТП'!DV12,IF($B$1=2,'Документы АСУТП'!DV13,IF($B$1=3,'Документы АСУТП'!DV14,'Документы АСУТП'!DV12))),0) -> 0 | EN8: =ТрЗ_ОП!$R$15 -> 0 | EO8: =IF(EN8=1,IF($B$1=1,'Документы АСУТП'!DW12,IF($B$1=2,'Документы АСУТП'!DW13,IF($B$1=3,'Документы АСУТП'!DW14,'Документы АСУТП'!DW12))),0) -> 0 | EP8: =ТрЗ_ОП!$R$15 -> 0 | EQ8: =IF(EP8=1,IF($B$1=1,'Документы АСУТП'!DX12,IF($B$1=2,'Документы АСУТП'!DX13,IF($B$1=3,'Документы АСУТП'!DX14,'Документы АСУТП'!DX12))),0) -> 0 | ER8: =ТрЗ_ОП!$R$15 -> 0 | ES8: =IF(ER8=1,IF($B$1=1,'Документы АСУТП'!DY12,IF($B$1=2,'Документы АСУТП'!DY13,IF($B$1=3,'Документы АСУТП'!DY14,'Документы АСУТП'!DY12))),0) -> 0 | ET8: =ТрЗ_ОП!$R$15 -> 0 | EU8: =IF(ET8=1,IF($B$1=1,'Документы АСУТП'!DZ12,IF($B$1=2,'Документы АСУТП'!DZ13,IF($B$1=3,'Документы АСУТП'!DZ14,'Документы АСУТП'!DZ12))),0) -> 0 | EV8: =B8*$CO8+E8*$CQ8+H8*$CS8+K8*$CU8+N8*$CW8+Q8*$CY8+T8*$DA8+W8*$DC8+Z8*$DE8+AC8*$DG8+AF8*$DI8+AI8*$DK8+AL8*$DM8+AO8*$DO8+AR8*$DQ8+AU8*$DS8+AX8*$DU8+BA8*$DW8+BD8*$DY8+BG8*$EA8+BJ8*$EC8+BM8*$EE8+BP8*$EG8+BS8*$EI8+BV8*$EK8+BY8*$EM8+CB8*$EO8+CE8*$EQ8+CH8*$ES8+$CK8*$EU8 -> 0 | EW8: =C8*$CO8+F8*$CQ8+I8*$CS8+L8*$CU8+O8*$CW8+R8*$CY8+U8*$DA8+X8*$DC8+AA8*$DE8+AD8*$DG8+AG8*$DI8+AJ8*$DK8+AM8*$DM8+AP8*$DO8+AS8*$DQ8+AV8*$DS8+AY8*$DU8+BB8*$DW8+BE8*$DY8+BH8*$EA8+BK8*$EC8+BN8*$EE8+BQ8*$EG8+BT8*$EI8+BW8*$EK8+BZ8*$EM8+CC8*$EO8+CF8*$EQ8+CI8*$ES8+$CL8*$EU8 -> 0 | EX8: =D8*$CO8+G8*$CQ8+J8*$CS8+M8*$CU8+P8*$CW8+S8*$CY8+V8*$DA8+Y8*$DC8+AB8*$DE8+AE8*$DG8+AH8*$DI8+AK8*$DK8+AN8*$DM8+AQ8*$DO8+AT8*$DQ8+AW8*$DS8+AZ8*$DU8+BC8*$DW8+BF8*$DY8+BI8*$EA8+BL8*$EC8+BO8*$EE8+BR8*$EG8+BU8*$EI8+BX8*$EK8+CA8*$EM8+CD8*$EO8+CG8*$EQ8+CJ8*$ES8+$CM8*$EU8 -> 0 | EY8: =SUM(EV8:EX8)*0.05 -> 0 | EZ8: =SUM(EV8:EY8) -> 0
A9: ТП
A10: Ведомость технического проекта | B10: 0.95 | C10: 0.05 | D10: 0 | E10: 0.95 | F10: 0.05 | G10: 0 | H10: 0.95 | I10: 0.05 | J10: 0 | K10: 0.95 | L10: 0.05 | M10: 0 | N10: 0.95 | O10: 0.05 | P10: 0 | Q10: 0.95 | R10: 0.05 | S10: 0 | T10: 0.95 | U10: 0.05 | V10: 0 | W10: 0.95 | X10: 0.05 | Y10: 0 | Z10: 0.95 | AA10: 0.05 | AB10: 0 | AC10: 0.95 | AD10: 0.05 | AE10: 0 | AF10: 0.95 | AG10: 0.05 | AH10: 0 | AI10: 0.95 | AJ10: 0.05 | AK10: 0 | AL10: 0.95 | AM10: 0.05 | AN10: 0 | AO10: 0.95 | AP10: 0.05 | AQ10: 0 | AR10: 0.95 | AS10: 0.05 | AT10: 0 | AU10: 0.95 | AV10: 0.05 | AW10: 0 | AX10: 0.95 | AY10: 0.05 | AZ10: 0 | BA10: 0.95 | BB10: 0.05 | BC10: 0 | BD10: 0.95 | BE10: 0.05 | BF10: 0 | BG10: 0.95 | BH10: 0.05 | BI10: 0 | BJ10: 0.95 | BK10: 0.05 | BL10: 0 | BM10: 0.95 | BN10: 0.05 | BO10: 0 | BP10: 0.95 | BQ10: 0.05 | BR10: 0 | BS10: 0.95 | BT10: 0.05 | BU10: 0 | BV10: 0.95 | BW10: 0.05 | BX10: 0 | BY10: 0.95 | BZ10: 0.05 | CA10: 0 | CB10: 0.95 | CC10: 0.05 | CD10: 0 | CE10: 0.95 | CF10: 0.05 | CG10: 0 | CH10: 0.95 | CI10: 0.05 | CJ10: 0 | CK10: 0.95 | CL10: 0.05 | CM10: 0 | CN10: =ТрЗ_ОП!$R$17 -> 1 | CO10: =IF(CN10=1,IF($B$1=1,'Документы АСУТП'!CW16,IF($B$1=2,'Документы АСУТП'!CW17,IF($B$1=3,'Документы АСУТП'!CW18,'Документы АСУТП'!CW16))),0) -> 0 | CP10: =ТрЗ_ОП!$R$17 -> 1 | CQ10: =IF(CP10=1,IF($B$1=1,'Документы АСУТП'!CX16,IF($B$1=2,'Документы АСУТП'!CX17,IF($B$1=3,'Документы АСУТП'!CX18,'Документы АСУТП'!CX16))),0) -> 0 | CR10: =ТрЗ_ОП!$R$17 -> 1 | CS10: =IF(CR10=1,IF($B$1=1,'Документы АСУТП'!CY16,IF($B$1=2,'Документы АСУТП'!CY17,IF($B$1=3,'Документы АСУТП'!CY18,'Документы АСУТП'!CY16))),0) -> 0 | CT10: =ТрЗ_ОП!$R$17 -> 1 | CU10: =IF(CT10=1,IF($B$1=1,'Документы АСУТП'!CZ16,IF($B$1=2,'Документы АСУТП'!CZ17,IF($B$1=3,'Документы АСУТП'!CZ18,'Документы АСУТП'!CZ16))),0) -> 0 | CV10: =ТрЗ_ОП!$R$17 -> 1 | CW10: =IF(CV10=1,IF($B$1=1,'Документы АСУТП'!DA16,IF($B$1=2,'Документы АСУТП'!DA17,IF($B$1=3,'Документы АСУТП'!DA18,'Документы АСУТП'!DA16))),0) -> 0 | CX10: =ТрЗ_ОП!$R$17 -> 1 | CY10: =IF(CX10=1,IF($B$1=1,'Документы АСУТП'!DB16,IF($B$1=2,'Документы АСУТП'!DB17,IF($B$1=3,'Документы АСУТП'!DB18,'Документы АСУТП'!DB16))),0) -> 0 | CZ10: =ТрЗ_ОП!$R$17 -> 1 | DA10: =IF(CZ10=1,IF($B$1=1,'Документы АСУТП'!DC16,IF($B$1=2,'Документы АСУТП'!DC17,IF($B$1=3,'Документы АСУТП'!DC18,'Документы АСУТП'!DC16))),0) -> 0 | DB10: =ТрЗ_ОП!$R$17 -> 1 | DC10: =IF(DB10=1,IF($B$1=1,'Документы АСУТП'!DD16,IF($B$1=2,'Документы АСУТП'!DD17,IF($B$1=3,'Документы АСУТП'!DD18,'Документы АСУТП'!DD16))),0) -> 0 | DD10: =ТрЗ_ОП!$R$17 -> 1 | DE10: =IF(DD10=1,IF($B$1=1,'Документы АСУТП'!DF16,IF($B$1=2,'Документы АСУТП'!DF17,IF($B$1=3,'Документы АСУТП'!DF18,'Документы АСУТП'!DF16))),0) -> 0 | DF10: =ТрЗ_ОП!$R$17 -> 1 | DG10: =IF(DF10=1,IF($B$1=1,'Документы АСУТП'!DE16,IF($B$1=2,'Документы АСУТП'!DE17,IF($B$1=3,'Документы АСУТП'!DE18,'Документы АСУТП'!DE16))),0) -> 0 | DH10: =ТрЗ_ОП!$R$17 -> 1 | DI10: =IF(DH10=1,IF($B$1=1,'Документы АСУТП'!DG16,IF($B$1=2,'Документы АСУТП'!DG17,IF($B$1=3,'Документы АСУТП'!DG18,'Документы АСУТП'!DG16))),0) -> 0 | DJ10: =ТрЗ_ОП!$R$17 -> 1 | DK10: =IF(DJ10=1,IF($B$1=1,'Документы АСУТП'!DH16,IF($B$1=2,'Документы АСУТП'!DH17,IF($B$1=3,'Документы АСУТП'!DH18,'Документы АСУТП'!DH16))),0) -> 0 | DL10: =ТрЗ_ОП!$R$17 -> 1 | DM10: =IF(DL10=1,IF($B$1=1,'Документы АСУТП'!DI16,IF($B$1=2,'Документы АСУТП'!DI17,IF($B$1=3,'Документы АСУТП'!DI18,'Документы АСУТП'!DI16))),0) -> 0 | DN10: =ТрЗ_ОП!$R$17 -> 1 | DO10: =IF(DN10=1,IF($B$1=1,'Документы АСУТП'!DJ16,IF($B$1=2,'Документы АСУТП'!DJ17,IF($B$1=3,'Документы АСУТП'!DJ18,'Документы АСУТП'!DJ16))),0) -> #REF! | DP10: =ТрЗ_ОП!$R$17 -> 1 | DQ10: =IF(DP10=1,IF($B$1=1,'Документы АСУТП'!DK16,IF($B$1=2,'Документы АСУТП'!DK17,IF($B$1=3,'Документы АСУТП'!DK18,'Документы АСУТП'!DK16))),0) -> 0 | DR10: =ТрЗ_ОП!$R$17 -> 1 | DS10: =IF(DR10=1,IF($B$1=1,'Документы АСУТП'!DL16,IF($B$1=2,'Документы АСУТП'!DL17,IF($B$1=3,'Документы АСУТП'!DL18,'Документы АСУТП'!DL16))),0) -> 0 | DT10: =ТрЗ_ОП!$R$17 -> 1 | DU10: =IF(DT10=1,IF($B$1=1,'Документы АСУТП'!DM16,IF($B$1=2,'Документы АСУТП'!DM17,IF($B$1=3,'Документы АСУТП'!DM18,'Документы АСУТП'!DM16))),0) -> 0 | DV10: =ТрЗ_ОП!$R17 -> 1 | DW10: =IF(DV10=1,IF($B$1=1,'Документы АСУТП'!DN16,IF($B$1=2,'Документы АСУТП'!DN17,IF($B$1=3,'Документы АСУТП'!DN18,'Документы АСУТП'!DN16))),0) -> 0 | DX10: =ТрЗ_ОП!$R17 -> 1 | DY10: =IF(DX10=1,IF($B$1=1,'Документы АСУТП'!DO16,IF($B$1=2,'Документы АСУТП'!DO17,IF($B$1=3,'Документы АСУТП'!DO18,'Документы АСУТП'!DO16))),0) -> 0 | DZ10: =ТрЗ_ОП!$R17 -> 1 | EA10: =IF(DZ10=1,IF($B$1=1,'Документы АСУТП'!DP16,IF($B$1=2,'Документы АСУТП'!DP17,IF($B$1=3,'Документы АСУТП'!DP18,'Документы АСУТП'!DP16))),0) -> 0 | EB10: =ТрЗ_ОП!$R17 -> 1 | EC10: =IF(EB10=1,IF($B$1=1,'Документы АСУТП'!DQ16,IF($B$1=2,'Документы АСУТП'!DQ17,IF($B$1=3,'Документы АСУТП'!DQ18,'Документы АСУТП'!DQ16))),0) -> 0 | ED10: =ТрЗ_ОП!$R17 -> 1 | EE10: =IF(ED10=1,IF($B$1=1,'Документы АСУТП'!DR16,IF($B$1=2,'Документы АСУТП'!DR17,IF($B$1=3,'Документы АСУТП'!DR18,'Документы АСУТП'!DR16))),0) -> 0 | EF10: =ТрЗ_ОП!$R17 -> 1 | EG10: =IF(EF10=1,IF($B$1=1,'Документы АСУТП'!DS16,IF($B$1=2,'Документы АСУТП'!DS17,IF($B$1=3,'Документы АСУТП'!DS18,'Документы АСУТП'!DS16))),0) -> 0 | EH10: =ТрЗ_ОП!$R17 -> 1 | EI10: =IF(EH10=1,IF($B$1=1,'Документы АСУТП'!DT16,IF($B$1=2,'Документы АСУТП'!DT17,IF($B$1=3,'Документы АСУТП'!DT18,'Документы АСУТП'!DT16))),0) -> 0 | EJ10: =ТрЗ_ОП!$R17 -> 1 | EK10: =IF(EJ10=1,IF($B$1=1,'Документы АСУТП'!DU16,IF($B$1=2,'Документы АСУТП'!DU17,IF($B$1=3,'Документы АСУТП'!DU18,'Документы АСУТП'!DU16))),0) -> 0 | EL10: =ТрЗ_ОП!$R17 -> 1 | EM10: =IF(EL10=1,IF($B$1=1,'Документы АСУТП'!DV16,IF($B$1=2,'Документы АСУТП'!DV17,IF($B$1=3,'Документы АСУТП'!DV18,'Документы АСУТП'!DV16))),0) -> 0 | EN10: =ТрЗ_ОП!$R17 -> 1 | EO10: =IF(EN10=1,IF($B$1=1,'Документы АСУТП'!DW16,IF($B$1=2,'Документы АСУТП'!DW17,IF($B$1=3,'Документы АСУТП'!DW18,'Документы АСУТП'!DW16))),0) -> 0 | EP10: =ТрЗ_ОП!$R17 -> 1 | EQ10: =IF(EP10=1,IF($B$1=1,'Документы АСУТП'!DX16,IF($B$1=2,'Документы АСУТП'!DX17,IF($B$1=3,'Документы АСУТП'!DX18,'Документы АСУТП'!DX16))),0) -> 0 | ER10: =ТрЗ_ОП!$R17 -> 1 | ES10: =IF(ER10=1,IF($B$1=1,'Документы АСУТП'!DY16,IF($B$1=2,'Документы АСУТП'!DY17,IF($B$1=3,'Документы АСУТП'!DY18,'Документы АСУТП'!DY16))),0) -> 0 | ET10: =ТрЗ_ОП!$R17 -> 1 | EU10: =IF(ET10=1,IF($B$1=1,'Документы АСУТП'!DZ16,IF($B$1=2,'Документы АСУТП'!DZ17,IF($B$1=3,'Документы АСУТП'!DZ18,'Документы АСУТП'!DZ16))),0) -> 0 | EV10: =B10*$CO10+E10*$CQ10+H10*$CS10+K10*$CU10+N10*$CW10+Q10*$CY10+T10*$DA10+W10*$DC10+Z10*$DE10+AC10*$DG10+AF10*$DI10+AI10*$DK10+AL10*$DM10+AO10*$DO10+AR10*$DQ10+AU10*$DS10+AX10*$DU10+BA10*$DW10+BD10*$DY10+BG10*$EA10+BJ10*$EC10+BM10*$EE10+BP10*$EG10+BS10*$EI10+BV10*$EK10+BY10*$EM10+CB10*$EO10+CE10*$EQ10+CH10*$ES10+$CK10*$EU10 -> #REF! | EW10: =C10*$CO10+F10*$CQ10+I10*$CS10+L10*$CU10+O10*$CW10+R10*$CY10+U10*$DA10+X10*$DC10+AA10*$DE10+AD10*$DG10+AG10*$DI10+AJ10*$DK10+AM10*$DM10+AP10*$DO10+AS10*$DQ10+AV10*$DS10+AY10*$DU10+BB10*$DW10+BE10*$DY10+BH10*$EA10+BK10*$EC10+BN10*$EE10+BQ10*$EG10+BT10*$EI10+BW10*$EK10+BZ10*$EM10+CC10*$EO10+CF10*$EQ10+CI10*$ES10+$CL10*$EU10 -> #REF! | EX10: =D10*$CO10+G10*$CQ10+J10*$CS10+M10*$CU10+P10*$CW10+S10*$CY10+V10*$DA10+Y10*$DC10+AB10*$DE10+AE10*$DG10+AH10*$DI10+AK10*$DK10+AN10*$DM10+AQ10*$DO10+AT10*$DQ10+AW10*$DS10+AZ10*$DU10+BC10*$DW10+BF10*$DY10+BI10*$EA10+BL10*$EC10+BO10*$EE10+BR10*$EG10+BU10*$EI10+BX10*$EK10+CA10*$EM10+CD10*$EO10+CG10*$EQ10+CJ10*$ES10+$CM10*$EU10 -> #REF! | EY10: =SUM(EV10:EX10)*0.05 -> #REF! | EZ10: =SUM(EV10:EY10) -> #REF!
A11: Ведомость покупных изделий | B11: 0.2 | C11: 0.5 | D11: 0.3 | E11: 0.2 | F11: 0.5 | G11: 0.3 | H11: 0.2 | I11: 0.5 | J11: 0.3 | K11: 0.2 | L11: 0.5 | M11: 0.3 | N11: 0.2 | O11: 0.5 | P11: 0.3 | Q11: 0.2 | R11: 0.5 | S11: 0.3 | T11: 0.2 | U11: 0.5 | V11: 0.3 | W11: 0.2 | X11: 0.5 | Y11: 0.3 | Z11: 0.2 | AA11: 0.5 | AB11: 0.3 | AC11: 0.2 | AD11: 0.5 | AE11: 0.3 | AF11: 0.2 | AG11: 0.5 | AH11: 0.3 | AI11: 0.2 | AJ11: 0.5 | AK11: 0.3 | AL11: 0.2 | AM11: 0.5 | AN11: 0.3 | AO11: 0.2 | AP11: 0.5 | AQ11: 0.3 | AR11: 0.2 | AS11: 0.5 | AT11: 0.3 | AU11: 0.2 | AV11: 0.5 | AW11: 0.3 | AX11: 0.2 | AY11: 0.5 | AZ11: 0.3 | BA11: 0.2 | BB11: 0.5 | BC11: 0.3 | BD11: 0.2 | BE11: 0.5 | BF11: 0.3 | BG11: 0.2 | BH11: 0.5 | BI11: 0.3 | BJ11: 0.2 | BK11: 0.5 | BL11: 0.3 | BM11: 0.2 | BN11: 0.5 | BO11: 0.3 | BP11: 0.2 | BQ11: 0.5 | BR11: 0.3 | BS11: 0.2 | BT11: 0.5 | BU11: 0.3 | BV11: 0.2 | BW11: 0.5 | BX11: 0.3 | BY11: 0.2 | BZ11: 0.5 | CA11: 0.3 | CB11: 0.2 | CC11: 0.5 | CD11: 0.3 | CE11: 0.2 | CF11: 0.5 | CG11: 0.3 | CH11: 0.2 | CI11: 0.5 | CJ11: 0.3 | CK11: 0.2 | CL11: 0.5 | CM11: 0.3 | CN11: =ТрЗ_ОП!$R$18 -> - | CO11: =IF(CN11=1,IF($B$1=1,'Документы АСУТП'!CW19,IF($B$1=2,'Документы АСУТП'!CW20,IF($B$1=3,'Документы АСУТП'!CW21,'Документы АСУТП'!CW19))),0) -> 0 | CP11: =ТрЗ_ОП!$R$18 -> - | CQ11: =IF(CP11=1,IF($B$1=1,'Документы АСУТП'!CX19,IF($B$1=2,'Документы АСУТП'!CX20,IF($B$1=3,'Документы АСУТП'!CX21,'Документы АСУТП'!CX19))),0) -> 0 | CR11: =ТрЗ_ОП!$R$18 -> - | CS11: =IF(CR11=1,IF($B$1=1,'Документы АСУТП'!CY19,IF($B$1=2,'Документы АСУТП'!CY20,IF($B$1=3,'Документы АСУТП'!CY21,'Документы АСУТП'!CY19))),0) -> 0 | CT11: =ТрЗ_ОП!$R$18 -> - | CU11: =IF(CT11=1,IF($B$1=1,'Документы АСУТП'!CZ19,IF($B$1=2,'Документы АСУТП'!CZ20,IF($B$1=3,'Документы АСУТП'!CZ21,'Документы АСУТП'!CZ19))),0) -> 0 | CV11: =ТрЗ_ОП!$R$18 -> - | CW11: =IF(CV11=1,IF($B$1=1,'Документы АСУТП'!DA19,IF($B$1=2,'Документы АСУТП'!DA20,IF($B$1=3,'Документы АСУТП'!DA21,'Документы АСУТП'!DA19))),0) -> 0 | CX11: =ТрЗ_ОП!$R$18 -> - | CY11: =IF(CX11=1,IF($B$1=1,'Документы АСУТП'!DB19,IF($B$1=2,'Документы АСУТП'!DB20,IF($B$1=3,'Документы АСУТП'!DB21,'Документы АСУТП'!DB19))),0) -> 0 | CZ11: =ТрЗ_ОП!$R$18 -> - | DA11: =IF(CZ11=1,IF($B$1=1,'Документы АСУТП'!DC19,IF($B$1=2,'Документы АСУТП'!DC20,IF($B$1=3,'Документы АСУТП'!DC21,'Документы АСУТП'!DC19))),0) -> 0 | DB11: =ТрЗ_ОП!$R$18 -> - | DC11: =IF(DB11=1,IF($B$1=1,'Документы АСУТП'!DD19,IF($B$1=2,'Документы АСУТП'!DD20,IF($B$1=3,'Документы АСУТП'!DD21,'Документы АСУТП'!DD19))),0) -> 0 | DD11: =ТрЗ_ОП!$R$18 -> - | DE11: =IF(DD11=1,IF($B$1=1,'Документы АСУТП'!DF19,IF($B$1=2,'Документы АСУТП'!DF20,IF($B$1=3,'Документы АСУТП'!DF21,'Документы АСУТП'!DF19))),0) -> 0 | DF11: =ТрЗ_ОП!$R$18 -> - | DG11: =IF(DF11=1,IF($B$1=1,'Документы АСУТП'!DE19,IF($B$1=2,'Документы АСУТП'!DE20,IF($B$1=3,'Документы АСУТП'!DE21,'Документы АСУТП'!DE19))),0) -> 0 | DH11: =ТрЗ_ОП!$R$18 -> - | DI11: =IF(DH11=1,IF($B$1=1,'Документы АСУТП'!DG19,IF($B$1=2,'Документы АСУТП'!DG20,IF($B$1=3,'Документы АСУТП'!DG21,'Документы АСУТП'!DG19))),0) -> 0 | DJ11: =ТрЗ_ОП!$R$18 -> - | DK11: =IF(DJ11=1,IF($B$1=1,'Документы АСУТП'!DH19,IF($B$1=2,'Документы АСУТП'!DH20,IF($B$1=3,'Документы АСУТП'!DH21,'Документы АСУТП'!DH19))),0) -> 0 | DL11: =ТрЗ_ОП!$R$18 -> - | DM11: =IF(DL11=1,IF($B$1=1,'Документы АСУТП'!DI19,IF($B$1=2,'Документы АСУТП'!DI20,IF($B$1=3,'Документы АСУТП'!DI21,'Документы АСУТП'!DI19))),0) -> 0 | DN11: =ТрЗ_ОП!$R$18 -> - | DO11: =IF(DN11=1,IF($B$1=1,'Документы АСУТП'!DJ19,IF($B$1=2,'Документы АСУТП'!DJ20,IF($B$1=3,'Документы АСУТП'!DJ21,'Документы АСУТП'!DJ19))),0) -> 0 | DP11: =ТрЗ_ОП!$R$18 -> - | DQ11: =IF(DP11=1,IF($B$1=1,'Документы АСУТП'!DK19,IF($B$1=2,'Документы АСУТП'!DK20,IF($B$1=3,'Документы АСУТП'!DK21,'Документы АСУТП'!DK19))),0) -> 0 | DR11: =ТрЗ_ОП!$R$18 -> - | DS11: =IF(DR11=1,IF($B$1=1,'Документы АСУТП'!DL19,IF($B$1=2,'Документы АСУТП'!DL20,IF($B$1=3,'Документы АСУТП'!DL21,'Документы АСУТП'!DL19))),0) -> 0 | DT11: =ТрЗ_ОП!$R$18 -> - | DU11: =IF(DT11=1,IF($B$1=1,'Документы АСУТП'!DM19,IF($B$1=2,'Документы АСУТП'!DM20,IF($B$1=3,'Документы АСУТП'!DM21,'Документы АСУТП'!DM19))),0) -> 0 | DV11: =ТрЗ_ОП!$R18 -> - | DW11: =IF(DV11=1,IF($B$1=1,'Документы АСУТП'!DN19,IF($B$1=2,'Документы АСУТП'!DN20,IF($B$1=3,'Документы АСУТП'!DN21,'Документы АСУТП'!DN19))),0) -> 0 | DX11: =ТрЗ_ОП!$R18 -> - | DY11: =IF(DX11=1,IF($B$1=1,'Документы АСУТП'!DO19,IF($B$1=2,'Документы АСУТП'!DO20,IF($B$1=3,'Документы АСУТП'!DO21,'Документы АСУТП'!DO19))),0) -> 0 | DZ11: =ТрЗ_ОП!$R18 -> - | EA11: =IF(DZ11=1,IF($B$1=1,'Документы АСУТП'!DP19,IF($B$1=2,'Документы АСУТП'!DP20,IF($B$1=3,'Документы АСУТП'!DP21,'Документы АСУТП'!DP19))),0) -> 0 | EB11: =ТрЗ_ОП!$R18 -> - | EC11: =IF(EB11=1,IF($B$1=1,'Документы АСУТП'!DQ19,IF($B$1=2,'Документы АСУТП'!DQ20,IF($B$1=3,'Документы АСУТП'!DQ21,'Документы АСУТП'!DQ19))),0) -> 0 | ED11: =ТрЗ_ОП!$R18 -> - | EE11: =IF(ED11=1,IF($B$1=1,'Документы АСУТП'!DR19,IF($B$1=2,'Документы АСУТП'!DR20,IF($B$1=3,'Документы АСУТП'!DR21,'Документы АСУТП'!DR19))),0) -> 0 | EF11: =ТрЗ_ОП!$R18 -> - | EG11: =IF(EF11=1,IF($B$1=1,'Документы АСУТП'!DS19,IF($B$1=2,'Документы АСУТП'!DS20,IF($B$1=3,'Документы АСУТП'!DS21,'Документы АСУТП'!DS19))),0) -> 0 | EH11: =ТрЗ_ОП!$R18 -> - | EI11: =IF(EH11=1,IF($B$1=1,'Документы АСУТП'!DT19,IF($B$1=2,'Документы АСУТП'!DT20,IF($B$1=3,'Документы АСУТП'!DT21,'Документы АСУТП'!DT19))),0) -> 0 | EJ11: =ТрЗ_ОП!$R18 -> - | EK11: =IF(EJ11=1,IF($B$1=1,'Документы АСУТП'!DU19,IF($B$1=2,'Документы АСУТП'!DU20,IF($B$1=3,'Документы АСУТП'!DU21,'Документы АСУТП'!DU19))),0) -> 0 | EL11: =ТрЗ_ОП!$R18 -> - | EM11: =IF(EL11=1,IF($B$1=1,'Документы АСУТП'!DV19,IF($B$1=2,'Документы АСУТП'!DV20,IF($B$1=3,'Документы АСУТП'!DV21,'Документы АСУТП'!DV19))),0) -> 0 | EN11: =ТрЗ_ОП!$R18 -> - | EO11: =IF(EN11=1,IF($B$1=1,'Документы АСУТП'!DW19,IF($B$1=2,'Документы АСУТП'!DW20,IF($B$1=3,'Документы АСУТП'!DW21,'Документы АСУТП'!DW19))),0) -> 0 | EP11: =ТрЗ_ОП!$R18 -> - | EQ11: =IF(EP11=1,IF($B$1=1,'Документы АСУТП'!DX19,IF($B$1=2,'Документы АСУТП'!DX20,IF($B$1=3,'Документы АСУТП'!DX21,'Документы АСУТП'!DX19))),0) -> 0 | ER11: =ТрЗ_ОП!$R18 -> - | ES11: =IF(ER11=1,IF($B$1=1,'Документы АСУТП'!DY19,IF($B$1=2,'Документы АСУТП'!DY20,IF($B$1=3,'Документы АСУТП'!DY21,'Документы АСУТП'!DY19))),0) -> 0 | ET11: =ТрЗ_ОП!$R18 -> - | EU11: =IF(ET11=1,IF($B$1=1,'Документы АСУТП'!DZ19,IF($B$1=2,'Документы АСУТП'!DZ20,IF($B$1=3,'Документы АСУТП'!DZ21,'Документы АСУТП'!DZ19))),0) -> 0 | EV11: =B11*$CO11+E11*$CQ11+H11*$CS11+K11*$CU11+N11*$CW11+Q11*$CY11+T11*$DA11+W11*$DC11+Z11*$DE11+AC11*$DG11+AF11*$DI11+AI11*$DK11+AL11*$DM11+AO11*$DO11+AR11*$DQ11+AU11*$DS11+AX11*$DU11+BA11*$DW11+BD11*$DY11+BG11*$EA11+BJ11*$EC11+BM11*$EE11+BP11*$EG11+BS11*$EI11+BV11*$EK11+BY11*$EM11+CB11*$EO11+CE11*$EQ11+CH11*$ES11+$CK11*$EU11 -> 0 | EW11: =C11*$CO11+F11*$CQ11+I11*$CS11+L11*$CU11+O11*$CW11+R11*$CY11+U11*$DA11+X11*$DC11+AA11*$DE11+AD11*$DG11+AG11*$DI11+AJ11*$DK11+AM11*$DM11+AP11*$DO11+AS11*$DQ11+AV11*$DS11+AY11*$DU11+BB11*$DW11+BE11*$DY11+BH11*$EA11+BK11*$EC11+BN11*$EE11+BQ11*$EG11+BT11*$EI11+BW11*$EK11+BZ11*$EM11+CC11*$EO11+CF11*$EQ11+CI11*$ES11+$CL11*$EU11 -> 0 | EX11: =D11*$CO11+G11*$CQ11+J11*$CS11+M11*$CU11+P11*$CW11+S11*$CY11+V11*$DA11+Y11*$DC11+AB11*$DE11+AE11*$DG11+AH11*$DI11+AK11*$DK11+AN11*$DM11+AQ11*$DO11+AT11*$DQ11+AW11*$DS11+AZ11*$DU11+BC11*$DW11+BF11*$DY11+BI11*$EA11+BL11*$EC11+BO11*$EE11+BR11*$EG11+BU11*$EI11+BX11*$EK11+CA11*$EM11+CD11*$EO11+CG11*$EQ11+CJ11*$ES11+$CM11*$EU11 -> 0 | EY11: =SUM(EV11:EX11)*0.05 -> 0 | EZ11: =SUM(EV11:EY11) -> 0
A12: Пояснительная записка к техническому проекту | B12: 0.7 | C12: 0.25 | D12: 0.05 | E12: 0.5 | F12: 0.3 | G12: 0.2 | H12: 0.7 | I12: 0.25 | J12: 0.05 | K12: 0.6 | L12: 0.3 | M12: 0.1 | N12: 0.5 | O12: 0.3 | P12: 0.2 | Q12: 0.6 | R12: 0.3 | S12: 0.1 | T12: 0.7 | U12: 0.25 | V12: 0.05 | W12: 0.6 | X12: 0.3 | Y12: 0.1 | Z12: 0.6 | AA12: 0.3 | AB12: 0.1 | AC12: 0.4 | AD12: 0.3 | AE12: 0.3 | AF12: 0.6 | AG12: 0.3 | AH12: 0.1 | AI12: 0.5 | AJ12: 0.3 | AK12: 0.2 | AL12: 0.4 | AM12: 0.3 | AN12: 0.3 | AO12: 0.4 | AP12: 0.3 | AQ12: 0.3 | AR12: 0.5 | AS12: 0.3 | AT12: 0.2 | AU12: 0.5 | AV12: 0.3 | AW12: 0.2 | AX12: 0.4 | AY12: 0.3 | AZ12: 0.3 | BA12: 0.5 | BB12: 0.3 | BC12: 0.2 | BD12: 0.5 | BE12: 0.3 | BF12: 0.2 | BG12: 0.5 | BH12: 0.3 | BI12: 0.2 | BJ12: 0.4 | BK12: 0.3 | BL12: 0.3 | BM12: 0.4 | BN12: 0.3 | BO12: 0.3 | BP12: 0.4 | BQ12: 0.3 | BR12: 0.3 | BS12: 0.5 | BT12: 0.3 | BU12: 0.2 | BV12: 0.5 | BW12: 0.3 | BX12: 0.2 | BY12: 0.4 | BZ12: 0.3 | CA12: 0.3 | CB12: 0.5 | CC12: 0.3 | CD12: 0.2 | CE12: 0.5 | CF12: 0.3 | CG12: 0.2 | CH12: 0.4 | CI12: 0.3 | CJ12: 0.3 | CK12: 0.4 | CL12: 0.3 | CM12: 0.3 | CN12: =ТрЗ_ОП!$R$19 -> 1 | CO12: =IF(CN12=1,IF($B$1=1,'Документы АСУТП'!CW22,IF($B$1=2,'Документы АСУТП'!CW23,IF($B$1=3,'Документы АСУТП'!CW24,'Документы АСУТП'!CW22))),0) -> 3 | CP12: =ТрЗ_ОП!$R$19 -> 1 | CQ12: =IF(CP12=1,IF($B$1=1,'Документы АСУТП'!CX22,IF($B$1=2,'Документы АСУТП'!CX23,IF($B$1=3,'Документы АСУТП'!CX24,'Документы АСУТП'!CX22))),0) -> 2.5 | CR12: =ТрЗ_ОП!$R$19 -> 1 | CS12: =IF(CR12=1,IF($B$1=1,'Документы АСУТП'!CY22,IF($B$1=2,'Документы АСУТП'!CY23,IF($B$1=3,'Документы АСУТП'!CY24,'Документы АСУТП'!CY22))),0) -> 0 | CT12: =ТрЗ_ОП!$R$19 -> 1 | CU12: =IF(CT12=1,IF($B$1=1,'Документы АСУТП'!CZ22,IF($B$1=2,'Документы АСУТП'!CZ23,IF($B$1=3,'Документы АСУТП'!CZ24,'Документы АСУТП'!CZ22))),0) -> 0 | CV12: =ТрЗ_ОП!$R$19 -> 1 | CW12: =IF(CV12=1,IF($B$1=1,'Документы АСУТП'!DA22,IF($B$1=2,'Документы АСУТП'!DA23,IF($B$1=3,'Документы АСУТП'!DA24,'Документы АСУТП'!DA22))),0) -> 0 | CX12: =ТрЗ_ОП!$R$19 -> 1 | CY12: =IF(CX12=1,IF($B$1=1,'Документы АСУТП'!DB22,IF($B$1=2,'Документы АСУТП'!DB23,IF($B$1=3,'Документы АСУТП'!DB24,'Документы АСУТП'!DB22))),0) -> 0 | CZ12: =ТрЗ_ОП!$R$19 -> 1 | DA12: =IF(CZ12=1,IF($B$1=1,'Документы АСУТП'!DC22,IF($B$1=2,'Документы АСУТП'!DC23,IF($B$1=3,'Документы АСУТП'!DC24,'Документы АСУТП'!DC22))),0) -> 0 | DB12: =ТрЗ_ОП!$R$19 -> 1 | DC12: =IF(DB12=1,IF($B$1=1,'Документы АСУТП'!DD22,IF($B$1=2,'Документы АСУТП'!DD23,IF($B$1=3,'Документы АСУТП'!DD24,'Документы АСУТП'!DD22))),0) -> 0 | DD12: =ТрЗ_ОП!$R$19 -> 1 | DE12: =IF(DD12=1,IF($B$1=1,'Документы АСУТП'!DF22,IF($B$1=2,'Документы АСУТП'!DF23,IF($B$1=3,'Документы АСУТП'!DF24,'Документы АСУТП'!DF22))),0) -> 0 | DF12: =ТрЗ_ОП!$R$19 -> 1 | DG12: =IF(DF12=1,IF($B$1=1,'Документы АСУТП'!DE22,IF($B$1=2,'Документы АСУТП'!DE23,IF($B$1=3,'Документы АСУТП'!DE24,'Документы АСУТП'!DE22))),0) -> 0 | DH12: =ТрЗ_ОП!$R$19 -> 1 | DI12: =IF(DH12=1,IF($B$1=1,'Документы АСУТП'!DG22,IF($B$1=2,'Документы АСУТП'!DG23,IF($B$1=3,'Документы АСУТП'!DG24,'Документы АСУТП'!DG22))),0) -> 0 | DJ12: =ТрЗ_ОП!$R$19 -> 1 | DK12: =IF(DJ12=1,IF($B$1=1,'Документы АСУТП'!DH22,IF($B$1=2,'Документы АСУТП'!DH23,IF($B$1=3,'Документы АСУТП'!DH24,'Документы АСУТП'!DH22))),0) -> 0 | DL12: =ТрЗ_ОП!$R$19 -> 1 | DM12: =IF(DL12=1,IF($B$1=1,'Документы АСУТП'!DI22,IF($B$1=2,'Документы АСУТП'!DI23,IF($B$1=3,'Документы АСУТП'!DI24,'Документы АСУТП'!DI22))),0) -> 0 | DN12: =ТрЗ_ОП!$R$19 -> 1 | DO12: =IF(DN12=1,IF($B$1=1,'Документы АСУТП'!DJ22,IF($B$1=2,'Документы АСУТП'!DJ23,IF($B$1=3,'Документы АСУТП'!DJ24,'Документы АСУТП'!DJ22))),0) -> #REF! | DP12: =ТрЗ_ОП!$R$19 -> 1 | DQ12: =IF(DP12=1,IF($B$1=1,'Документы АСУТП'!DK22,IF($B$1=2,'Документы АСУТП'!DK23,IF($B$1=3,'Документы АСУТП'!DK24,'Документы АСУТП'!DK22))),0) -> 0 | DR12: =ТрЗ_ОП!$R$19 -> 1 | DS12: =IF(DR12=1,IF($B$1=1,'Документы АСУТП'!DL22,IF($B$1=2,'Документы АСУТП'!DL23,IF($B$1=3,'Документы АСУТП'!DL24,'Документы АСУТП'!DL22))),0) -> 0 | DT12: =ТрЗ_ОП!$R$19 -> 1 | DU12: =IF(DT12=1,IF($B$1=1,'Документы АСУТП'!DM22,IF($B$1=2,'Документы АСУТП'!DM23,IF($B$1=3,'Документы АСУТП'!DM24,'Документы АСУТП'!DM22))),0) -> 0 | DV12: =ТрЗ_ОП!$R19 -> 1 | DW12: =IF(DV12=1,IF($B$1=1,'Документы АСУТП'!DN22,IF($B$1=2,'Документы АСУТП'!DN23,IF($B$1=3,'Документы АСУТП'!DN24,'Документы АСУТП'!DN22))),0) -> 0 | DX12: =ТрЗ_ОП!$R19 -> 1 | DY12: =IF(DX12=1,IF($B$1=1,'Документы АСУТП'!DO22,IF($B$1=2,'Документы АСУТП'!DO23,IF($B$1=3,'Документы АСУТП'!DO24,'Документы АСУТП'!DO22))),0) -> 0 | DZ12: =ТрЗ_ОП!$R19 -> 1 | EA12: =IF(DZ12=1,IF($B$1=1,'Документы АСУТП'!DP22,IF($B$1=2,'Документы АСУТП'!DP23,IF($B$1=3,'Документы АСУТП'!DP24,'Документы АСУТП'!DP22))),0) -> 0 | EB12: =ТрЗ_ОП!$R19 -> 1 | EC12: =IF(EB12=1,IF($B$1=1,'Документы АСУТП'!DQ22,IF($B$1=2,'Документы АСУТП'!DQ23,IF($B$1=3,'Документы АСУТП'!DQ24,'Документы АСУТП'!DQ22))),0) -> 0 | ED12: =ТрЗ_ОП!$R19 -> 1 | EE12: =IF(ED12=1,IF($B$1=1,'Документы АСУТП'!DR22,IF($B$1=2,'Документы АСУТП'!DR23,IF($B$1=3,'Документы АСУТП'!DR24,'Документы АСУТП'!DR22))),0) -> 0 | EF12: =ТрЗ_ОП!$R19 -> 1 | EG12: =IF(EF12=1,IF($B$1=1,'Документы АСУТП'!DS22,IF($B$1=2,'Документы АСУТП'!DS23,IF($B$1=3,'Документы АСУТП'!DS24,'Документы АСУТП'!DS22))),0) -> 0 | EH12: =ТрЗ_ОП!$R19 -> 1 | EI12: =IF(EH12=1,IF($B$1=1,'Документы АСУТП'!DT22,IF($B$1=2,'Документы АСУТП'!DT23,IF($B$1=3,'Документы АСУТП'!DT24,'Документы АСУТП'!DT22))),0) -> 0 | EJ12: =ТрЗ_ОП!$R19 -> 1 | EK12: =IF(EJ12=1,IF($B$1=1,'Документы АСУТП'!DU22,IF($B$1=2,'Документы АСУТП'!DU23,IF($B$1=3,'Документы АСУТП'!DU24,'Документы АСУТП'!DU22))),0) -> 0 | EL12: =ТрЗ_ОП!$R19 -> 1 | EM12: =IF(EL12=1,IF($B$1=1,'Документы АСУТП'!DV22,IF($B$1=2,'Документы АСУТП'!DV23,IF($B$1=3,'Документы АСУТП'!DV24,'Документы АСУТП'!DV22))),0) -> 0 | EN12: =ТрЗ_ОП!$R19 -> 1 | EO12: =IF(EN12=1,IF($B$1=1,'Документы АСУТП'!DW22,IF($B$1=2,'Документы АСУТП'!DW23,IF($B$1=3,'Документы АСУТП'!DW24,'Документы АСУТП'!DW22))),0) -> 0 | EP12: =ТрЗ_ОП!$R19 -> 1 | EQ12: =IF(EP12=1,IF($B$1=1,'Документы АСУТП'!DX22,IF($B$1=2,'Документы АСУТП'!DX23,IF($B$1=3,'Документы АСУТП'!DX24,'Документы АСУТП'!DX22))),0) -> 0 | ER12: =ТрЗ_ОП!$R19 -> 1 | ES12: =IF(ER12=1,IF($B$1=1,'Документы АСУТП'!DY22,IF($B$1=2,'Документы АСУТП'!DY23,IF($B$1=3,'Документы АСУТП'!DY24,'Документы АСУТП'!DY22))),0) -> 0 | ET12: =ТрЗ_ОП!$R19 -> 1 | EU12: =IF(ET12=1,IF($B$1=1,'Документы АСУТП'!DZ22,IF($B$1=2,'Документы АСУТП'!DZ23,IF($B$1=3,'Документы АСУТП'!DZ24,'Документы АСУТП'!DZ22))),0) -> 0 | EV12: =B12*$CO12+E12*$CQ12+H12*$CS12+K12*$CU12+N12*$CW12+Q12*$CY12+T12*$DA12+W12*$DC12+Z12*$DE12+AC12*$DG12+AF12*$DI12+AI12*$DK12+AL12*$DM12+AO12*$DO12+AR12*$DQ12+AU12*$DS12+AX12*$DU12+BA12*$DW12+BD12*$DY12+BG12*$EA12+BJ12*$EC12+BM12*$EE12+BP12*$EG12+BS12*$EI12+BV12*$EK12+BY12*$EM12+CB12*$EO12+CE12*$EQ12+CH12*$ES12+$CK12*$EU12 -> #REF! | EW12: =C12*$CO12+F12*$CQ12+I12*$CS12+L12*$CU12+O12*$CW12+R12*$CY12+U12*$DA12+X12*$DC12+AA12*$DE12+AD12*$DG12+AG12*$DI12+AJ12*$DK12+AM12*$DM12+AP12*$DO12+AS12*$DQ12+AV12*$DS12+AY12*$DU12+BB12*$DW12+BE12*$DY12+BH12*$EA12+BK12*$EC12+BN12*$EE12+BQ12*$EG12+BT12*$EI12+BW12*$EK12+BZ12*$EM12+CC12*$EO12+CF12*$EQ12+CI12*$ES12+$CL12*$EU12 -> #REF! | EX12: =D12*$CO12+G12*$CQ12+J12*$CS12+M12*$CU12+P12*$CW12+S12*$CY12+V12*$DA12+Y12*$DC12+AB12*$DE12+AE12*$DG12+AH12*$DI12+AK12*$DK12+AN12*$DM12+AQ12*$DO12+AT12*$DQ12+AW12*$DS12+AZ12*$DU12+BC12*$DW12+BF12*$DY12+BI12*$EA12+BL12*$EC12+BO12*$EE12+BR12*$EG12+BU12*$EI12+BX12*$EK12+CA12*$EM12+CD12*$EO12+CG12*$EQ12+CJ12*$ES12+$CM12*$EU12 -> #REF! | EY12: =SUM(EV12:EX12)*0.05 -> #REF! | EZ12: =SUM(EV12:EY12) -> #REF!
A13: Описание комплекса технических средств | B13: 0.7 | C13: 0.25 | D13: 0.05 | E13: 0.5 | F13: 0.3 | G13: 0.2 | H13: 0.7 | I13: 0.25 | J13: 0.05 | K13: 0.6 | L13: 0.3 | M13: 0.1 | N13: 0.5 | O13: 0.3 | P13: 0.2 | Q13: 0.6 | R13: 0.3 | S13: 0.1 | T13: 0.7 | U13: 0.25 | V13: 0.05 | W13: 0.6 | X13: 0.3 | Y13: 0.1 | Z13: 0.6 | AA13: 0.3 | AB13: 0.1 | AC13: 0.4 | AD13: 0.3 | AE13: 0.3 | AF13: 0.6 | AG13: 0.3 | AH13: 0.1 | AI13: 0.5 | AJ13: 0.3 | AK13: 0.2 | AL13: 0.4 | AM13: 0.3 | AN13: 0.3 | AO13: 0.4 | AP13: 0.3 | AQ13: 0.3 | AR13: 0.5 | AS13: 0.3 | AT13: 0.2 | AU13: 0.5 | AV13: 0.3 | AW13: 0.2 | AX13: 0.4 | AY13: 0.3 | AZ13: 0.3 | BA13: 0.5 | BB13: 0.3 | BC13: 0.2 | BD13: 0.5 | BE13: 0.3 | BF13: 0.2 | BG13: 0.5 | BH13: 0.3 | BI13: 0.2 | BJ13: 0.4 | BK13: 0.3 | BL13: 0.3 | BM13: 0.4 | BN13: 0.3 | BO13: 0.3 | BP13: 0.4 | BQ13: 0.3 | BR13: 0.3 | BS13: 0.5 | BT13: 0.3 | BU13: 0.2 | BV13: 0.5 | BW13: 0.3 | BX13: 0.2 | BY13: 0.4 | BZ13: 0.3 | CA13: 0.3 | CB13: 0.5 | CC13: 0.3 | CD13: 0.2 | CE13: 0.5 | CF13: 0.3 | CG13: 0.2 | CH13: 0.4 | CI13: 0.3 | CJ13: 0.3 | CK13: 0.4 | CL13: 0.3 | CM13: 0.3 | CN13: =ТрЗ_ОП!$R$20 -> 1 | CO13: =IF(CN13=1,IF($B$1=1,'Документы АСУТП'!CW25,IF($B$1=2,'Документы АСУТП'!CW26,IF($B$1=3,'Документы АСУТП'!CW27,'Документы АСУТП'!CW25))),0) -> 1 | CP13: =ТрЗ_ОП!$R$20 -> 1 | CQ13: =IF(CP13=1,IF($B$1=1,'Документы АСУТП'!CX25,IF($B$1=2,'Документы АСУТП'!CX26,IF($B$1=3,'Документы АСУТП'!CX27,'Документы АСУТП'!CX25))),0) -> 2 | CR13: =ТрЗ_ОП!$R$20 -> 1 | CS13: =IF(CR13=1,IF($B$1=1,'Документы АСУТП'!CY25,IF($B$1=2,'Документы АСУТП'!CY26,IF($B$1=3,'Документы АСУТП'!CY27,'Документы АСУТП'!CY25))),0) -> 0 | CT13: =ТрЗ_ОП!$R$20 -> 1 | CU13: =IF(CT13=1,IF($B$1=1,'Документы АСУТП'!CZ25,IF($B$1=2,'Документы АСУТП'!CZ26,IF($B$1=3,'Документы АСУТП'!CZ27,'Документы АСУТП'!CZ25))),0) -> 0 | CV13: =ТрЗ_ОП!$R$20 -> 1 | CW13: =IF(CV13=1,IF($B$1=1,'Документы АСУТП'!DA25,IF($B$1=2,'Документы АСУТП'!DA26,IF($B$1=3,'Документы АСУТП'!DA27,'Документы АСУТП'!DA25))),0) -> 0 | CX13: =ТрЗ_ОП!$R$20 -> 1 | CY13: =IF(CX13=1,IF($B$1=1,'Документы АСУТП'!DB25,IF($B$1=2,'Документы АСУТП'!DB26,IF($B$1=3,'Документы АСУТП'!DB27,'Документы АСУТП'!DB25))),0) -> 0 | CZ13: =ТрЗ_ОП!$R$20 -> 1 | DA13: =IF(CZ13=1,IF($B$1=1,'Документы АСУТП'!DC25,IF($B$1=2,'Документы АСУТП'!DC26,IF($B$1=3,'Документы АСУТП'!DC27,'Документы АСУТП'!DC25))),0) -> 0 | DB13: =ТрЗ_ОП!$R$20 -> 1 | DC13: =IF(DB13=1,IF($B$1=1,'Документы АСУТП'!DD25,IF($B$1=2,'Документы АСУТП'!DD26,IF($B$1=3,'Документы АСУТП'!DD27,'Документы АСУТП'!DD25))),0) -> 0 | DD13: =ТрЗ_ОП!$R$20 -> 1 | DE13: =IF(DD13=1,IF($B$1=1,'Документы АСУТП'!DF25,IF($B$1=2,'Документы АСУТП'!DF26,IF($B$1=3,'Документы АСУТП'!DF27,'Документы АСУТП'!DF25))),0) -> 0 | DF13: =ТрЗ_ОП!$R$20 -> 1 | DG13: =IF(DF13=1,IF($B$1=1,'Документы АСУТП'!DE25,IF($B$1=2,'Документы АСУТП'!DE26,IF($B$1=3,'Документы АСУТП'!DE27,'Документы АСУТП'!DE25))),0) -> 0 | DH13: =ТрЗ_ОП!$R$20 -> 1 | DI13: =IF(DH13=1,IF($B$1=1,'Документы АСУТП'!DG25,IF($B$1=2,'Документы АСУТП'!DG26,IF($B$1=3,'Документы АСУТП'!DG27,'Документы АСУТП'!DG25))),0) -> 0 | DJ13: =ТрЗ_ОП!$R$20 -> 1 | DK13: =IF(DJ13=1,IF($B$1=1,'Документы АСУТП'!DH25,IF($B$1=2,'Документы АСУТП'!DH26,IF($B$1=3,'Документы АСУТП'!DH27,'Документы АСУТП'!DH25))),0) -> 0 | DL13: =ТрЗ_ОП!$R$20 -> 1 | DM13: =IF(DL13=1,IF($B$1=1,'Документы АСУТП'!DI25,IF($B$1=2,'Документы АСУТП'!DI26,IF($B$1=3,'Документы АСУТП'!DI27,'Документы АСУТП'!DI25))),0) -> 0 | DN13: =ТрЗ_ОП!$R$20 -> 1 | DO13: =IF(DN13=1,IF($B$1=1,'Документы АСУТП'!DJ25,IF($B$1=2,'Документы АСУТП'!DJ26,IF($B$1=3,'Документы АСУТП'!DJ27,'Документы АСУТП'!DJ25))),0) -> #REF! | DP13: =ТрЗ_ОП!$R$20 -> 1 | DQ13: =IF(DP13=1,IF($B$1=1,'Документы АСУТП'!DK25,IF($B$1=2,'Документы АСУТП'!DK26,IF($B$1=3,'Документы АСУТП'!DK27,'Документы АСУТП'!DK25))),0) -> 0 | DR13: =ТрЗ_ОП!$R$20 -> 1 | DS13: =IF(DR13=1,IF($B$1=1,'Документы АСУТП'!DL25,IF($B$1=2,'Документы АСУТП'!DL26,IF($B$1=3,'Документы АСУТП'!DL27,'Документы АСУТП'!DL25))),0) -> 0 | DT13: =ТрЗ_ОП!$R$20 -> 1 | DU13: =IF(DT13=1,IF($B$1=1,'Документы АСУТП'!DM25,IF($B$1=2,'Документы АСУТП'!DM26,IF($B$1=3,'Документы АСУТП'!DM27,'Документы АСУТП'!DM25))),0) -> 0 | DV13: =ТрЗ_ОП!$R20 -> 1 | DW13: =IF(DV13=1,IF($B$1=1,'Документы АСУТП'!DN25,IF($B$1=2,'Документы АСУТП'!DN26,IF($B$1=3,'Документы АСУТП'!DN27,'Документы АСУТП'!DN25))),0) -> 0 | DX13: =ТрЗ_ОП!$R20 -> 1 | DY13: =IF(DX13=1,IF($B$1=1,'Документы АСУТП'!DO25,IF($B$1=2,'Документы АСУТП'!DO26,IF($B$1=3,'Документы АСУТП'!DO27,'Документы АСУТП'!DO25))),0) -> 0 | DZ13: =ТрЗ_ОП!$R20 -> 1 | EA13: =IF(DZ13=1,IF($B$1=1,'Документы АСУТП'!DP25,IF($B$1=2,'Документы АСУТП'!DP26,IF($B$1=3,'Документы АСУТП'!DP27,'Документы АСУТП'!DP25))),0) -> 0 | EB13: =ТрЗ_ОП!$R20 -> 1 | EC13: =IF(EB13=1,IF($B$1=1,'Документы АСУТП'!DQ25,IF($B$1=2,'Документы АСУТП'!DQ26,IF($B$1=3,'Документы АСУТП'!DQ27,'Документы АСУТП'!DQ25))),0) -> 0 | ED13: =ТрЗ_ОП!$R20 -> 1 | EE13: =IF(ED13=1,IF($B$1=1,'Документы АСУТП'!DR25,IF($B$1=2,'Документы АСУТП'!DR26,IF($B$1=3,'Документы АСУТП'!DR27,'Документы АСУТП'!DR25))),0) -> 0 | EF13: =ТрЗ_ОП!$R20 -> 1 | EG13: =IF(EF13=1,IF($B$1=1,'Документы АСУТП'!DS25,IF($B$1=2,'Документы АСУТП'!DS26,IF($B$1=3,'Документы АСУТП'!DS27,'Документы АСУТП'!DS25))),0) -> 0 | EH13: =ТрЗ_ОП!$R20 -> 1 | EI13: =IF(EH13=1,IF($B$1=1,'Документы АСУТП'!DT25,IF($B$1=2,'Документы АСУТП'!DT26,IF($B$1=3,'Документы АСУТП'!DT27,'Документы АСУТП'!DT25))),0) -> 0 | EJ13: =ТрЗ_ОП!$R20 -> 1 | EK13: =IF(EJ13=1,IF($B$1=1,'Документы АСУТП'!DU25,IF($B$1=2,'Документы АСУТП'!DU26,IF($B$1=3,'Документы АСУТП'!DU27,'Документы АСУТП'!DU25))),0) -> 0 | EL13: =ТрЗ_ОП!$R20 -> 1 | EM13: =IF(EL13=1,IF($B$1=1,'Документы АСУТП'!DV25,IF($B$1=2,'Документы АСУТП'!DV26,IF($B$1=3,'Документы АСУТП'!DV27,'Документы АСУТП'!DV25))),0) -> 0 | EN13: =ТрЗ_ОП!$R20 -> 1 | EO13: =IF(EN13=1,IF($B$1=1,'Документы АСУТП'!DW25,IF($B$1=2,'Документы АСУТП'!DW26,IF($B$1=3,'Документы АСУТП'!DW27,'Документы АСУТП'!DW25))),0) -> 0 | EP13: =ТрЗ_ОП!$R20 -> 1 | EQ13: =IF(EP13=1,IF($B$1=1,'Документы АСУТП'!DX25,IF($B$1=2,'Документы АСУТП'!DX26,IF($B$1=3,'Документы АСУТП'!DX27,'Документы АСУТП'!DX25))),0) -> 0 | ER13: =ТрЗ_ОП!$R20 -> 1 | ES13: =IF(ER13=1,IF($B$1=1,'Документы АСУТП'!DY25,IF($B$1=2,'Документы АСУТП'!DY26,IF($B$1=3,'Документы АСУТП'!DY27,'Документы АСУТП'!DY25))),0) -> 0 | ET13: =ТрЗ_ОП!$R20 -> 1 | EU13: =IF(ET13=1,IF($B$1=1,'Документы АСУТП'!DZ25,IF($B$1=2,'Документы АСУТП'!DZ26,IF($B$1=3,'Документы АСУТП'!DZ27,'Документы АСУТП'!DZ25))),0) -> 0 | EV13: =B13*$CO13+E13*$CQ13+H13*$CS13+K13*$CU13+N13*$CW13+Q13*$CY13+T13*$DA13+W13*$DC13+Z13*$DE13+AC13*$DG13+AF13*$DI13+AI13*$DK13+AL13*$DM13+AO13*$DO13+AR13*$DQ13+AU13*$DS13+AX13*$DU13+BA13*$DW13+BD13*$DY13+BG13*$EA13+BJ13*$EC13+BM13*$EE13+BP13*$EG13+BS13*$EI13+BV13*$EK13+BY13*$EM13+CB13*$EO13+CE13*$EQ13+CH13*$ES13+$CK13*$EU13 -> #REF! | EW13: =C13*$CO13+F13*$CQ13+I13*$CS13+L13*$CU13+O13*$CW13+R13*$CY13+U13*$DA13+X13*$DC13+AA13*$DE13+AD13*$DG13+AG13*$DI13+AJ13*$DK13+AM13*$DM13+AP13*$DO13+AS13*$DQ13+AV13*$DS13+AY13*$DU13+BB13*$DW13+BE13*$DY13+BH13*$EA13+BK13*$EC13+BN13*$EE13+BQ13*$EG13+BT13*$EI13+BW13*$EK13+BZ13*$EM13+CC13*$EO13+CF13*$EQ13+CI13*$ES13+$CL13*$EU13 -> #REF! | EX13: =D13*$CO13+G13*$CQ13+J13*$CS13+M13*$CU13+P13*$CW13+S13*$CY13+V13*$DA13+Y13*$DC13+AB13*$DE13+AE13*$DG13+AH13*$DI13+AK13*$DK13+AN13*$DM13+AQ13*$DO13+AT13*$DQ13+AW13*$DS13+AZ13*$DU13+BC13*$DW13+BF13*$DY13+BI13*$EA13+BL13*$EC13+BO13*$EE13+BR13*$EG13+BU13*$EI13+BX13*$EK13+CA13*$EM13+CD13*$EO13+CG13*$EQ13+CJ13*$ES13+$CM13*$EU13 -> #REF! | EY13: =SUM(EV13:EX13)*0.05 -> #REF! | EZ13: =SUM(EV13:EY13) -> #REF!
A14: Описание программного обеспечения | B14: 0.7 | C14: 0.25 | D14: 0.05 | E14: 0.5 | F14: 0.3 | G14: 0.2 | H14: 0.7 | I14: 0.25 | J14: 0.05 | K14: 0.6 | L14: 0.3 | M14: 0.1 | N14: 0.5 | O14: 0.3 | P14: 0.2 | Q14: 0.6 | R14: 0.3 | S14: 0.1 | T14: 0.7 | U14: 0.25 | V14: 0.05 | W14: 0.6 | X14: 0.3 | Y14: 0.1 | Z14: 0.6 | AA14: 0.3 | AB14: 0.1 | AC14: 0.4 | AD14: 0.3 | AE14: 0.3 | AF14: 0.6 | AG14: 0.3 | AH14: 0.1 | AI14: 0.5 | AJ14: 0.3 | AK14: 0.2 | AL14: 0.4 | AM14: 0.3 | AN14: 0.3 | AO14: 0.4 | AP14: 0.3 | AQ14: 0.3 | AR14: 0.5 | AS14: 0.3 | AT14: 0.2 | AU14: 0.5 | AV14: 0.3 | AW14: 0.2 | AX14: 0.4 | AY14: 0.3 | AZ14: 0.3 | BA14: 0.5 | BB14: 0.3 | BC14: 0.2 | BD14: 0.5 | BE14: 0.3 | BF14: 0.2 | BG14: 0.5 | BH14: 0.3 | BI14: 0.2 | BJ14: 0.4 | BK14: 0.3 | BL14: 0.3 | BM14: 0.4 | BN14: 0.3 | BO14: 0.3 | BP14: 0.4 | BQ14: 0.3 | BR14: 0.3 | BS14: 0.5 | BT14: 0.3 | BU14: 0.2 | BV14: 0.5 | BW14: 0.3 | BX14: 0.2 | BY14: 0.4 | BZ14: 0.3 | CA14: 0.3 | CB14: 0.5 | CC14: 0.3 | CD14: 0.2 | CE14: 0.5 | CF14: 0.3 | CG14: 0.2 | CH14: 0.4 | CI14: 0.3 | CJ14: 0.3 | CK14: 0.4 | CL14: 0.3 | CM14: 0.3 | CN14: =ТрЗ_ОП!$R$21 -> 1 | CO14: =IF(CN14=1,IF($B$1=1,'Документы АСУТП'!CW28,IF($B$1=2,'Документы АСУТП'!CW29,IF($B$1=3,'Документы АСУТП'!CW30,'Документы АСУТП'!CW28))),0) -> 3.5 | CP14: =ТрЗ_ОП!$R$21 -> 1 | CQ14: =IF(CP14=1,IF($B$1=1,'Документы АСУТП'!CX28,IF($B$1=2,'Документы АСУТП'!CX29,IF($B$1=3,'Документы АСУТП'!CX30,'Документы АСУТП'!CX28))),0) -> 4 | CR14: =ТрЗ_ОП!$R$21 -> 1 | CS14: =IF(CR14=1,IF($B$1=1,'Документы АСУТП'!CY28,IF($B$1=2,'Документы АСУТП'!CY29,IF($B$1=3,'Документы АСУТП'!CY30,'Документы АСУТП'!CY28))),0) -> 0 | CT14: =ТрЗ_ОП!$R$21 -> 1 | CU14: =IF(CT14=1,IF($B$1=1,'Документы АСУТП'!CZ28,IF($B$1=2,'Документы АСУТП'!CZ29,IF($B$1=3,'Документы АСУТП'!CZ30,'Документы АСУТП'!CZ28))),0) -> 0 | CV14: =ТрЗ_ОП!$R$21 -> 1 | CW14: =IF(CV14=1,IF($B$1=1,'Документы АСУТП'!DA28,IF($B$1=2,'Документы АСУТП'!DA29,IF($B$1=3,'Документы АСУТП'!DA30,'Документы АСУТП'!DA28))),0) -> 0 | CX14: =ТрЗ_ОП!$R$21 -> 1 | CY14: =IF(CX14=1,IF($B$1=1,'Документы АСУТП'!DB28,IF($B$1=2,'Документы АСУТП'!DB29,IF($B$1=3,'Документы АСУТП'!DB30,'Документы АСУТП'!DB28))),0) -> 0 | CZ14: =ТрЗ_ОП!$R$21 -> 1 | DA14: =IF(CZ14=1,IF($B$1=1,'Документы АСУТП'!DC28,IF($B$1=2,'Документы АСУТП'!DC29,IF($B$1=3,'Документы АСУТП'!DC30,'Документы АСУТП'!DC28))),0) -> 0 | DB14: =ТрЗ_ОП!$R$21 -> 1 | DC14: =IF(DB14=1,IF($B$1=1,'Документы АСУТП'!DD28,IF($B$1=2,'Документы АСУТП'!DD29,IF($B$1=3,'Документы АСУТП'!DD30,'Документы АСУТП'!DD28))),0) -> 0 | DD14: =ТрЗ_ОП!$R$21 -> 1 | DE14: =IF(DD14=1,IF($B$1=1,'Документы АСУТП'!DF28,IF($B$1=2,'Документы АСУТП'!DF29,IF($B$1=3,'Документы АСУТП'!DF30,'Документы АСУТП'!DF28))),0) -> 0 | DF14: =ТрЗ_ОП!$R$21 -> 1 | DG14: =IF(DF14=1,IF($B$1=1,'Документы АСУТП'!DE28,IF($B$1=2,'Документы АСУТП'!DE29,IF($B$1=3,'Документы АСУТП'!DE30,'Документы АСУТП'!DE28))),0) -> 0 | DH14: =ТрЗ_ОП!$R$21 -> 1 | DI14: =IF(DH14=1,IF($B$1=1,'Документы АСУТП'!DG28,IF($B$1=2,'Документы АСУТП'!DG29,IF($B$1=3,'Документы АСУТП'!DG30,'Документы АСУТП'!DG28))),0) -> 0 | DJ14: =ТрЗ_ОП!$R$21 -> 1 | DK14: =IF(DJ14=1,IF($B$1=1,'Документы АСУТП'!DH28,IF($B$1=2,'Документы АСУТП'!DH29,IF($B$1=3,'Документы АСУТП'!DH30,'Документы АСУТП'!DH28))),0) -> 0 | DL14: =ТрЗ_ОП!$R$21 -> 1 | DM14: =IF(DL14=1,IF($B$1=1,'Документы АСУТП'!DI28,IF($B$1=2,'Документы АСУТП'!DI29,IF($B$1=3,'Документы АСУТП'!DI30,'Документы АСУТП'!DI28))),0) -> 0 | DN14: =ТрЗ_ОП!$R$21 -> 1 | DO14: =IF(DN14=1,IF($B$1=1,'Документы АСУТП'!DJ28,IF($B$1=2,'Документы АСУТП'!DJ29,IF($B$1=3,'Документы АСУТП'!DJ30,'Документы АСУТП'!DJ28))),0) -> #REF! | DP14: =ТрЗ_ОП!$R$21 -> 1 | DQ14: =IF(DP14=1,IF($B$1=1,'Документы АСУТП'!DK28,IF($B$1=2,'Документы АСУТП'!DK29,IF($B$1=3,'Документы АСУТП'!DK30,'Документы АСУТП'!DK28))),0) -> 0 | DR14: =ТрЗ_ОП!$R$21 -> 1 | DS14: =IF(DR14=1,IF($B$1=1,'Документы АСУТП'!DL28,IF($B$1=2,'Документы АСУТП'!DL29,IF($B$1=3,'Документы АСУТП'!DL30,'Документы АСУТП'!DL28))),0) -> 0 | DT14: =ТрЗ_ОП!$R$21 -> 1 | DU14: =IF(DT14=1,IF($B$1=1,'Документы АСУТП'!DM28,IF($B$1=2,'Документы АСУТП'!DM29,IF($B$1=3,'Документы АСУТП'!DM30,'Документы АСУТП'!DM28))),0) -> 0 | DV14: =ТрЗ_ОП!$R21 -> 1 | DW14: =IF(DV14=1,IF($B$1=1,'Документы АСУТП'!DN28,IF($B$1=2,'Документы АСУТП'!DN29,IF($B$1=3,'Документы АСУТП'!DN30,'Документы АСУТП'!DN28))),0) -> 0 | DX14: =ТрЗ_ОП!$R21 -> 1 | DY14: =IF(DX14=1,IF($B$1=1,'Документы АСУТП'!DO28,IF($B$1=2,'Документы АСУТП'!DO29,IF($B$1=3,'Документы АСУТП'!DO30,'Документы АСУТП'!DO28))),0) -> 0 | DZ14: =ТрЗ_ОП!$R21 -> 1 | EA14: =IF(DZ14=1,IF($B$1=1,'Документы АСУТП'!DP28,IF($B$1=2,'Документы АСУТП'!DP29,IF($B$1=3,'Документы АСУТП'!DP30,'Документы АСУТП'!DP28))),0) -> 0 | EB14: =ТрЗ_ОП!$R21 -> 1 | EC14: =IF(EB14=1,IF($B$1=1,'Документы АСУТП'!DQ28,IF($B$1=2,'Документы АСУТП'!DQ29,IF($B$1=3,'Документы АСУТП'!DQ30,'Документы АСУТП'!DQ28))),0) -> 0 | ED14: =ТрЗ_ОП!$R21 -> 1 | EE14: =IF(ED14=1,IF($B$1=1,'Документы АСУТП'!DR28,IF($B$1=2,'Документы АСУТП'!DR29,IF($B$1=3,'Документы АСУТП'!DR30,'Документы АСУТП'!DR28))),0) -> 0 | EF14: =ТрЗ_ОП!$R21 -> 1 | EG14: =IF(EF14=1,IF($B$1=1,'Документы АСУТП'!DS28,IF($B$1=2,'Документы АСУТП'!DS29,IF($B$1=3,'Документы АСУТП'!DS30,'Документы АСУТП'!DS28))),0) -> 0 | EH14: =ТрЗ_ОП!$R21 -> 1 | EI14: =IF(EH14=1,IF($B$1=1,'Документы АСУТП'!DT28,IF($B$1=2,'Документы АСУТП'!DT29,IF($B$1=3,'Документы АСУТП'!DT30,'Документы АСУТП'!DT28))),0) -> 0 | EJ14: =ТрЗ_ОП!$R21 -> 1 | EK14: =IF(EJ14=1,IF($B$1=1,'Документы АСУТП'!DU28,IF($B$1=2,'Документы АСУТП'!DU29,IF($B$1=3,'Документы АСУТП'!DU30,'Документы АСУТП'!DU28))),0) -> 0 | EL14: =ТрЗ_ОП!$R21 -> 1 | EM14: =IF(EL14=1,IF($B$1=1,'Документы АСУТП'!DV28,IF($B$1=2,'Документы АСУТП'!DV29,IF($B$1=3,'Документы АСУТП'!DV30,'Документы АСУТП'!DV28))),0) -> 0 | EN14: =ТрЗ_ОП!$R21 -> 1 | EO14: =IF(EN14=1,IF($B$1=1,'Документы АСУТП'!DW28,IF($B$1=2,'Документы АСУТП'!DW29,IF($B$1=3,'Документы АСУТП'!DW30,'Документы АСУТП'!DW28))),0) -> 0 | EP14: =ТрЗ_ОП!$R21 -> 1 | EQ14: =IF(EP14=1,IF($B$1=1,'Документы АСУТП'!DX28,IF($B$1=2,'Документы АСУТП'!DX29,IF($B$1=3,'Документы АСУТП'!DX30,'Документы АСУТП'!DX28))),0) -> 0 | ER14: =ТрЗ_ОП!$R21 -> 1 | ES14: =IF(ER14=1,IF($B$1=1,'Документы АСУТП'!DY28,IF($B$1=2,'Документы АСУТП'!DY29,IF($B$1=3,'Документы АСУТП'!DY30,'Документы АСУТП'!DY28))),0) -> 0 | ET14: =ТрЗ_ОП!$R21 -> 1 | EU14: =IF(ET14=1,IF($B$1=1,'Документы АСУТП'!DZ28,IF($B$1=2,'Документы АСУТП'!DZ29,IF($B$1=3,'Документы АСУТП'!DZ30,'Документы АСУТП'!DZ28))),0) -> 0 | EV14: =B14*$CO14+E14*$CQ14+H14*$CS14+K14*$CU14+N14*$CW14+Q14*$CY14+T14*$DA14+W14*$DC14+Z14*$DE14+AC14*$DG14+AF14*$DI14+AI14*$DK14+AL14*$DM14+AO14*$DO14+AR14*$DQ14+AU14*$DS14+AX14*$DU14+BA14*$DW14+BD14*$DY14+BG14*$EA14+BJ14*$EC14+BM14*$EE14+BP14*$EG14+BS14*$EI14+BV14*$EK14+BY14*$EM14+CB14*$EO14+CE14*$EQ14+CH14*$ES14+$CK14*$EU14 -> #REF! | EW14: =C14*$CO14+F14*$CQ14+I14*$CS14+L14*$CU14+O14*$CW14+R14*$CY14+U14*$DA14+X14*$DC14+AA14*$DE14+AD14*$DG14+AG14*$DI14+AJ14*$DK14+AM14*$DM14+AP14*$DO14+AS14*$DQ14+AV14*$DS14+AY14*$DU14+BB14*$DW14+BE14*$DY14+BH14*$EA14+BK14*$EC14+BN14*$EE14+BQ14*$EG14+BT14*$EI14+BW14*$EK14+BZ14*$EM14+CC14*$EO14+CF14*$EQ14+CI14*$ES14+$CL14*$EU14 -> #REF! | EX14: =D14*$CO14+G14*$CQ14+J14*$CS14+M14*$CU14+P14*$CW14+S14*$CY14+V14*$DA14+Y14*$DC14+AB14*$DE14+AE14*$DG14+AH14*$DI14+AK14*$DK14+AN14*$DM14+AQ14*$DO14+AT14*$DQ14+AW14*$DS14+AZ14*$DU14+BC14*$DW14+BF14*$DY14+BI14*$EA14+BL14*$EC14+BO14*$EE14+BR14*$EG14+BU14*$EI14+BX14*$EK14+CA14*$EM14+CD14*$EO14+CG14*$EQ14+CJ14*$ES14+$CM14*$EU14 -> #REF! | EY14: =SUM(EV14:EX14)*0.05 -> #REF! | EZ14: =SUM(EV14:EY14) -> #REF!
A15: Схема структурная | B15: 0.2 | C15: 0.5 | D15: 0.3 | E15: 0.2 | F15: 0.5 | G15: 0.3 | H15: 0.2 | I15: 0.5 | J15: 0.3 | K15: 0.2 | L15: 0.5 | M15: 0.3 | N15: 0.2 | O15: 0.5 | P15: 0.3 | Q15: 0.2 | R15: 0.5 | S15: 0.3 | T15: 0.2 | U15: 0.5 | V15: 0.3 | W15: 0.2 | X15: 0.5 | Y15: 0.3 | Z15: 0.2 | AA15: 0.5 | AB15: 0.3 | AC15: 0.2 | AD15: 0.5 | AE15: 0.3 | AF15: 0.2 | AG15: 0.5 | AH15: 0.3 | AI15: 0.2 | AJ15: 0.5 | AK15: 0.3 | AL15: 0.2 | AM15: 0.5 | AN15: 0.3 | AO15: 0.2 | AP15: 0.5 | AQ15: 0.3 | AR15: 0.2 | AS15: 0.5 | AT15: 0.3 | AU15: 0.2 | AV15: 0.5 | AW15: 0.3 | AX15: 0.2 | AY15: 0.5 | AZ15: 0.3 | BA15: 0.2 | BB15: 0.5 | BC15: 0.3 | BD15: 0.2 | BE15: 0.5 | BF15: 0.3 | BG15: 0.2 | BH15: 0.5 | BI15: 0.3 | BJ15: 0.2 | BK15: 0.5 | BL15: 0.3 | BM15: 0.2 | BN15: 0.5 | BO15: 0.3 | BP15: 0.2 | BQ15: 0.5 | BR15: 0.3 | BS15: 0.2 | BT15: 0.5 | BU15: 0.3 | BV15: 0.2 | BW15: 0.5 | BX15: 0.3 | BY15: 0.2 | BZ15: 0.5 | CA15: 0.3 | CB15: 0.2 | CC15: 0.5 | CD15: 0.3 | CE15: 0.2 | CF15: 0.5 | CG15: 0.3 | CH15: 0.2 | CI15: 0.5 | CJ15: 0.3 | CK15: 0.2 | CL15: 0.5 | CM15: 0.3 | CN15: =ТрЗ_ОП!$R$22 -> 1 | CO15: =IF(CN15=1,IF($B$1=1,'Документы АСУТП'!CW31,IF($B$1=2,'Документы АСУТП'!CW32,IF($B$1=3,'Документы АСУТП'!CW33,'Документы АСУТП'!CW31))),0) -> 0.5 | CP15: =ТрЗ_ОП!$R$22 -> 1 | CQ15: =IF(CP15=1,IF($B$1=1,'Документы АСУТП'!CX31,IF($B$1=2,'Документы АСУТП'!CX32,IF($B$1=3,'Документы АСУТП'!CX33,'Документы АСУТП'!CX31))),0) -> 1 | CR15: =ТрЗ_ОП!$R$22 -> 1 | CS15: =IF(CR15=1,IF($B$1=1,'Документы АСУТП'!CY31,IF($B$1=2,'Документы АСУТП'!CY32,IF($B$1=3,'Документы АСУТП'!CY33,'Документы АСУТП'!CY31))),0) -> 0 | CT15: =ТрЗ_ОП!$R$22 -> 1 | CU15: =IF(CT15=1,IF($B$1=1,'Документы АСУТП'!CZ31,IF($B$1=2,'Документы АСУТП'!CZ32,IF($B$1=3,'Документы АСУТП'!CZ33,'Документы АСУТП'!CZ31))),0) -> 0 | CV15: =ТрЗ_ОП!$R$22 -> 1 | CW15: =IF(CV15=1,IF($B$1=1,'Документы АСУТП'!DA31,IF($B$1=2,'Документы АСУТП'!DA32,IF($B$1=3,'Документы АСУТП'!DA33,'Документы АСУТП'!DA31))),0) -> 0 | CX15: =ТрЗ_ОП!$R$22 -> 1 | CY15: =IF(CX15=1,IF($B$1=1,'Документы АСУТП'!DB31,IF($B$1=2,'Документы АСУТП'!DB32,IF($B$1=3,'Документы АСУТП'!DB33,'Документы АСУТП'!DB31))),0) -> 0 | CZ15: =ТрЗ_ОП!$R$22 -> 1 | DA15: =IF(CZ15=1,IF($B$1=1,'Документы АСУТП'!DC31,IF($B$1=2,'Документы АСУТП'!DC32,IF($B$1=3,'Документы АСУТП'!DC33,'Документы АСУТП'!DC31))),0) -> 0 | DB15: =ТрЗ_ОП!$R$22 -> 1 | DC15: =IF(DB15=1,IF($B$1=1,'Документы АСУТП'!DD31,IF($B$1=2,'Документы АСУТП'!DD32,IF($B$1=3,'Документы АСУТП'!DD33,'Документы АСУТП'!DD31))),0) -> 0 | DD15: =ТрЗ_ОП!$R$22 -> 1 | DE15: =IF(DD15=1,IF($B$1=1,'Документы АСУТП'!DF31,IF($B$1=2,'Документы АСУТП'!DF32,IF($B$1=3,'Документы АСУТП'!DF33,'Документы АСУТП'!DF31))),0) -> 0 | DF15: =ТрЗ_ОП!$R$22 -> 1 | DG15: =IF(DF15=1,IF($B$1=1,'Документы АСУТП'!DE31,IF($B$1=2,'Документы АСУТП'!DE32,IF($B$1=3,'Документы АСУТП'!DE33,'Документы АСУТП'!DE31))),0) -> 0 | DH15: =ТрЗ_ОП!$R$22 -> 1 | DI15: =IF(DH15=1,IF($B$1=1,'Документы АСУТП'!DG31,IF($B$1=2,'Документы АСУТП'!DG32,IF($B$1=3,'Документы АСУТП'!DG33,'Документы АСУТП'!DG31))),0) -> 0 | DJ15: =ТрЗ_ОП!$R$22 -> 1 | DK15: =IF(DJ15=1,IF($B$1=1,'Документы АСУТП'!DH31,IF($B$1=2,'Документы АСУТП'!DH32,IF($B$1=3,'Документы АСУТП'!DH33,'Документы АСУТП'!DH31))),0) -> 0 | DL15: =ТрЗ_ОП!$R$22 -> 1 | DM15: =IF(DL15=1,IF($B$1=1,'Документы АСУТП'!DI31,IF($B$1=2,'Документы АСУТП'!DI32,IF($B$1=3,'Документы АСУТП'!DI33,'Документы АСУТП'!DI31))),0) -> 0 | DN15: =ТрЗ_ОП!$R$22 -> 1 | DO15: =IF(DN15=1,IF($B$1=1,'Документы АСУТП'!DJ31,IF($B$1=2,'Документы АСУТП'!DJ32,IF($B$1=3,'Документы АСУТП'!DJ33,'Документы АСУТП'!DJ31))),0) -> #REF! | DP15: =ТрЗ_ОП!$R$22 -> 1 | DQ15: =IF(DP15=1,IF($B$1=1,'Документы АСУТП'!DK31,IF($B$1=2,'Документы АСУТП'!DK32,IF($B$1=3,'Документы АСУТП'!DK33,'Документы АСУТП'!DK31))),0) -> 0 | DR15: =ТрЗ_ОП!$R$22 -> 1 | DS15: =IF(DR15=1,IF($B$1=1,'Документы АСУТП'!DL31,IF($B$1=2,'Документы АСУТП'!DL32,IF($B$1=3,'Документы АСУТП'!DL33,'Документы АСУТП'!DL31))),0) -> 0 | DT15: =ТрЗ_ОП!$R$22 -> 1 | DU15: =IF(DT15=1,IF($B$1=1,'Документы АСУТП'!DM31,IF($B$1=2,'Документы АСУТП'!DM32,IF($B$1=3,'Документы АСУТП'!DM33,'Документы АСУТП'!DM31))),0) -> 0 | DV15: =ТрЗ_ОП!$R22 -> 1 | DW15: =IF(DV15=1,IF($B$1=1,'Документы АСУТП'!DN31,IF($B$1=2,'Документы АСУТП'!DN32,IF($B$1=3,'Документы АСУТП'!DN33,'Документы АСУТП'!DN31))),0) -> 0 | DX15: =ТрЗ_ОП!$R22 -> 1 | DY15: =IF(DX15=1,IF($B$1=1,'Документы АСУТП'!DO31,IF($B$1=2,'Документы АСУТП'!DO32,IF($B$1=3,'Документы АСУТП'!DO33,'Документы АСУТП'!DO31))),0) -> 0 | DZ15: =ТрЗ_ОП!$R22 -> 1 | EA15: =IF(DZ15=1,IF($B$1=1,'Документы АСУТП'!DP31,IF($B$1=2,'Документы АСУТП'!DP32,IF($B$1=3,'Документы АСУТП'!DP33,'Документы АСУТП'!DP31))),0) -> 0 | EB15: =ТрЗ_ОП!$R22 -> 1 | EC15: =IF(EB15=1,IF($B$1=1,'Документы АСУТП'!DQ31,IF($B$1=2,'Документы АСУТП'!DQ32,IF($B$1=3,'Документы АСУТП'!DQ33,'Документы АСУТП'!DQ31))),0) -> 0 | ED15: =ТрЗ_ОП!$R22 -> 1 | EE15: =IF(ED15=1,IF($B$1=1,'Документы АСУТП'!DR31,IF($B$1=2,'Документы АСУТП'!DR32,IF($B$1=3,'Документы АСУТП'!DR33,'Документы АСУТП'!DR31))),0) -> 0 | EF15: =ТрЗ_ОП!$R22 -> 1 | EG15: =IF(EF15=1,IF($B$1=1,'Документы АСУТП'!DS31,IF($B$1=2,'Документы АСУТП'!DS32,IF($B$1=3,'Документы АСУТП'!DS33,'Документы АСУТП'!DS31))),0) -> 0 | EH15: =ТрЗ_ОП!$R22 -> 1 | EI15: =IF(EH15=1,IF($B$1=1,'Документы АСУТП'!DT31,IF($B$1=2,'Документы АСУТП'!DT32,IF($B$1=3,'Документы АСУТП'!DT33,'Документы АСУТП'!DT31))),0) -> 0 | EJ15: =ТрЗ_ОП!$R22 -> 1 | EK15: =IF(EJ15=1,IF($B$1=1,'Документы АСУТП'!DU31,IF($B$1=2,'Документы АСУТП'!DU32,IF($B$1=3,'Документы АСУТП'!DU33,'Документы АСУТП'!DU31))),0) -> 0 | EL15: =ТрЗ_ОП!$R22 -> 1 | EM15: =IF(EL15=1,IF($B$1=1,'Документы АСУТП'!DV31,IF($B$1=2,'Документы АСУТП'!DV32,IF($B$1=3,'Документы АСУТП'!DV33,'Документы АСУТП'!DV31))),0) -> 0 | EN15: =ТрЗ_ОП!$R22 -> 1 | EO15: =IF(EN15=1,IF($B$1=1,'Документы АСУТП'!DW31,IF($B$1=2,'Документы АСУТП'!DW32,IF($B$1=3,'Документы АСУТП'!DW33,'Документы АСУТП'!DW31))),0) -> 0 | EP15: =ТрЗ_ОП!$R22 -> 1 | EQ15: =IF(EP15=1,IF($B$1=1,'Документы АСУТП'!DX31,IF($B$1=2,'Документы АСУТП'!DX32,IF($B$1=3,'Документы АСУТП'!DX33,'Документы АСУТП'!DX31))),0) -> 0 | ER15: =ТрЗ_ОП!$R22 -> 1 | ES15: =IF(ER15=1,IF($B$1=1,'Документы АСУТП'!DY31,IF($B$1=2,'Документы АСУТП'!DY32,IF($B$1=3,'Документы АСУТП'!DY33,'Документы АСУТП'!DY31))),0) -> 0 | ET15: =ТрЗ_ОП!$R22 -> 1 | EU15: =IF(ET15=1,IF($B$1=1,'Документы АСУТП'!DZ31,IF($B$1=2,'Документы АСУТП'!DZ32,IF($B$1=3,'Документы АСУТП'!DZ33,'Документы АСУТП'!DZ31))),0) -> 0 | EV15: =B15*$CO15+E15*$CQ15+H15*$CS15+K15*$CU15+N15*$CW15+Q15*$CY15+T15*$DA15+W15*$DC15+Z15*$DE15+AC15*$DG15+AF15*$DI15+AI15*$DK15+AL15*$DM15+AO15*$DO15+AR15*$DQ15+AU15*$DS15+AX15*$DU15+BA15*$DW15+BD15*$DY15+BG15*$EA15+BJ15*$EC15+BM15*$EE15+BP15*$EG15+BS15*$EI15+BV15*$EK15+BY15*$EM15+CB15*$EO15+CE15*$EQ15+CH15*$ES15+$CK15*$EU15 -> #REF! | EW15: =C15*$CO15+F15*$CQ15+I15*$CS15+L15*$CU15+O15*$CW15+R15*$CY15+U15*$DA15+X15*$DC15+AA15*$DE15+AD15*$DG15+AG15*$DI15+AJ15*$DK15+AM15*$DM15+AP15*$DO15+AS15*$DQ15+AV15*$DS15+AY15*$DU15+BB15*$DW15+BE15*$DY15+BH15*$EA15+BK15*$EC15+BN15*$EE15+BQ15*$EG15+BT15*$EI15+BW15*$EK15+BZ15*$EM15+CC15*$EO15+CF15*$EQ15+CI15*$ES15+$CL15*$EU15 -> #REF! | EX15: =D15*$CO15+G15*$CQ15+J15*$CS15+M15*$CU15+P15*$CW15+S15*$CY15+V15*$DA15+Y15*$DC15+AB15*$DE15+AE15*$DG15+AH15*$DI15+AK15*$DK15+AN15*$DM15+AQ15*$DO15+AT15*$DQ15+AW15*$DS15+AZ15*$DU15+BC15*$DW15+BF15*$DY15+BI15*$EA15+BL15*$EC15+BO15*$EE15+BR15*$EG15+BU15*$EI15+BX15*$EK15+CA15*$EM15+CD15*$EO15+CG15*$EQ15+CJ15*$ES15+$CM15*$EU15 -> #REF! | EY15: =SUM(EV15:EX15)*0.05 -> #REF! | EZ15: =SUM(EV15:EY15) -> #REF!
A16: Схема функциональная | B16: 0.2 | C16: 0.5 | D16: 0.3 | E16: 0.2 | F16: 0.5 | G16: 0.3 | H16: 0.2 | I16: 0.5 | J16: 0.3 | K16: 0.2 | L16: 0.5 | M16: 0.3 | N16: 0.2 | O16: 0.5 | P16: 0.3 | Q16: 0.2 | R16: 0.5 | S16: 0.3 | T16: 0.2 | U16: 0.5 | V16: 0.3 | W16: 0.2 | X16: 0.5 | Y16: 0.3 | Z16: 0.2 | AA16: 0.5 | AB16: 0.3 | AC16: 0.2 | AD16: 0.5 | AE16: 0.3 | AF16: 0.2 | AG16: 0.5 | AH16: 0.3 | AI16: 0.2 | AJ16: 0.5 | AK16: 0.3 | AL16: 0.2 | AM16: 0.5 | AN16: 0.3 | AO16: 0.2 | AP16: 0.5 | AQ16: 0.3 | AR16: 0.2 | AS16: 0.5 | AT16: 0.3 | AU16: 0.2 | AV16: 0.5 | AW16: 0.3 | AX16: 0.2 | AY16: 0.5 | AZ16: 0.3 | BA16: 0.2 | BB16: 0.5 | BC16: 0.3 | BD16: 0.2 | BE16: 0.5 | BF16: 0.3 | BG16: 0.2 | BH16: 0.5 | BI16: 0.3 | BJ16: 0.2 | BK16: 0.5 | BL16: 0.3 | BM16: 0.2 | BN16: 0.5 | BO16: 0.3 | BP16: 0.2 | BQ16: 0.5 | BR16: 0.3 | BS16: 0.2 | BT16: 0.5 | BU16: 0.3 | BV16: 0.2 | BW16: 0.5 | BX16: 0.3 | BY16: 0.2 | BZ16: 0.5 | CA16: 0.3 | CB16: 0.2 | CC16: 0.5 | CD16: 0.3 | CE16: 0.2 | CF16: 0.5 | CG16: 0.3 | CH16: 0.2 | CI16: 0.5 | CJ16: 0.3 | CK16: 0.2 | CL16: 0.5 | CM16: 0.3 | CN16: =ТрЗ_ОП!$R$23 -> 1 | CO16: =IF(CN16=1,IF($B$1=1,'Документы АСУТП'!CW34,IF($B$1=2,'Документы АСУТП'!CW35,IF($B$1=3,'Документы АСУТП'!CW36,'Документы АСУТП'!CW34))),0) -> 1.5 | CP16: =ТрЗ_ОП!$R$23 -> 1 | CQ16: =IF(CP16=1,IF($B$1=1,'Документы АСУТП'!CX34,IF($B$1=2,'Документы АСУТП'!CX35,IF($B$1=3,'Документы АСУТП'!CX36,'Документы АСУТП'!CX34))),0) -> 2 | CR16: =ТрЗ_ОП!$R$23 -> 1 | CS16: =IF(CR16=1,IF($B$1=1,'Документы АСУТП'!CY34,IF($B$1=2,'Документы АСУТП'!CY35,IF($B$1=3,'Документы АСУТП'!CY36,'Документы АСУТП'!CY34))),0) -> 0 | CT16: =ТрЗ_ОП!$R$23 -> 1 | CU16: =IF(CT16=1,IF($B$1=1,'Документы АСУТП'!CZ34,IF($B$1=2,'Документы АСУТП'!CZ35,IF($B$1=3,'Документы АСУТП'!CZ36,'Документы АСУТП'!CZ34))),0) -> 0 | CV16: =ТрЗ_ОП!$R$23 -> 1 | CW16: =IF(CV16=1,IF($B$1=1,'Документы АСУТП'!DA34,IF($B$1=2,'Документы АСУТП'!DA35,IF($B$1=3,'Документы АСУТП'!DA36,'Документы АСУТП'!DA34))),0) -> 0 | CX16: =ТрЗ_ОП!$R$23 -> 1 | CY16: =IF(CX16=1,IF($B$1=1,'Документы АСУТП'!DB34,IF($B$1=2,'Документы АСУТП'!DB35,IF($B$1=3,'Документы АСУТП'!DB36,'Документы АСУТП'!DB34))),0) -> 0 | CZ16: =ТрЗ_ОП!$R$23 -> 1 | DA16: =IF(CZ16=1,IF($B$1=1,'Документы АСУТП'!DC34,IF($B$1=2,'Документы АСУТП'!DC35,IF($B$1=3,'Документы АСУТП'!DC36,'Документы АСУТП'!DC34))),0) -> 0 | DB16: =ТрЗ_ОП!$R$23 -> 1 | DC16: =IF(DB16=1,IF($B$1=1,'Документы АСУТП'!DD34,IF($B$1=2,'Документы АСУТП'!DD35,IF($B$1=3,'Документы АСУТП'!DD36,'Документы АСУТП'!DD34))),0) -> 0 | DD16: =ТрЗ_ОП!$R$23 -> 1 | DE16: =IF(DD16=1,IF($B$1=1,'Документы АСУТП'!DF34,IF($B$1=2,'Документы АСУТП'!DF35,IF($B$1=3,'Документы АСУТП'!DF36,'Документы АСУТП'!DF34))),0) -> 0 | DF16: =ТрЗ_ОП!$R$23 -> 1 | DG16: =IF(DF16=1,IF($B$1=1,'Документы АСУТП'!DE34,IF($B$1=2,'Документы АСУТП'!DE35,IF($B$1=3,'Документы АСУТП'!DE36,'Документы АСУТП'!DE34))),0) -> 0 | DH16: =ТрЗ_ОП!$R$23 -> 1 | DI16: =IF(DH16=1,IF($B$1=1,'Документы АСУТП'!DG34,IF($B$1=2,'Документы АСУТП'!DG35,IF($B$1=3,'Документы АСУТП'!DG36,'Документы АСУТП'!DG34))),0) -> 0 | DJ16: =ТрЗ_ОП!$R$23 -> 1 | DK16: =IF(DJ16=1,IF($B$1=1,'Документы АСУТП'!DH34,IF($B$1=2,'Документы АСУТП'!DH35,IF($B$1=3,'Документы АСУТП'!DH36,'Документы АСУТП'!DH34))),0) -> 0 | DL16: =ТрЗ_ОП!$R$23 -> 1 | DM16: =IF(DL16=1,IF($B$1=1,'Документы АСУТП'!DI34,IF($B$1=2,'Документы АСУТП'!DI35,IF($B$1=3,'Документы АСУТП'!DI36,'Документы АСУТП'!DI34))),0) -> 0 | DN16: =ТрЗ_ОП!$R$23 -> 1 | DO16: =IF(DN16=1,IF($B$1=1,'Документы АСУТП'!DJ34,IF($B$1=2,'Документы АСУТП'!DJ35,IF($B$1=3,'Документы АСУТП'!DJ36,'Документы АСУТП'!DJ34))),0) -> #REF! | DP16: =ТрЗ_ОП!$R$23 -> 1 | DQ16: =IF(DP16=1,IF($B$1=1,'Документы АСУТП'!DK34,IF($B$1=2,'Документы АСУТП'!DK35,IF($B$1=3,'Документы АСУТП'!DK36,'Документы АСУТП'!DK34))),0) -> 0 | DR16: =ТрЗ_ОП!$R$23 -> 1 | DS16: =IF(DR16=1,IF($B$1=1,'Документы АСУТП'!DL34,IF($B$1=2,'Документы АСУТП'!DL35,IF($B$1=3,'Документы АСУТП'!DL36,'Документы АСУТП'!DL34))),0) -> 0 | DT16: =ТрЗ_ОП!$R$23 -> 1 | DU16: =IF(DT16=1,IF($B$1=1,'Документы АСУТП'!DM34,IF($B$1=2,'Документы АСУТП'!DM35,IF($B$1=3,'Документы АСУТП'!DM36,'Документы АСУТП'!DM34))),0) -> 0 | DV16: =ТрЗ_ОП!$R23 -> 1 | DW16: =IF(DV16=1,IF($B$1=1,'Документы АСУТП'!DN34,IF($B$1=2,'Документы АСУТП'!DN35,IF($B$1=3,'Документы АСУТП'!DN36,'Документы АСУТП'!DN34))),0) -> 0 | DX16: =ТрЗ_ОП!$R23 -> 1 | DY16: =IF(DX16=1,IF($B$1=1,'Документы АСУТП'!DO34,IF($B$1=2,'Документы АСУТП'!DO35,IF($B$1=3,'Документы АСУТП'!DO36,'Документы АСУТП'!DO34))),0) -> 0 | DZ16: =ТрЗ_ОП!$R23 -> 1 | EA16: =IF(DZ16=1,IF($B$1=1,'Документы АСУТП'!DP34,IF($B$1=2,'Документы АСУТП'!DP35,IF($B$1=3,'Документы АСУТП'!DP36,'Документы АСУТП'!DP34))),0) -> 0 | EB16: =ТрЗ_ОП!$R23 -> 1 | EC16: =IF(EB16=1,IF($B$1=1,'Документы АСУТП'!DQ34,IF($B$1=2,'Документы АСУТП'!DQ35,IF($B$1=3,'Документы АСУТП'!DQ36,'Документы АСУТП'!DQ34))),0) -> 0 | ED16: =ТрЗ_ОП!$R23 -> 1 | EE16: =IF(ED16=1,IF($B$1=1,'Документы АСУТП'!DR34,IF($B$1=2,'Документы АСУТП'!DR35,IF($B$1=3,'Документы АСУТП'!DR36,'Документы АСУТП'!DR34))),0) -> 0 | EF16: =ТрЗ_ОП!$R23 -> 1 | EG16: =IF(EF16=1,IF($B$1=1,'Документы АСУТП'!DS34,IF($B$1=2,'Документы АСУТП'!DS35,IF($B$1=3,'Документы АСУТП'!DS36,'Документы АСУТП'!DS34))),0) -> 0 | EH16: =ТрЗ_ОП!$R23 -> 1 | EI16: =IF(EH16=1,IF($B$1=1,'Документы АСУТП'!DT34,IF($B$1=2,'Документы АСУТП'!DT35,IF($B$1=3,'Документы АСУТП'!DT36,'Документы АСУТП'!DT34))),0) -> 0 | EJ16: =ТрЗ_ОП!$R23 -> 1 | EK16: =IF(EJ16=1,IF($B$1=1,'Документы АСУТП'!DU34,IF($B$1=2,'Документы АСУТП'!DU35,IF($B$1=3,'Документы АСУТП'!DU36,'Документы АСУТП'!DU34))),0) -> 0 | EL16: =ТрЗ_ОП!$R23 -> 1 | EM16: =IF(EL16=1,IF($B$1=1,'Документы АСУТП'!DV34,IF($B$1=2,'Документы АСУТП'!DV35,IF($B$1=3,'Документы АСУТП'!DV36,'Документы АСУТП'!DV34))),0) -> 0 | EN16: =ТрЗ_ОП!$R23 -> 1 | EO16: =IF(EN16=1,IF($B$1=1,'Документы АСУТП'!DW34,IF($B$1=2,'Документы АСУТП'!DW35,IF($B$1=3,'Документы АСУТП'!DW36,'Документы АСУТП'!DW34))),0) -> 0 | EP16: =ТрЗ_ОП!$R23 -> 1 | EQ16: =IF(EP16=1,IF($B$1=1,'Документы АСУТП'!DX34,IF($B$1=2,'Документы АСУТП'!DX35,IF($B$1=3,'Документы АСУТП'!DX36,'Документы АСУТП'!DX34))),0) -> 0 | ER16: =ТрЗ_ОП!$R23 -> 1 | ES16: =IF(ER16=1,IF($B$1=1,'Документы АСУТП'!DY34,IF($B$1=2,'Документы АСУТП'!DY35,IF($B$1=3,'Документы АСУТП'!DY36,'Документы АСУТП'!DY34))),0) -> 0 | ET16: =ТрЗ_ОП!$R23 -> 1 | EU16: =IF(ET16=1,IF($B$1=1,'Документы АСУТП'!DZ34,IF($B$1=2,'Документы АСУТП'!DZ35,IF($B$1=3,'Документы АСУТП'!DZ36,'Документы АСУТП'!DZ34))),0) -> 0 | EV16: =B16*$CO16+E16*$CQ16+H16*$CS16+K16*$CU16+N16*$CW16+Q16*$CY16+T16*$DA16+W16*$DC16+Z16*$DE16+AC16*$DG16+AF16*$DI16+AI16*$DK16+AL16*$DM16+AO16*$DO16+AR16*$DQ16+AU16*$DS16+AX16*$DU16+BA16*$DW16+BD16*$DY16+BG16*$EA16+BJ16*$EC16+BM16*$EE16+BP16*$EG16+BS16*$EI16+BV16*$EK16+BY16*$EM16+CB16*$EO16+CE16*$EQ16+CH16*$ES16+$CK16*$EU16 -> #REF! | EW16: =C16*$CO16+F16*$CQ16+I16*$CS16+L16*$CU16+O16*$CW16+R16*$CY16+U16*$DA16+X16*$DC16+AA16*$DE16+AD16*$DG16+AG16*$DI16+AJ16*$DK16+AM16*$DM16+AP16*$DO16+AS16*$DQ16+AV16*$DS16+AY16*$DU16+BB16*$DW16+BE16*$DY16+BH16*$EA16+BK16*$EC16+BN16*$EE16+BQ16*$EG16+BT16*$EI16+BW16*$EK16+BZ16*$EM16+CC16*$EO16+CF16*$EQ16+CI16*$ES16+$CL16*$EU16 -> #REF! | EX16: =D16*$CO16+G16*$CQ16+J16*$CS16+M16*$CU16+P16*$CW16+S16*$CY16+V16*$DA16+Y16*$DC16+AB16*$DE16+AE16*$DG16+AH16*$DI16+AK16*$DK16+AN16*$DM16+AQ16*$DO16+AT16*$DQ16+AW16*$DS16+AZ16*$DU16+BC16*$DW16+BF16*$DY16+BI16*$EA16+BL16*$EC16+BO16*$EE16+BR16*$EG16+BU16*$EI16+BX16*$EK16+CA16*$EM16+CD16*$EO16+CG16*$EQ16+CJ16*$ES16+$CM16*$EU16 -> #REF! | EY16: =SUM(EV16:EX16)*0.05 -> #REF! | EZ16: =SUM(EV16:EY16) -> #REF!
A17: ТРП
A18: Пояснительная записка к технорабочему проекту | B18: 0.7 | C18: 0.25 | D18: 0.05 | E18: 0.5 | F18: 0.3 | G18: 0.2 | H18: 0.7 | I18: 0.25 | J18: 0.05 | K18: 0.6 | L18: 0.3 | M18: 0.1 | N18: 0.5 | O18: 0.3 | P18: 0.2 | Q18: 0.6 | R18: 0.3 | S18: 0.1 | T18: 0.7 | U18: 0.25 | V18: 0.05 | W18: 0.6 | X18: 0.3 | Y18: 0.1 | Z18: 0.6 | AA18: 0.3 | AB18: 0.1 | AC18: 0.4 | AD18: 0.3 | AE18: 0.3 | AF18: 0.6 | AG18: 0.3 | AH18: 0.1 | AI18: 0.5 | AJ18: 0.3 | AK18: 0.2 | AL18: 0.4 | AM18: 0.3 | AN18: 0.3 | AO18: 0.4 | AP18: 0.3 | AQ18: 0.3 | AR18: 0.5 | AS18: 0.3 | AT18: 0.2 | AU18: 0.5 | AV18: 0.3 | AW18: 0.2 | AX18: 0.4 | AY18: 0.3 | AZ18: 0.3 | BA18: 0.5 | BB18: 0.3 | BC18: 0.2 | BD18: 0.5 | BE18: 0.3 | BF18: 0.2 | BG18: 0.5 | BH18: 0.3 | BI18: 0.2 | BJ18: 0.4 | BK18: 0.3 | BL18: 0.3 | BM18: 0.4 | BN18: 0.3 | BO18: 0.3 | BP18: 0.4 | BQ18: 0.3 | BR18: 0.3 | BS18: 0.5 | BT18: 0.3 | BU18: 0.2 | BV18: 0.5 | BW18: 0.3 | BX18: 0.2 | BY18: 0.4 | BZ18: 0.3 | CA18: 0.3 | CB18: 0.5 | CC18: 0.3 | CD18: 0.2 | CE18: 0.5 | CF18: 0.3 | CG18: 0.2 | CH18: 0.4 | CI18: 0.3 | CJ18: 0.3 | CK18: 0.4 | CL18: 0.3 | CM18: 0.3 | CN18: =ТрЗ_ОП!$R$25 -> - | CO18: =IF(CN18=1,IF($B$1=1,'Документы АСУТП'!CW38,IF($B$1=2,'Документы АСУТП'!CW39,IF($B$1=3,'Документы АСУТП'!CW40,'Документы АСУТП'!CW38))),0) -> 0 | CP18: =ТрЗ_ОП!$R$25 -> - | CQ18: =IF(CP18=1,IF($B$1=1,'Документы АСУТП'!CX38,IF($B$1=2,'Документы АСУТП'!CX39,IF($B$1=3,'Документы АСУТП'!CX40,'Документы АСУТП'!CX38))),0) -> 0 | CR18: =ТрЗ_ОП!$R$25 -> - | CS18: =IF(CR18=1,IF($B$1=1,'Документы АСУТП'!CY38,IF($B$1=2,'Документы АСУТП'!CY39,IF($B$1=3,'Документы АСУТП'!CY40,'Документы АСУТП'!CY38))),0) -> 0 | CT18: =ТрЗ_ОП!$R$25 -> - | CU18: =IF(CT18=1,IF($B$1=1,'Документы АСУТП'!CZ38,IF($B$1=2,'Документы АСУТП'!CZ39,IF($B$1=3,'Документы АСУТП'!CZ40,'Документы АСУТП'!CZ38))),0) -> 0 | CV18: =ТрЗ_ОП!$R$25 -> - | CW18: =IF(CV18=1,IF($B$1=1,'Документы АСУТП'!DA38,IF($B$1=2,'Документы АСУТП'!DA39,IF($B$1=3,'Документы АСУТП'!DA40,'Документы АСУТП'!DA38))),0) -> 0 | CX18: =ТрЗ_ОП!$R$25 -> - | CY18: =IF(CX18=1,IF($B$1=1,'Документы АСУТП'!DB38,IF($B$1=2,'Документы АСУТП'!DB39,IF($B$1=3,'Документы АСУТП'!DB40,'Документы АСУТП'!DB38))),0) -> 0 | CZ18: =ТрЗ_ОП!$R$25 -> - | DA18: =IF(CZ18=1,IF($B$1=1,'Документы АСУТП'!DC38,IF($B$1=2,'Документы АСУТП'!DC39,IF($B$1=3,'Документы АСУТП'!DC40,'Документы АСУТП'!DC38))),0) -> 0 | DB18: =ТрЗ_ОП!$R$25 -> - | DC18: =IF(DB18=1,IF($B$1=1,'Документы АСУТП'!DD38,IF($B$1=2,'Документы АСУТП'!DD39,IF($B$1=3,'Документы АСУТП'!DD40,'Документы АСУТП'!DD38))),0) -> 0 | DD18: =ТрЗ_ОП!$R$25 -> - | DE18: =IF(DD18=1,IF($B$1=1,'Документы АСУТП'!DF38,IF($B$1=2,'Документы АСУТП'!DF39,IF($B$1=3,'Документы АСУТП'!DF40,'Документы АСУТП'!DF38))),0) -> 0 | DF18: =ТрЗ_ОП!$R$25 -> - | DG18: =IF(DF18=1,IF($B$1=1,'Документы АСУТП'!DE38,IF($B$1=2,'Документы АСУТП'!DE39,IF($B$1=3,'Документы АСУТП'!DE40,'Документы АСУТП'!DE38))),0) -> 0 | DH18: =ТрЗ_ОП!$R$25 -> - | DI18: =IF(DH18=1,IF($B$1=1,'Документы АСУТП'!DG38,IF($B$1=2,'Документы АСУТП'!DG39,IF($B$1=3,'Документы АСУТП'!DG40,'Документы АСУТП'!DG38))),0) -> 0 | DJ18: =ТрЗ_ОП!$R$25 -> - | DK18: =IF(DJ18=1,IF($B$1=1,'Документы АСУТП'!DH38,IF($B$1=2,'Документы АСУТП'!DH39,IF($B$1=3,'Документы АСУТП'!DH40,'Документы АСУТП'!DH38))),0) -> 0 | DL18: =ТрЗ_ОП!$R$25 -> - | DM18: =IF(DL18=1,IF($B$1=1,'Документы АСУТП'!DI38,IF($B$1=2,'Документы АСУТП'!DI39,IF($B$1=3,'Документы АСУТП'!DI40,'Документы АСУТП'!DI38))),0) -> 0 | DN18: =ТрЗ_ОП!$R$25 -> - | DO18: =IF(DN18=1,IF($B$1=1,'Документы АСУТП'!DJ38,IF($B$1=2,'Документы АСУТП'!DJ39,IF($B$1=3,'Документы АСУТП'!DJ40,'Документы АСУТП'!DJ38))),0) -> 0 | DP18: =ТрЗ_ОП!$R$25 -> - | DQ18: =IF(DP18=1,IF($B$1=1,'Документы АСУТП'!DK38,IF($B$1=2,'Документы АСУТП'!DK39,IF($B$1=3,'Документы АСУТП'!DK40,'Документы АСУТП'!DK38))),0) -> 0 | DR18: =ТрЗ_ОП!$R$25 -> - | DS18: =IF(DR18=1,IF($B$1=1,'Документы АСУТП'!DL38,IF($B$1=2,'Документы АСУТП'!DL39,IF($B$1=3,'Документы АСУТП'!DL40,'Документы АСУТП'!DL38))),0) -> 0 | DT18: =ТрЗ_ОП!$R$25 -> - | DU18: =IF(DT18=1,IF($B$1=1,'Документы АСУТП'!DM38,IF($B$1=2,'Документы АСУТП'!DM39,IF($B$1=3,'Документы АСУТП'!DM40,'Документы АСУТП'!DM38))),0) -> 0 | DV18: =ТрЗ_ОП!$R$25 -> - | DW18: =IF(DV18=1,IF($B$1=1,'Документы АСУТП'!DN38,IF($B$1=2,'Документы АСУТП'!DN39,IF($B$1=3,'Документы АСУТП'!DN40,'Документы АСУТП'!DN38))),0) -> 0 | DX18: =ТрЗ_ОП!$R$25 -> - | DY18: =IF(DX18=1,IF($B$1=1,'Документы АСУТП'!DO38,IF($B$1=2,'Документы АСУТП'!DO39,IF($B$1=3,'Документы АСУТП'!DO40,'Документы АСУТП'!DO38))),0) -> 0 | DZ18: =ТрЗ_ОП!$R$25 -> - | EA18: =IF(DZ18=1,IF($B$1=1,'Документы АСУТП'!DP38,IF($B$1=2,'Документы АСУТП'!DP39,IF($B$1=3,'Документы АСУТП'!DP40,'Документы АСУТП'!DP38))),0) -> 0 | EB18: =ТрЗ_ОП!$R$25 -> - | EC18: =IF(EB18=1,IF($B$1=1,'Документы АСУТП'!DQ38,IF($B$1=2,'Документы АСУТП'!DQ39,IF($B$1=3,'Документы АСУТП'!DQ40,'Документы АСУТП'!DQ38))),0) -> 0 | ED18: =ТрЗ_ОП!$R$25 -> - | EE18: =IF(ED18=1,IF($B$1=1,'Документы АСУТП'!DR38,IF($B$1=2,'Документы АСУТП'!DR39,IF($B$1=3,'Документы АСУТП'!DR40,'Документы АСУТП'!DR38))),0) -> 0 | EF18: =ТрЗ_ОП!$R$25 -> - | EG18: =IF(EF18=1,IF($B$1=1,'Документы АСУТП'!DS38,IF($B$1=2,'Документы АСУТП'!DS39,IF($B$1=3,'Документы АСУТП'!DS40,'Документы АСУТП'!DS38))),0) -> 0 | EH18: =ТрЗ_ОП!$R$25 -> - | EI18: =IF(EH18=1,IF($B$1=1,'Документы АСУТП'!DT38,IF($B$1=2,'Документы АСУТП'!DT39,IF($B$1=3,'Документы АСУТП'!DT40,'Документы АСУТП'!DT38))),0) -> 0 | EJ18: =ТрЗ_ОП!$R$25 -> - | EK18: =IF(EJ18=1,IF($B$1=1,'Документы АСУТП'!DU38,IF($B$1=2,'Документы АСУТП'!DU39,IF($B$1=3,'Документы АСУТП'!DU40,'Документы АСУТП'!DU38))),0) -> 0 | EL18: =ТрЗ_ОП!$R$25 -> - | EM18: =IF(EL18=1,IF($B$1=1,'Документы АСУТП'!DV38,IF($B$1=2,'Документы АСУТП'!DV39,IF($B$1=3,'Документы АСУТП'!DV40,'Документы АСУТП'!DV38))),0) -> 0 | EN18: =ТрЗ_ОП!$R$25 -> - | EO18: =IF(EN18=1,IF($B$1=1,'Документы АСУТП'!DW38,IF($B$1=2,'Документы АСУТП'!DW39,IF($B$1=3,'Документы АСУТП'!DW40,'Документы АСУТП'!DW38))),0) -> 0 | EP18: =ТрЗ_ОП!$R$25 -> - | EQ18: =IF(EP18=1,IF($B$1=1,'Документы АСУТП'!DX38,IF($B$1=2,'Документы АСУТП'!DX39,IF($B$1=3,'Документы АСУТП'!DX40,'Документы АСУТП'!DX38))),0) -> 0 | ER18: =ТрЗ_ОП!$R$25 -> - | ES18: =IF(ER18=1,IF($B$1=1,'Документы АСУТП'!DY38,IF($B$1=2,'Документы АСУТП'!DY39,IF($B$1=3,'Документы АСУТП'!DY40,'Документы АСУТП'!DY38))),0) -> 0 | ET18: =ТрЗ_ОП!$R$25 -> - | EU18: =IF(ET18=1,IF($B$1=1,'Документы АСУТП'!DZ38,IF($B$1=2,'Документы АСУТП'!DZ39,IF($B$1=3,'Документы АСУТП'!DZ40,'Документы АСУТП'!DZ38))),0) -> 0 | EV18: =B18*$CO18+E18*$CQ18+H18*$CS18+K18*$CU18+N18*$CW18+Q18*$CY18+T18*$DA18+W18*$DC18+Z18*$DE18+AC18*$DG18+AF18*$DI18+AI18*$DK18+AL18*$DM18+AO18*$DO18+AR18*$DQ18+AU18*$DS18+AX18*$DU18+BA18*$DW18+BD18*$DY18+BG18*$EA18+BJ18*$EC18+BM18*$EE18+BP18*$EG18+BS18*$EI18+BV18*$EK18+BY18*$EM18+CB18*$EO18+CE18*$EQ18+CH18*$ES18+$CK18*$EU18 -> 0 | EW18: =C18*$CO18+F18*$CQ18+I18*$CS18+L18*$CU18+O18*$CW18+R18*$CY18+U18*$DA18+X18*$DC18+AA18*$DE18+AD18*$DG18+AG18*$DI18+AJ18*$DK18+AM18*$DM18+AP18*$DO18+AS18*$DQ18+AV18*$DS18+AY18*$DU18+BB18*$DW18+BE18*$DY18+BH18*$EA18+BK18*$EC18+BN18*$EE18+BQ18*$EG18+BT18*$EI18+BW18*$EK18+BZ18*$EM18+CC18*$EO18+CF18*$EQ18+CI18*$ES18+$CL18*$EU18 -> 0 | EX18: =D18*$CO18+G18*$CQ18+J18*$CS18+M18*$CU18+P18*$CW18+S18*$CY18+V18*$DA18+Y18*$DC18+AB18*$DE18+AE18*$DG18+AH18*$DI18+AK18*$DK18+AN18*$DM18+AQ18*$DO18+AT18*$DQ18+AW18*$DS18+AZ18*$DU18+BC18*$DW18+BF18*$DY18+BI18*$EA18+BL18*$EC18+BO18*$EE18+BR18*$EG18+BU18*$EI18+BX18*$EK18+CA18*$EM18+CD18*$EO18+CG18*$EQ18+CJ18*$ES18+$CM18*$EU18 -> 0 | EY18: =SUM(EV18:EX18)*0.05 -> 0 | EZ18: =SUM(EV18:EY18) -> 0
A19: РД
A20: Спецификация оборудования | B20: 0.2 | C20: 0.5 | D20: 0.3 | E20: 0.2 | F20: 0.5 | G20: 0.3 | H20: 0.2 | I20: 0.5 | J20: 0.3 | K20: 0.2 | L20: 0.5 | M20: 0.3 | N20: 0.2 | O20: 0.5 | P20: 0.3 | Q20: 0.2 | R20: 0.5 | S20: 0.3 | T20: 0.2 | U20: 0.5 | V20: 0.3 | W20: 0.2 | X20: 0.5 | Y20: 0.3 | Z20: 0.2 | AA20: 0.5 | AB20: 0.3 | AC20: 0.2 | AD20: 0.5 | AE20: 0.3 | AF20: 0.2 | AG20: 0.5 | AH20: 0.3 | AI20: 0.2 | AJ20: 0.5 | AK20: 0.3 | AL20: 0.2 | AM20: 0.5 | AN20: 0.3 | AO20: 0.2 | AP20: 0.5 | AQ20: 0.3 | AR20: 0.2 | AS20: 0.5 | AT20: 0.3 | AU20: 0.2 | AV20: 0.5 | AW20: 0.3 | AX20: 0.2 | AY20: 0.5 | AZ20: 0.3 | BA20: 0.2 | BB20: 0.5 | BC20: 0.3 | BD20: 0.2 | BE20: 0.5 | BF20: 0.3 | BG20: 0.2 | BH20: 0.5 | BI20: 0.3 | BJ20: 0.2 | BK20: 0.5 | BL20: 0.3 | BM20: 0.2 | BN20: 0.5 | BO20: 0.3 | BP20: 0.2 | BQ20: 0.5 | BR20: 0.3 | BS20: 0.2 | BT20: 0.5 | BU20: 0.3 | BV20: 0.2 | BW20: 0.5 | BX20: 0.3 | BY20: 0.2 | BZ20: 0.5 | CA20: 0.3 | CB20: 0.2 | CC20: 0.5 | CD20: 0.3 | CE20: 0.2 | CF20: 0.5 | CG20: 0.3 | CH20: 0.2 | CI20: 0.5 | CJ20: 0.3 | CK20: 0.2 | CL20: 0.5 | CM20: 0.3 | CN20: =ТрЗ_ОП!$R$27 -> 1 | CO20: =IF(CN20=1,IF($B$1=1,'Документы АСУТП'!CW42,IF($B$1=2,'Документы АСУТП'!CW43,IF($B$1=3,'Документы АСУТП'!CW44,'Документы АСУТП'!CW42))),0) -> 0.5 | CP20: =ТрЗ_ОП!$R$27 -> 1 | CQ20: =IF(CP20=1,IF($B$1=1,'Документы АСУТП'!CX42,IF($B$1=2,'Документы АСУТП'!CX43,IF($B$1=3,'Документы АСУТП'!CX44,'Документы АСУТП'!CX42))),0) -> 1 | CR20: =ТрЗ_ОП!$R$27 -> 1 | CS20: =IF(CR20=1,IF($B$1=1,'Документы АСУТП'!CY42,IF($B$1=2,'Документы АСУТП'!CY43,IF($B$1=3,'Документы АСУТП'!CY44,'Документы АСУТП'!CY42))),0) -> 0 | CT20: =ТрЗ_ОП!$R$27 -> 1 | CU20: =IF(CT20=1,IF($B$1=1,'Документы АСУТП'!CZ42,IF($B$1=2,'Документы АСУТП'!CZ43,IF($B$1=3,'Документы АСУТП'!CZ44,'Документы АСУТП'!CZ42))),0) -> 0 | CV20: =ТрЗ_ОП!$R$27 -> 1 | CW20: =IF(CV20=1,IF($B$1=1,'Документы АСУТП'!DA42,IF($B$1=2,'Документы АСУТП'!DA43,IF($B$1=3,'Документы АСУТП'!DA44,'Документы АСУТП'!DA42))),0) -> 0 | CX20: =ТрЗ_ОП!$R$27 -> 1 | CY20: =IF(CX20=1,IF($B$1=1,'Документы АСУТП'!DB42,IF($B$1=2,'Документы АСУТП'!DB43,IF($B$1=3,'Документы АСУТП'!DB44,'Документы АСУТП'!DB42))),0) -> 0 | CZ20: =ТрЗ_ОП!$R$27 -> 1 | DA20: =IF(CZ20=1,IF($B$1=1,'Документы АСУТП'!DC42,IF($B$1=2,'Документы АСУТП'!DC43,IF($B$1=3,'Документы АСУТП'!DC44,'Документы АСУТП'!DC42))),0) -> 0 | DB20: =ТрЗ_ОП!$R$27 -> 1 | DC20: =IF(DB20=1,IF($B$1=1,'Документы АСУТП'!DD42,IF($B$1=2,'Документы АСУТП'!DD43,IF($B$1=3,'Документы АСУТП'!DD44,'Документы АСУТП'!DD42))),0) -> 0 | DD20: =ТрЗ_ОП!$R$27 -> 1 | DE20: =IF(DD20=1,IF($B$1=1,'Документы АСУТП'!DF42,IF($B$1=2,'Документы АСУТП'!DF43,IF($B$1=3,'Документы АСУТП'!DF44,'Документы АСУТП'!DF42))),0) -> 0 | DF20: =ТрЗ_ОП!$R$27 -> 1 | DG20: =IF(DF20=1,IF($B$1=1,'Документы АСУТП'!DE42,IF($B$1=2,'Документы АСУТП'!DE43,IF($B$1=3,'Документы АСУТП'!DE44,'Документы АСУТП'!DE42))),0) -> 0 | DH20: =ТрЗ_ОП!$R$27 -> 1 | DI20: =IF(DH20=1,IF($B$1=1,'Документы АСУТП'!DG42,IF($B$1=2,'Документы АСУТП'!DG43,IF($B$1=3,'Документы АСУТП'!DG44,'Документы АСУТП'!DG42))),0) -> 0 | DJ20: =ТрЗ_ОП!$R$27 -> 1 | DK20: =IF(DJ20=1,IF($B$1=1,'Документы АСУТП'!DH42,IF($B$1=2,'Документы АСУТП'!DH43,IF($B$1=3,'Документы АСУТП'!DH44,'Документы АСУТП'!DH42))),0) -> 0 | DL20: =ТрЗ_ОП!$R$27 -> 1 | DM20: =IF(DL20=1,IF($B$1=1,'Документы АСУТП'!DI42,IF($B$1=2,'Документы АСУТП'!DI43,IF($B$1=3,'Документы АСУТП'!DI44,'Документы АСУТП'!DI42))),0) -> 0 | DN20: =ТрЗ_ОП!$R$27 -> 1 | DO20: =IF(DN20=1,IF($B$1=1,'Документы АСУТП'!DJ42,IF($B$1=2,'Документы АСУТП'!DJ43,IF($B$1=3,'Документы АСУТП'!DJ44,'Документы АСУТП'!DJ42))),0) -> #REF! | DP20: =ТрЗ_ОП!$R$27 -> 1 | DQ20: =IF(DP20=1,IF($B$1=1,'Документы АСУТП'!DK42,IF($B$1=2,'Документы АСУТП'!DK43,IF($B$1=3,'Документы АСУТП'!DK44,'Документы АСУТП'!DK42))),0) -> 0 | DR20: =ТрЗ_ОП!$R$27 -> 1 | DS20: =IF(DR20=1,IF($B$1=1,'Документы АСУТП'!DL42,IF($B$1=2,'Документы АСУТП'!DL43,IF($B$1=3,'Документы АСУТП'!DL44,'Документы АСУТП'!DL42))),0) -> 0 | DT20: =ТрЗ_ОП!$R$27 -> 1 | DU20: =IF(DT20=1,IF($B$1=1,'Документы АСУТП'!DM42,IF($B$1=2,'Документы АСУТП'!DM43,IF($B$1=3,'Документы АСУТП'!DM44,'Документы АСУТП'!DM42))),0) -> 0 | DV20: =ТрЗ_ОП!$R$27 -> 1 | DW20: =IF(DV20=1,IF($B$1=1,'Документы АСУТП'!DN42,IF($B$1=2,'Документы АСУТП'!DN43,IF($B$1=3,'Документы АСУТП'!DN44,'Документы АСУТП'!DN42))),0) -> 0 | DX20: =ТрЗ_ОП!$R$27 -> 1 | DY20: =IF(DX20=1,IF($B$1=1,'Документы АСУТП'!DO42,IF($B$1=2,'Документы АСУТП'!DO43,IF($B$1=3,'Документы АСУТП'!DO44,'Документы АСУТП'!DO42))),0) -> 0 | DZ20: =ТрЗ_ОП!$R$27 -> 1 | EA20: =IF(DZ20=1,IF($B$1=1,'Документы АСУТП'!DP42,IF($B$1=2,'Документы АСУТП'!DP43,IF($B$1=3,'Документы АСУТП'!DP44,'Документы АСУТП'!DP42))),0) -> 0 | EB20: =ТрЗ_ОП!$R$27 -> 1 | EC20: =IF(EB20=1,IF($B$1=1,'Документы АСУТП'!DQ42,IF($B$1=2,'Документы АСУТП'!DQ43,IF($B$1=3,'Документы АСУТП'!DQ44,'Документы АСУТП'!DQ42))),0) -> 0 | ED20: =ТрЗ_ОП!$R$27 -> 1 | EE20: =IF(ED20=1,IF($B$1=1,'Документы АСУТП'!DR42,IF($B$1=2,'Документы АСУТП'!DR43,IF($B$1=3,'Документы АСУТП'!DR44,'Документы АСУТП'!DR42))),0) -> 0 | EF20: =ТрЗ_ОП!$R$27 -> 1 | EG20: =IF(EF20=1,IF($B$1=1,'Документы АСУТП'!DS42,IF($B$1=2,'Документы АСУТП'!DS43,IF($B$1=3,'Документы АСУТП'!DS44,'Документы АСУТП'!DS42))),0) -> 0 | EH20: =ТрЗ_ОП!$R$27 -> 1 | EI20: =IF(EH20=1,IF($B$1=1,'Документы АСУТП'!DT42,IF($B$1=2,'Документы АСУТП'!DT43,IF($B$1=3,'Документы АСУТП'!DT44,'Документы АСУТП'!DT42))),0) -> 0 | EJ20: =ТрЗ_ОП!$R$27 -> 1 | EK20: =IF(EJ20=1,IF($B$1=1,'Документы АСУТП'!DU42,IF($B$1=2,'Документы АСУТП'!DU43,IF($B$1=3,'Документы АСУТП'!DU44,'Документы АСУТП'!DU42))),0) -> 0 | EL20: =ТрЗ_ОП!$R$27 -> 1 | EM20: =IF(EL20=1,IF($B$1=1,'Документы АСУТП'!DV42,IF($B$1=2,'Документы АСУТП'!DV43,IF($B$1=3,'Документы АСУТП'!DV44,'Документы АСУТП'!DV42))),0) -> 0 | EN20: =ТрЗ_ОП!$R$27 -> 1 | EO20: =IF(EN20=1,IF($B$1=1,'Документы АСУТП'!DW42,IF($B$1=2,'Документы АСУТП'!DW43,IF($B$1=3,'Документы АСУТП'!DW44,'Документы АСУТП'!DW42))),0) -> 0 | EP20: =ТрЗ_ОП!$R$27 -> 1 | EQ20: =IF(EP20=1,IF($B$1=1,'Документы АСУТП'!DX42,IF($B$1=2,'Документы АСУТП'!DX43,IF($B$1=3,'Документы АСУТП'!DX44,'Документы АСУТП'!DX42))),0) -> 0 | ER20: =ТрЗ_ОП!$R$27 -> 1 | ES20: =IF(ER20=1,IF($B$1=1,'Документы АСУТП'!DY42,IF($B$1=2,'Документы АСУТП'!DY43,IF($B$1=3,'Документы АСУТП'!DY44,'Документы АСУТП'!DY42))),0) -> 0 | ET20: =ТрЗ_ОП!$R$27 -> 1 | EU20: =IF(ET20=1,IF($B$1=1,'Документы АСУТП'!DZ42,IF($B$1=2,'Документы АСУТП'!DZ43,IF($B$1=3,'Документы АСУТП'!DZ44,'Документы АСУТП'!DZ42))),0) -> 0 | EV20: =B20*$CO20+E20*$CQ20+H20*$CS20+K20*$CU20+N20*$CW20+Q20*$CY20+T20*$DA20+W20*$DC20+Z20*$DE20+AC20*$DG20+AF20*$DI20+AI20*$DK20+AL20*$DM20+AO20*$DO20+AR20*$DQ20+AU20*$DS20+AX20*$DU20+BA20*$DW20+BD20*$DY20+BG20*$EA20+BJ20*$EC20+BM20*$EE20+BP20*$EG20+BS20*$EI20+BV20*$EK20+BY20*$EM20+CB20*$EO20+CE20*$EQ20+CH20*$ES20+$CK20*$EU20 -> #REF! | EW20: =C20*$CO20+F20*$CQ20+I20*$CS20+L20*$CU20+O20*$CW20+R20*$CY20+U20*$DA20+X20*$DC20+AA20*$DE20+AD20*$DG20+AG20*$DI20+AJ20*$DK20+AM20*$DM20+AP20*$DO20+AS20*$DQ20+AV20*$DS20+AY20*$DU20+BB20*$DW20+BE20*$DY20+BH20*$EA20+BK20*$EC20+BN20*$EE20+BQ20*$EG20+BT20*$EI20+BW20*$EK20+BZ20*$EM20+CC20*$EO20+CF20*$EQ20+CI20*$ES20+$CL20*$EU20 -> #REF! | EX20: =D20*$CO20+G20*$CQ20+J20*$CS20+M20*$CU20+P20*$CW20+S20*$CY20+V20*$DA20+Y20*$DC20+AB20*$DE20+AE20*$DG20+AH20*$DI20+AK20*$DK20+AN20*$DM20+AQ20*$DO20+AT20*$DQ20+AW20*$DS20+AZ20*$DU20+BC20*$DW20+BF20*$DY20+BI20*$EA20+BL20*$EC20+BO20*$EE20+BR20*$EG20+BU20*$EI20+BX20*$EK20+CA20*$EM20+CD20*$EO20+CG20*$EQ20+CJ20*$ES20+$CM20*$EU20 -> #REF! | EY20: =SUM(EV20:EX20)*0.05 -> #REF! | EZ20: =SUM(EV20:EY20) -> #REF!
A21: Инструкция по установке и настройке | B21: 0.7 | C21: 0.25 | D21: 0.05 | E21: 0.5 | F21: 0.3 | G21: 0.2 | H21: 0.7 | I21: 0.25 | J21: 0.05 | K21: 0.6 | L21: 0.3 | M21: 0.1 | N21: 0.5 | O21: 0.3 | P21: 0.2 | Q21: 0.6 | R21: 0.3 | S21: 0.1 | T21: 0.7 | U21: 0.25 | V21: 0.05 | W21: 0.6 | X21: 0.3 | Y21: 0.1 | Z21: 0.6 | AA21: 0.3 | AB21: 0.1 | AC21: 0.4 | AD21: 0.3 | AE21: 0.3 | AF21: 0.6 | AG21: 0.3 | AH21: 0.1 | AI21: 0.5 | AJ21: 0.3 | AK21: 0.2 | AL21: 0.4 | AM21: 0.3 | AN21: 0.3 | AO21: 0.4 | AP21: 0.3 | AQ21: 0.3 | AR21: 0.5 | AS21: 0.3 | AT21: 0.2 | AU21: 0.5 | AV21: 0.3 | AW21: 0.2 | AX21: 0.4 | AY21: 0.3 | AZ21: 0.3 | BA21: 0.5 | BB21: 0.3 | BC21: 0.2 | BD21: 0.5 | BE21: 0.3 | BF21: 0.2 | BG21: 0.5 | BH21: 0.3 | BI21: 0.2 | BJ21: 0.4 | BK21: 0.3 | BL21: 0.3 | BM21: 0.4 | BN21: 0.3 | BO21: 0.3 | BP21: 0.4 | BQ21: 0.3 | BR21: 0.3 | BS21: 0.5 | BT21: 0.3 | BU21: 0.2 | BV21: 0.5 | BW21: 0.3 | BX21: 0.2 | BY21: 0.4 | BZ21: 0.3 | CA21: 0.3 | CB21: 0.5 | CC21: 0.3 | CD21: 0.2 | CE21: 0.5 | CF21: 0.3 | CG21: 0.2 | CH21: 0.4 | CI21: 0.3 | CJ21: 0.3 | CK21: 0.4 | CL21: 0.3 | CM21: 0.3 | CN21: =ТрЗ_ОП!$R$28 -> 1 | CO21: =IF(CN21=1,IF($B$1=1,'Документы АСУТП'!CW45,IF($B$1=2,'Документы АСУТП'!CW46,IF($B$1=3,'Документы АСУТП'!CW47,'Документы АСУТП'!CW45))),0) -> 2.5 | CP21: =ТрЗ_ОП!$R$28 -> 1 | CQ21: =IF(CP21=1,IF($B$1=1,'Документы АСУТП'!CX45,IF($B$1=2,'Документы АСУТП'!CX46,IF($B$1=3,'Документы АСУТП'!CX47,'Документы АСУТП'!CX45))),0) -> 5 | CR21: =ТрЗ_ОП!$R$28 -> 1 | CS21: =IF(CR21=1,IF($B$1=1,'Документы АСУТП'!CY45,IF($B$1=2,'Документы АСУТП'!CY46,IF($B$1=3,'Документы АСУТП'!CY47,'Документы АСУТП'!CY45))),0) -> 0 | CT21: =ТрЗ_ОП!$R$28 -> 1 | CU21: =IF(CT21=1,IF($B$1=1,'Документы АСУТП'!CZ45,IF($B$1=2,'Документы АСУТП'!CZ46,IF($B$1=3,'Документы АСУТП'!CZ47,'Документы АСУТП'!CZ45))),0) -> 0 | CV21: =ТрЗ_ОП!$R$28 -> 1 | CW21: =IF(CV21=1,IF($B$1=1,'Документы АСУТП'!DA45,IF($B$1=2,'Документы АСУТП'!DA46,IF($B$1=3,'Документы АСУТП'!DA47,'Документы АСУТП'!DA45))),0) -> 0 | CX21: =ТрЗ_ОП!$R$28 -> 1 | CY21: =IF(CX21=1,IF($B$1=1,'Документы АСУТП'!DB45,IF($B$1=2,'Документы АСУТП'!DB46,IF($B$1=3,'Документы АСУТП'!DB47,'Документы АСУТП'!DB45))),0) -> 0 | CZ21: =ТрЗ_ОП!$R$28 -> 1 | DA21: =IF(CZ21=1,IF($B$1=1,'Документы АСУТП'!DC45,IF($B$1=2,'Документы АСУТП'!DC46,IF($B$1=3,'Документы АСУТП'!DC47,'Документы АСУТП'!DC45))),0) -> 0 | DB21: =ТрЗ_ОП!$R$28 -> 1 | DC21: =IF(DB21=1,IF($B$1=1,'Документы АСУТП'!DD45,IF($B$1=2,'Документы АСУТП'!DD46,IF($B$1=3,'Документы АСУТП'!DD47,'Документы АСУТП'!DD45))),0) -> 0 | DD21: =ТрЗ_ОП!$R$28 -> 1 | DE21: =IF(DD21=1,IF($B$1=1,'Документы АСУТП'!DF45,IF($B$1=2,'Документы АСУТП'!DF46,IF($B$1=3,'Документы АСУТП'!DF47,'Документы АСУТП'!DF45))),0) -> 0 | DF21: =ТрЗ_ОП!$R$28 -> 1 | DG21: =IF(DF21=1,IF($B$1=1,'Документы АСУТП'!DE45,IF($B$1=2,'Документы АСУТП'!DE46,IF($B$1=3,'Документы АСУТП'!DE47,'Документы АСУТП'!DE45))),0) -> 0 | DH21: =ТрЗ_ОП!$R$28 -> 1 | DI21: =IF(DH21=1,IF($B$1=1,'Документы АСУТП'!DG45,IF($B$1=2,'Документы АСУТП'!DG46,IF($B$1=3,'Документы АСУТП'!DG47,'Документы АСУТП'!DG45))),0) -> 0 | DJ21: =ТрЗ_ОП!$R$28 -> 1 | DK21: =IF(DJ21=1,IF($B$1=1,'Документы АСУТП'!DH45,IF($B$1=2,'Документы АСУТП'!DH46,IF($B$1=3,'Документы АСУТП'!DH47,'Документы АСУТП'!DH45))),0) -> 0 | DL21: =ТрЗ_ОП!$R$28 -> 1 | DM21: =IF(DL21=1,IF($B$1=1,'Документы АСУТП'!DI45,IF($B$1=2,'Документы АСУТП'!DI46,IF($B$1=3,'Документы АСУТП'!DI47,'Документы АСУТП'!DI45))),0) -> 0 | DN21: =ТрЗ_ОП!$R$28 -> 1 | DO21: =IF(DN21=1,IF($B$1=1,'Документы АСУТП'!DJ45,IF($B$1=2,'Документы АСУТП'!DJ46,IF($B$1=3,'Документы АСУТП'!DJ47,'Документы АСУТП'!DJ45))),0) -> #REF! | DP21: =ТрЗ_ОП!$R$28 -> 1 | DQ21: =IF(DP21=1,IF($B$1=1,'Документы АСУТП'!DK45,IF($B$1=2,'Документы АСУТП'!DK46,IF($B$1=3,'Документы АСУТП'!DK47,'Документы АСУТП'!DK45))),0) -> 0 | DR21: =ТрЗ_ОП!$R$28 -> 1 | DS21: =IF(DR21=1,IF($B$1=1,'Документы АСУТП'!DL45,IF($B$1=2,'Документы АСУТП'!DL46,IF($B$1=3,'Документы АСУТП'!DL47,'Документы АСУТП'!DL45))),0) -> 0 | DT21: =ТрЗ_ОП!$R$28 -> 1 | DU21: =IF(DT21=1,IF($B$1=1,'Документы АСУТП'!DM45,IF($B$1=2,'Документы АСУТП'!DM46,IF($B$1=3,'Документы АСУТП'!DM47,'Документы АСУТП'!DM45))),0) -> 0 | DV21: =ТрЗ_ОП!$R$28 -> 1 | DW21: =IF(DV21=1,IF($B$1=1,'Документы АСУТП'!DN45,IF($B$1=2,'Документы АСУТП'!DN46,IF($B$1=3,'Документы АСУТП'!DN47,'Документы АСУТП'!DN45))),0) -> 0 | DX21: =ТрЗ_ОП!$R$28 -> 1 | DY21: =IF(DX21=1,IF($B$1=1,'Документы АСУТП'!DO45,IF($B$1=2,'Документы АСУТП'!DO46,IF($B$1=3,'Документы АСУТП'!DO47,'Документы АСУТП'!DO45))),0) -> 0 | DZ21: =ТрЗ_ОП!$R$28 -> 1 | EA21: =IF(DZ21=1,IF($B$1=1,'Документы АСУТП'!DP45,IF($B$1=2,'Документы АСУТП'!DP46,IF($B$1=3,'Документы АСУТП'!DP47,'Документы АСУТП'!DP45))),0) -> 0 | EB21: =ТрЗ_ОП!$R$28 -> 1 | EC21: =IF(EB21=1,IF($B$1=1,'Документы АСУТП'!DQ45,IF($B$1=2,'Документы АСУТП'!DQ46,IF($B$1=3,'Документы АСУТП'!DQ47,'Документы АСУТП'!DQ45))),0) -> 0 | ED21: =ТрЗ_ОП!$R$28 -> 1 | EE21: =IF(ED21=1,IF($B$1=1,'Документы АСУТП'!DR45,IF($B$1=2,'Документы АСУТП'!DR46,IF($B$1=3,'Документы АСУТП'!DR47,'Документы АСУТП'!DR45))),0) -> 0 | EF21: =ТрЗ_ОП!$R$28 -> 1 | EG21: =IF(EF21=1,IF($B$1=1,'Документы АСУТП'!DS45,IF($B$1=2,'Документы АСУТП'!DS46,IF($B$1=3,'Документы АСУТП'!DS47,'Документы АСУТП'!DS45))),0) -> 0 | EH21: =ТрЗ_ОП!$R$28 -> 1 | EI21: =IF(EH21=1,IF($B$1=1,'Документы АСУТП'!DT45,IF($B$1=2,'Документы АСУТП'!DT46,IF($B$1=3,'Документы АСУТП'!DT47,'Документы АСУТП'!DT45))),0) -> 0 | EJ21: =ТрЗ_ОП!$R$28 -> 1 | EK21: =IF(EJ21=1,IF($B$1=1,'Документы АСУТП'!DU45,IF($B$1=2,'Документы АСУТП'!DU46,IF($B$1=3,'Документы АСУТП'!DU47,'Документы АСУТП'!DU45))),0) -> 0 | EL21: =ТрЗ_ОП!$R$28 -> 1 | EM21: =IF(EL21=1,IF($B$1=1,'Документы АСУТП'!DV45,IF($B$1=2,'Документы АСУТП'!DV46,IF($B$1=3,'Документы АСУТП'!DV47,'Документы АСУТП'!DV45))),0) -> 0 | EN21: =ТрЗ_ОП!$R$28 -> 1 | EO21: =IF(EN21=1,IF($B$1=1,'Документы АСУТП'!DW45,IF($B$1=2,'Документы АСУТП'!DW46,IF($B$1=3,'Документы АСУТП'!DW47,'Документы АСУТП'!DW45))),0) -> 0 | EP21: =ТрЗ_ОП!$R$28 -> 1 | EQ21: =IF(EP21=1,IF($B$1=1,'Документы АСУТП'!DX45,IF($B$1=2,'Документы АСУТП'!DX46,IF($B$1=3,'Документы АСУТП'!DX47,'Документы АСУТП'!DX45))),0) -> 0 | ER21: =ТрЗ_ОП!$R$28 -> 1 | ES21: =IF(ER21=1,IF($B$1=1,'Документы АСУТП'!DY45,IF($B$1=2,'Документы АСУТП'!DY46,IF($B$1=3,'Документы АСУТП'!DY47,'Документы АСУТП'!DY45))),0) -> 0 | ET21: =ТрЗ_ОП!$R$28 -> 1 | EU21: =IF(ET21=1,IF($B$1=1,'Документы АСУТП'!DZ45,IF($B$1=2,'Документы АСУТП'!DZ46,IF($B$1=3,'Документы АСУТП'!DZ47,'Документы АСУТП'!DZ45))),0) -> 0 | EV21: =B21*$CO21+E21*$CQ21+H21*$CS21+K21*$CU21+N21*$CW21+Q21*$CY21+T21*$DA21+W21*$DC21+Z21*$DE21+AC21*$DG21+AF21*$DI21+AI21*$DK21+AL21*$DM21+AO21*$DO21+AR21*$DQ21+AU21*$DS21+AX21*$DU21+BA21*$DW21+BD21*$DY21+BG21*$EA21+BJ21*$EC21+BM21*$EE21+BP21*$EG21+BS21*$EI21+BV21*$EK21+BY21*$EM21+CB21*$EO21+CE21*$EQ21+CH21*$ES21+$CK21*$EU21 -> #REF! | EW21: =C21*$CO21+F21*$CQ21+I21*$CS21+L21*$CU21+O21*$CW21+R21*$CY21+U21*$DA21+X21*$DC21+AA21*$DE21+AD21*$DG21+AG21*$DI21+AJ21*$DK21+AM21*$DM21+AP21*$DO21+AS21*$DQ21+AV21*$DS21+AY21*$DU21+BB21*$DW21+BE21*$DY21+BH21*$EA21+BK21*$EC21+BN21*$EE21+BQ21*$EG21+BT21*$EI21+BW21*$EK21+BZ21*$EM21+CC21*$EO21+CF21*$EQ21+CI21*$ES21+$CL21*$EU21 -> #REF! | EX21: =D21*$CO21+G21*$CQ21+J21*$CS21+M21*$CU21+P21*$CW21+S21*$CY21+V21*$DA21+Y21*$DC21+AB21*$DE21+AE21*$DG21+AH21*$DI21+AK21*$DK21+AN21*$DM21+AQ21*$DO21+AT21*$DQ21+AW21*$DS21+AZ21*$DU21+BC21*$DW21+BF21*$DY21+BI21*$EA21+BL21*$EC21+BO21*$EE21+BR21*$EG21+BU21*$EI21+BX21*$EK21+CA21*$EM21+CD21*$EO21+CG21*$EQ21+CJ21*$ES21+$CM21*$EU21 -> #REF! | EY21: =SUM(EV21:EX21)*0.05 -> #REF! | EZ21: =SUM(EV21:EY21) -> #REF!
